Workbook
Name _1988: #REF!
Name _CBD02: #REF!
Name _Fill: #REF!
Name _Key1: #REF!
Name _Key2: #REF!
Name _MD5: #REF!
Name _Sort: #REF!
Name _SPR1: #REF!
Name _T2: #REF!
Name adada: #REF!
Name adda: #REF!
Name ana: #REF!
Name as: #REF!
Name asd: #REF!
Name asfs: #REF!
Name CONT02092000.4: #REF!
Name dasdasd: #REF!
Name Devoluções: #REF!
Name DIFF: #REF!
Name EEEE: #REF!
Name egterqfg23gt432: #REF!
Name ertgqetq: #REF!
Name fdsfs: #REF!
Name ffefwef: #REF!
Name FREGT: #REF!
Name fsfsgf: #REF!
Name g45h42g4tg42: #REF!
Name Gastos.com.Pessoal.Comercial: #REF!
Name Gastos.com.Pessoal.Industrial: #REF!
Name GERAL: #REF!
Name gfwegweg: #REF!
Name grewgq: #REF!
Name imob: #REF!
Name imob1: #REF!
Name jhkj: #REF!
Name klkl: #REF!
Name LANCTOS: #REF!
Name LLOYD: #REF!
Name m: #REF!
Name n: #REF!
Name nikol: #REF!
Name njo: #REF!
Name nlkp: #REF!
Name nnn: #REF!
Name PDC: #REF!
Name pinco: #REF!
Name pippo: #REF!
Name Pró.Labore: #REF!
Name qertwqrt: #REF!
Name RIC: #REF!
Name RICL: #REF!
Name RICLASS: #REF!
Name RPC: #REF!
Name S: #REF!
Name sa: #REF!
Name sadaas: #REF!
Name SPR: #REF!
Name SS: #REF!
Name t34t34t: #REF!
Name t3gtt: #REF!

Sheet Claude Log
A1: Turn # | B1: Date | C1: User Request | D1: Action Taken | E1: Details | F1: Outcome
A2: 1 | B2: 46139 | C2: Atualizar fórmulas das colunas P e T para usar as mesmas fontes de busca de X e AB (RESUMO local em vez de arquivo externo Despesas 2026). | D2: Substituí todas as fórmulas VLOOKUP em P e T que apontavam para o arquivo externo '\\192.168.1.250\...\Despesas 2026 - Detalhado.xlsx' pela fonte local RESUMO!$A$3:$M$200. | E2: 246 fórmulas atualizadas (123 em P col 2=jan; 123 em T col 3=fev). Padrão: =IFERROR(VLOOKUP($I<row>,RESUMO!$A$3:$M$200,<col>,FALSE),""). Linhas 154/155 também padronizadas para usar $I em vez de I/M. | F2: Valores recalculados conferem com originais (ex: P13=52.378,26; T13=71.719,76). P12 e T12 totalizadores OK.

Sheet Acompanhamento Orçamento
I2: Karams 2026
I3: DRE (2) | J3: 112025 | L3: 122025 | N3: 12026 | R3: 22026 | V3: 32026 | Z3: 42026 | AD3: 52026 | AH3: 62026 | AJ3: 72026 | AL3: 82026 | AN3: 92026 | AP3: 102026 | AR3: 112026 | AT3: 122026 | AW3: -27948522
J4: Orçado | L4: Orçado | N4: Orçado | P4: Realizado | R4: Orçado | T4: Realizado | V4: Orçado | X4: Realizado | Z4: Orçado | AB4: Realizado | AD4: Orçado | AF4: Realizado | AH4: Orçado | AJ4: Orçado | AL4: Orçado | AN4: Orçado | AP4: Orçado | AR4: Orçado | AT4: Orçado
J5: 45962 | K5: AV | L5: 45992 | M5: AV | N5: 46023 | O5: AV | P5: 46023 | Q5: AV | R5: 46054 | S5: AV | T5: 46054 | U5: AV | V5: 46082 | W5: AV | X5: 46082 | Y5: AV | Z5: 46113 | AA5: AV | AB5: 46113 | AC5: AV | AD5: 46143 | AE5: AV | AF5: 46143 | AG5: AV | AH5: 46174 | AI5: AV | AJ5: 46204 | AK5: AV | AL5: 46235 | AM5: AV | AN5: 46266 | AO5: AV | AP5: 46296 | AQ5: AV | AR5: 46327 | AS5: AV | AT5: 46357 | AU5: AV | AW5: 2026 | AX5: AV | AY5: Média
I6: Min disponíveis | J6: 32793.329 | L6: 25993.761 | N6: 20560.304 | R6: 28477.134 | V6: 36152.605 | Z6: 32373.389 | AD6: 34928.872 | AH6: 28747.412 | AJ6: 28861.681 | AL6: 33440.249 | AN6: 38093.595 | AP6: 38900.537 | AR6: 33860.639 | AT6: 30093.75
I7: Min ocupados | J7: 52896 | L7: 33408 | N7: 58464 | R7: 55680 | V7: 64032 | Z7: 55680 | AD7: 58464 | AH7: 61248 | AJ7: 64032 | AL7: 61248 | AN7: 61248 | AP7: 58464 | AR7: 55680 | AT7: 33408
I8: % Capacidade Ocupada | J8: 0.61995859 | L8: 0.77806997 | N8: 0.3516746 | R8: 0.51144278 | V8: 0.56460215 | Z8: 0.58141862 | AD8: 0.59744239 | AH8: 0.46936082 | AJ8: 0.4507384 | AL8: 0.54598107 | AN8: 0.62195655 | AP8: 0.66537591 | AR8: 0.6081293 | AT8: 0.90079471
C9: Mês
B10: Tipo | C10: Ini | D10: Fin | E10: Premissa | F10: Valor | H10: Responsável | I10: Faturamento | J10: 2500000 | K10: 1 | L10: 2000000 | M10: 1 | N10: 1623447 | O10: 1 | P10: 1505834 | Q10: =P10/N10-1 -> -0.072446456 | R10: 2225988 | S10: 1 | T10: 2046711.4 | U10: =T10/R10-1 -> -0.080537983 | V10: 2800428.7 | W10: 1 | X10: 2626243.4 | Y10: =X10/V10-1 -> -0.062199519 | Z10: 2446309.8 | AA10: 1 | AB10: 2327111.8 | AC10: =AB10/Z10-1 -> -0.048725636 | AD10: 2562865.1 | AE10: 1 | AF10: 430572.21 | AG10: =AF10/AD10-1 -> -0.83199576 | AH10: 2217691.5 | AI10: 1 | AJ10: 2246169.5 | AK10: 1 | AL10: 2691085.6 | AM10: 1 | AN10: 2979407.8 | AO10: 1 | AP10: 3011564.5 | AQ10: 1 | AR10: 2738571.6 | AS10: 1 | AT10: 2456470.9 | AU10: 1 | AW10: 30000000 | AX10: 1 | AY10: 2500000
I12: Deduções | J12: -194500 | K12: -0.0778 | L12: -155600 | M12: -0.0778 | N12: -126304.17 | O12: -0.0778 | P12: =SUM(P13:P19) -> 136035.24 | Q12: =IFERROR((P12*-1)/N12-1,"") -> 0.077044696 | R12: -173181.87 | S12: -0.0778 | T12: =SUM(T13:T19) -> 115564.43 | U12: =IFERROR((T12*-1)/R12-1,"") -> -0.33269902 | V12: -217873.35 | W12: -0.0778 | X12: =SUM(X13:X19) -> 169337.99 | Y12: =IFERROR((X12*-1)/V12-1,"") -> -0.2227687 | Z12: -190322.91 | AA12: -0.0778 | AB12: =SUM(AB13:AB19) -> 140077.9 | AC12: =IFERROR((AB12*-1)/Z12-1,"") -> -0.26399873 | AD12: -199390.91 | AE12: -0.0778 | AF12: =SUM(AF13:AF19) -> 0 | AG12: =IFERROR((AF12*-1)/AD12-1,"") -> -1 | AH12: -172536.4 | AI12: -0.0778 | AJ12: -174751.98 | AK12: -0.0778 | AL12: -209366.46 | AM12: -0.0778 | AN12: -231797.93 | AO12: -0.0778 | AP12: -234299.72 | AQ12: -0.0778 | AR12: -213060.87 | AS12: -0.0778 | AT12: -191113.43 | AU12: -0.0778 | AW12: -2334000 | AX12: -0.0778 | AY12: -194500
B13: % | C13: 8 | D13: 9 | E13: % 8-9 de 2025 | F13: -0.0262 | H13: Letícia | I13: Simples Nacional | J13: -65500 | K13: -0.0262 | L13: -52400 | M13: -0.0262 | N13: =P$10*$F13 -> -39452.85 | O13: -0.0262 | P13: =IFERROR(VLOOKUP($I13,RESUMO!$A$3:$M$200,2,FALSE),"") -> 52378.26 | Q13: =IFERROR((P13*-1)/N13-1,"") -> 0.32761663 | R13: =T$10*$F13 -> -53623.839 | S13: -0.0262 | T13: =IFERROR(VLOOKUP($I13,RESUMO!$A$3:$M$200,3,FALSE),"") -> 71719.76 | U13: =IFERROR((T13*-1)/R13-1,"") -> 0.33746037 | V13: =X$10*$F13 -> -68807.577 | W13: -0.0262 | X13: =IFERROR(VLOOKUP($I13,RESUMO!$A$3:$M$200,4,FALSE),"") -> 81164.49 | Y13: =IFERROR((X13*-1)/V13-1,"") -> 0.17958651 | Z13: =AB$10*$F13 -> -60970.33 | AA13: -0.0262 | AB13: =IFERROR(VLOOKUP($I13,RESUMO!$A$3:$M$200,5,FALSE),"") -> 70210.77 | AC13: =IFERROR((AB13*-1)/Z13-1,"") -> 0.15155634 | AD13: -67147.067 | AE13: -0.0262 | AF13: =IFERROR(VLOOKUP($I13,RESUMO!$A$3:$M$200,6,FALSE),"") -> 0 | AG13: =IFERROR((AF13*-1)/AD13-1,"") -> -1 | AH13: -58103.516 | AI13: -0.0262 | AJ13: -58849.64 | AK13: -0.0262 | AL13: -70506.442 | AM13: -0.0262 | AN13: -78060.486 | AO13: -0.0262 | AP13: -78902.99 | AQ13: -0.0262 | AR13: -71750.576 | AS13: -0.0262 | AT13: -64359.537 | AU13: -0.0262 | AW13: -786000 | AX13: -0.0262 | AY13: -65500
B14: % | C14: 8 | D14: 9 | E14: % 8-9 de 2025 | F14: -0.02465 | H14: Letícia | I14: ICMS | J14: -61625 | K14: -0.02465 | L14: -49300 | M14: -0.02465 | N14: =P$10*$F14 -> -37118.808 | O14: -0.02465 | P14: =IFERROR(VLOOKUP($I14,RESUMO!$A$3:$M$200,2,FALSE),"") -> 60679.01 | Q14: =IFERROR((P14*-1)/N14-1,"") -> 0.63472412 | R14: =T$10*$F14 -> -50451.437 | S14: -0.02465 | T14: =IFERROR(VLOOKUP($I14,RESUMO!$A$3:$M$200,3,FALSE),"") -> 18975.32 | U14: =IFERROR((T14*-1)/R14-1,"") -> -0.6238894 | V14: =X$10*$F14 -> -64736.9 | W14: -0.02465 | X14: =IFERROR(VLOOKUP($I14,RESUMO!$A$3:$M$200,4,FALSE),"") -> 39057.06 | Y14: =IFERROR((X14*-1)/V14-1,"") -> -0.3966801 | Z14: =AB$10*$F14 -> -57363.307 | AA14: -0.02465 | AB14: =IFERROR(VLOOKUP($I14,RESUMO!$A$3:$M$200,5,FALSE),"") -> 24861.83 | AC14: =IFERROR((AB14*-1)/Z14-1,"") -> -0.56659001 | AD14: -63174.626 | AE14: -0.02465 | AF14: =IFERROR(VLOOKUP($I14,RESUMO!$A$3:$M$200,6,FALSE),"") -> 0 | AG14: =IFERROR((AF14*-1)/AD14-1,"") -> -1 | AH14: -54666.095 | AI14: -0.02465 | AJ14: -55368.077 | AK14: -0.02465 | AL14: -66335.259 | AM14: -0.02465 | AN14: -73442.403 | AO14: -0.02465 | AP14: -74235.065 | AQ14: -0.02465 | AR14: -67505.79 | AS14: -0.02465 | AT14: -60552.007 | AU14: -0.02465 | AW14: -739500 | AX14: -0.02465 | AY14: -61625
B15: % | C15: 8 | D15: 9 | E15: % 8-9 de 2025 | F15: -0.00275 | H15: Letícia | I15: PIS | J15: -6875 | K15: -0.00275 | L15: -5500 | M15: -0.00275 | N15: =P$10*$F15 -> -4141.0434 | O15: -0.00275 | P15: =IFERROR(VLOOKUP($I15,RESUMO!$A$3:$M$200,2,FALSE),"") -> 0 | Q15: =IFERROR((P15*-1)/N15-1,"") -> -1 | R15: =T$10*$F15 -> -5628.4564 | S15: -0.00275 | T15: =IFERROR(VLOOKUP($I15,RESUMO!$A$3:$M$200,3,FALSE),"") -> 496.96 | U15: =IFERROR((T15*-1)/R15-1,"") -> -0.91170581 | V15: =X$10*$F15 -> -7222.1693 | W15: -0.00275 | X15: =IFERROR(VLOOKUP($I15,RESUMO!$A$3:$M$200,4,FALSE),"") -> 3431.3 | Y15: =IFERROR((X15*-1)/V15-1,"") -> -0.52489344 | Z15: =AB$10*$F15 -> -6399.5575 | AA15: -0.00275 | AB15: =IFERROR(VLOOKUP($I15,RESUMO!$A$3:$M$200,5,FALSE),"") -> 2462.42 | AC15: =IFERROR((AB15*-1)/Z15-1,"") -> -0.61522027 | AD15: -7047.8791 | AE15: -0.00275 | AF15: =IFERROR(VLOOKUP($I15,RESUMO!$A$3:$M$200,6,FALSE),"") -> 0 | AG15: =IFERROR((AF15*-1)/AD15-1,"") -> -1 | AH15: -6098.6515 | AI15: -0.00275 | AJ15: -6176.966 | AK15: -0.00275 | AL15: -7400.4853 | AM15: -0.00275 | AN15: -8193.3716 | AO15: -0.00275 | AP15: -8281.8024 | AQ15: -0.00275 | AR15: -7531.0719 | AS15: -0.00275 | AT15: -6755.2949 | AU15: -0.00275 | AW15: -82500 | AX15: -0.00275 | AY15: -6875
B16: % | C16: 8 | D16: 9 | E16: % 8-9 de 2025 | F16: -0.0106 | H16: Letícia | I16: IPI | J16: -26500 | K16: -0.0106 | L16: -21200 | M16: -0.0106 | N16: =P$10*$F16 -> -15961.84 | O16: -0.0106 | P16: =IFERROR(VLOOKUP($I16,RESUMO!$A$3:$M$200,2,FALSE),"") -> 15874.39 | Q16: =IFERROR((P16*-1)/N16-1,"") -> -0.0054787034 | R16: =T$10*$F16 -> -21695.141 | S16: -0.0106 | T16: =IFERROR(VLOOKUP($I16,RESUMO!$A$3:$M$200,3,FALSE),"") -> 14761.73 | U16: =IFERROR((T16*-1)/R16-1,"") -> -0.31958359 | V16: =X$10*$F16 -> -27838.18 | W16: -0.0106 | X16: =IFERROR(VLOOKUP($I16,RESUMO!$A$3:$M$200,4,FALSE),"") -> 22197.7 | Y16: =IFERROR((X16*-1)/V16-1,"") -> -0.2026167 | Z16: =AB$10*$F16 -> -24667.385 | AA16: -0.0106 | AB16: =IFERROR(VLOOKUP($I16,RESUMO!$A$3:$M$200,5,FALSE),"") -> 20723.31 | AC16: =IFERROR((AB16*-1)/Z16-1,"") -> -0.15989029 | AD16: -27166.371 | AE16: -0.0106 | AF16: =IFERROR(VLOOKUP($I16,RESUMO!$A$3:$M$200,6,FALSE),"") -> 0 | AG16: =IFERROR((AF16*-1)/AD16-1,"") -> -1 | AH16: -23507.53 | AI16: -0.0106 | AJ16: -23809.396 | AK16: -0.0106 | AL16: -28525.507 | AM16: -0.0106 | AN16: -31581.723 | AO16: -0.0106 | AP16: -31922.584 | AQ16: -0.0106 | AR16: -29028.859 | AS16: -0.0106 | AT16: -26038.591 | AU16: -0.0106 | AW16: -318000 | AX16: -0.0106 | AY16: -26500
B17: % | C17: 8 | D17: 9 | E17: % 8-9 de 2025 | F17: -0.01275 | H17: Letícia | I17: COFINS | J17: -31875 | K17: -0.01275 | L17: -25500 | M17: -0.01275 | N17: =P$10*$F17 -> -19199.383 | O17: -0.01275 | P17: =IFERROR(VLOOKUP($I17,RESUMO!$A$3:$M$200,2,FALSE),"") -> 0 | Q17: =IFERROR((P17*-1)/N17-1,"") -> -1 | R17: =T$10*$F17 -> -26095.571 | S17: -0.01275 | T17: =IFERROR(VLOOKUP($I17,RESUMO!$A$3:$M$200,3,FALSE),"") -> 2460.61 | U17: =IFERROR((T17*-1)/R17-1,"") -> -0.90570775 | V17: =X$10*$F17 -> -33484.603 | W17: -0.01275 | X17: =IFERROR(VLOOKUP($I17,RESUMO!$A$3:$M$200,4,FALSE),"") -> 15906.25 | Y17: =IFERROR((X17*-1)/V17-1,"") -> -0.52496824 | Z17: =AB$10*$F17 -> -29670.676 | AA17: -0.01275 | AB17: =IFERROR(VLOOKUP($I17,RESUMO!$A$3:$M$200,5,FALSE),"") -> 11442.92 | AC17: =IFERROR((AB17*-1)/Z17-1,"") -> -0.61433571 | AD17: -32676.531 | AE17: -0.01275 | AF17: =IFERROR(VLOOKUP($I17,RESUMO!$A$3:$M$200,6,FALSE),"") -> 0 | AG17: =IFERROR((AF17*-1)/AD17-1,"") -> -1 | AH17: -28275.566 | AI17: -0.01275 | AJ17: -28638.66 | AK17: -0.01275 | AL17: -34311.341 | AM17: -0.01275 | AN17: -37987.45 | AO17: -0.01275 | AP17: -38397.447 | AQ17: -0.01275 | AR17: -34916.788 | AS17: -0.01275 | AT17: -31320.004 | AU17: -0.01275 | AW17: -382500 | AX17: -0.01275 | AY17: -31875
B18: % | C18: 8 | D18: 9 | E18: % 8-9 de 2025 | F18: -0.00085 | H18: Letícia | I18: Outros Impostos | J18: -2125 | K18: -0.00085 | L18: -1700 | M18: -0.00085 | N18: =P$10*$F18 -> -1279.9589 | O18: -0.00085 | P18: =IFERROR(VLOOKUP($I18,RESUMO!$A$3:$M$200,2,FALSE),"") -> 1443.62 | Q18: =IFERROR((P18*-1)/N18-1,"") -> 0.12786435 | R18: =T$10*$F18 -> -1739.7047 | S18: -0.00085 | T18: =IFERROR(VLOOKUP($I18,RESUMO!$A$3:$M$200,3,FALSE),"") -> 1490.09 | U18: =IFERROR((T18*-1)/R18-1,"") -> -0.14348108 | V18: =X$10*$F18 -> -2232.3069 | W18: -0.00085 | X18: =IFERROR(VLOOKUP($I18,RESUMO!$A$3:$M$200,4,FALSE),"") -> 1921.23 | Y18: =IFERROR((X18*-1)/V18-1,"") -> -0.13935221 | Z18: =AB$10*$F18 -> -1978.0451 | AA18: -0.00085 | AB18: =IFERROR(VLOOKUP($I18,RESUMO!$A$3:$M$200,5,FALSE),"") -> 4716.69 | AC18: =IFERROR((AB18*-1)/Z18-1,"") -> 1.384521 | AD18: -2178.4354 | AE18: -0.00085 | AF18: =IFERROR(VLOOKUP($I18,RESUMO!$A$3:$M$200,6,FALSE),"") -> 0 | AG18: =IFERROR((AF18*-1)/AD18-1,"") -> -1 | AH18: -1885.0377 | AI18: -0.00085 | AJ18: -1909.244 | AK18: -0.00085 | AL18: -2287.4227 | AM18: -0.00085 | AN18: -2532.4967 | AO18: -0.00085 | AP18: -2559.8298 | AQ18: -0.00085 | AR18: -2327.7859 | AS18: -0.00085 | AT18: -2088.0003 | AU18: -0.00085 | AW18: -25500 | AX18: -0.00085 | AY18: -2125
B19: % | C19: 8 | D19: 9 | E19: % 8-9 de 2025 | F19: -0.00085 | H19: Letícia | I19: Impostos a recolher | J19: -2125 | K19: -0.00085 | L19: -1700 | M19: -0.00085 | N19: 0 | O19: 0 | P19: =IFERROR(VLOOKUP($I19,RESUMO!$A$3:$M$200,2,FALSE),"") -> 5659.96 | Q19: =IFERROR((P19*-1)/N19-1,"") | R19: 0 | S19: -0.00085 | T19: =IFERROR(VLOOKUP($I19,RESUMO!$A$3:$M$200,3,FALSE),"") -> 5659.96 | U19: =IFERROR((T19*-1)/R19-1,"") | V19: 0 | W19: -0.00085 | X19: =IFERROR(VLOOKUP($I19,RESUMO!$A$3:$M$200,4,FALSE),"") -> 5659.96 | Y19: =IFERROR((X19*-1)/V19-1,"") | Z19: 0 | AA19: -0.00085 | AB19: =IFERROR(VLOOKUP($I19,RESUMO!$A$3:$M$200,5,FALSE),"") -> 5659.96 | AC19: =IFERROR((AB19*-1)/Z19-1,"") | AD19: 0 | AE19: -0.00085 | AF19: =IFERROR(VLOOKUP($I19,RESUMO!$A$3:$M$200,6,FALSE),"") -> 0 | AG19: =IFERROR((AF19*-1)/AD19-1,"") | AH19: -1885.0377 | AI19: -0.00085 | AJ19: 0 | AK19: -0.00085 | AL19: 0 | AM19: -0.00085 | AN19: 0 | AO19: -0.00085 | AP19: 0 | AQ19: -0.00085 | AR19: 0 | AS19: -0.00085 | AT19: 0 | AU19: -0.00085 | AW19: 0 | AX19: -0.00085 | AY19: -2125
I21: Receita Líquida | J21: 2305500 | K21: 0.9222 | L21: 1844400 | M21: 0.9222 | N21: 1497142.8 | O21: 0.9222 | P21: =P10-P12 -> 1369798.7 | Q21: =P21/N21-1 -> -0.08505805 | R21: 2052806.1 | S21: 0.9222 | T21: =T10-T12 -> 1931147 | U21: =T21/R21-1 -> -0.059264801 | V21: 2582555.4 | W21: 0.9222 | X21: =X10-X12 -> 2456905.4 | Y21: =X21/V21-1 -> -0.048653344 | Z21: 2255986.9 | AA21: 0.9222 | AB21: =AB10-AB12 -> 2187033.9 | AC21: =AB21/Z21-1 -> -0.030564449 | AD21: 2363474.2 | AE21: 0.9222 | AF21: =AF10-AF12 -> 430572.21 | AG21: =AF21/AD21-1 -> -0.81782234 | AH21: 2045155.1 | AI21: 0.9222 | AJ21: 2071417.5 | AK21: 0.9222 | AL21: 2481719.1 | AM21: 0.9222 | AN21: 2747609.9 | AO21: 0.9222 | AP21: 2777264.8 | AQ21: 0.9222 | AR21: 2525510.7 | AS21: 0.9222 | AT21: 2265357.5 | AU21: 0.9222 | AW21: 27666000 | AX21: 0.9222 | AY21: 2305500
I23: Custo | J23: -1407557 | K23: -0.56302279 | L23: -1214782 | M23: -0.60739099 | N23: =N24+N32+N46 -> -1024256.3 | O23: -0.65884626 | P23: =P24+P32+P46 -> 958701.04 | Q23: =IFERROR((P23*-1)/N23-1,"") -> -0.064002764 | R23: =R24+R32+R46 -> -1232791.6 | S23: -0.58486912 | T23: =T24+T32+T46 -> 1278370.6 | U23: =IFERROR((T23*-1)/R23-1,"") -> 0.036972168 | V23: =V24+V32+V46 -> -1456230.1 | W23: -0.54398359 | X23: =X24+X32+X46 -> 1479833.6 | Y23: =IFERROR((X23*-1)/V23-1,"") -> 0.016208596 | Z23: -1386856.7 | AA23: -0.56691786 | AB23: =AB24+AB32+AB46 -> 1173956.9 | AC23: =IFERROR((AB23*-1)/Z23-1,"") -> -0.15351252 | AD23: -1455440.7 | AE23: -0.56789594 | AF23: =AF24+AF32+AF46 -> 41622.25 | AG23: =IFERROR((AF23*-1)/AD23-1,"") -> -0.9714023 | AH23: -1322359 | AI23: -0.59627726 | AJ23: -1333338.7 | AK23: -0.59360556 | AL23: -1504876.1 | AM23: -0.55920782 | AN23: -1616038.7 | AO23: -0.54240266 | AP23: -1628436.7 | AQ23: -0.54072783 | AR23: -1523184.3 | AS23: -0.55619664 | AT23: -1414420.4 | AU23: -0.57579367 | AW23: -17079852 | AX23: -0.56932841 | AY23: -1423321
I24: CPV | J24: -963875 | K24: -0.38555 | L24: -771100 | M24: -0.38555 | N24: =SUM(N25:N31) -> -580574.29 | O24: -0.38555 | P24: =SUM(P25:P31) -> 572872.95 | Q24: =IFERROR((P24*-1)/N24-1,"") -> -0.01326504 | R24: =SUM(R25:R31) -> -789109.59 | S24: -0.38555 | T24: =SUM(T25:T31) -> 852739.33 | U24: =IFERROR((T24*-1)/R24-1,"") -> 0.080634856 | V24: =SUM(V25:V31) -> -1012548.1 | W24: -0.38555 | X24: =SUM(X25:X31) -> 1039300.8 | Y24: =IFERROR((X24*-1)/V24-1,"") -> 0.026421111 | Z24: =SUM(Z25:Z31) -> -897217.97 | AA24: -0.38555 | AB24: =SUM(AB25:AB31) -> 851006.53 | AC24: =IFERROR((AB24*-1)/Z24-1,"") -> -0.05150525 | AD24: -988112.66 | AE24: -0.38555 | AF24: =SUM(AF25:AF31) -> 2977.13 | AG24: =IFERROR((AF24*-1)/AD24-1,"") -> -0.99698705 | AH24: -855030.95 | AI24: -0.38555 | AJ24: -866010.63 | AK24: -0.38555 | AL24: -1037548 | AM24: -0.38555 | AN24: -1148710.7 | AO24: -0.38555 | AP24: -1161108.7 | AQ24: -0.38555 | AR24: -1055856.3 | AS24: -0.38555 | AT24: -947092.35 | AU24: -0.38555 | AW24: -11566500 | AX24: -0.38555 | AY24: -963875
B25: % | C25: 2 | D25: 9 | E25: % 2-9 de 2025 | F25: -0.08275 | H25: Mylena | I25: Entrada de Compras | J25: -206875 | K25: -0.08275 | L25: -165500 | M25: -0.08275 | N25: =P$10*$F25 -> -124607.76 | O25: -0.08275 | P25: 561916.11 | Q25: =IFERROR((P25*-1)/N25-1,"") -> 3.5094792 | R25: =T$10*$F25 -> -169365.37 | S25: -0.08275 | T25: 830151.62 | U25: =IFERROR((T25*-1)/R25-1,"") -> 3.9015428 | V25: =X$10*$F25 -> -217321.64 | W25: -0.08275 | X25: 1009819.9 | Y25: =IFERROR((X25*-1)/V25-1,"") -> 3.6466605 | Z25: =AB$10*$F25 -> -192568.5 | AA25: -0.08275 | AB25: 833834.01 | AC25: =IFERROR((AB25*-1)/Z25-1,"") -> 3.3300643 | AD25: -212077.09 | AE25: -0.08275 | AF25: =IFERROR(VLOOKUP($I25,RESUMO!$A$3:$M$200,6,FALSE),"") | AG25: =IFERROR((AF25*-1)/AD25-1,"") | AH25: -183513.97 | AI25: -0.08275 | AJ25: -185870.52 | AK25: -0.08275 | AL25: -222687.33 | AM25: -0.08275 | AN25: -246546 | AO25: -0.08275 | AP25: -249206.96 | AQ25: -0.08275 | AR25: -226616.8 | AS25: -0.08275 | AT25: -203272.97 | AU25: -0.08275 | AW25: -2482500 | AX25: -0.08275 | AY25: -206875
B26: % | C26: 2 | D26: 9 | E26: % 2-9 de 2025 | F26: 0 | H26: Mylena | I26: Compras | J26: -206875 | K26: -0.08275 | L26: -165500 | M26: -0.08275 | N26: =P$10*$F26 -> 0 | O26: 0 | P26: =IFERROR(VLOOKUP($I26,RESUMO!$A$3:$M$200,2,FALSE),"") -> 564 | Q26: =IFERROR((P26*-1)/N26-1,"") | R26: =T$10*$F26 -> 0 | S26: 0 | T26: =IFERROR(VLOOKUP($I26,RESUMO!$A$3:$M$200,3,FALSE),"") -> 987.68 | U26: =IFERROR((T26*-1)/R26-1,"") | V26: =X$10*$F26 -> 0 | W26: 0 | X26: =IFERROR(VLOOKUP($I26,RESUMO!$A$3:$M$200,4,FALSE),"") -> 1534.3 | Y26: =IFERROR((X26*-1)/V26-1,"") | Z26: =AB$10*$F26 -> 0 | AA26: 0 | AB26: =IFERROR(VLOOKUP($I26,RESUMO!$A$3:$M$200,5,FALSE),"") -> 9.5 | AC26: =IFERROR((AB26*-1)/Z26-1,"") | AD26: 0 | AE26: 0 | AF26: =IFERROR(VLOOKUP($I26,RESUMO!$A$3:$M$200,6,FALSE),"") -> 0 | AG26: =IFERROR((AF26*-1)/AD26-1,"") | AH26: 0 | AI26: 0 | AJ26: 0 | AK26: 0 | AL26: 0 | AM26: 0 | AN26: 0 | AO26: 0 | AP26: 0 | AQ26: 0 | AR26: 0 | AS26: 0 | AT26: 0 | AU26: 0 | AW26: -2482500 | AX26: -0.08275 | AY26: -206875
B27: % | C27: 2 | D27: 9 | E27: % 2-9 de 2025 | F27: -0.1049125 | H27: Mylena | I27: Compras - Espuma | J27: -262281.25 | K27: -0.1049125 | L27: -209825 | M27: -0.1049125 | N27: =P$10*$F27 -> -157980.81 | O27: -0.1049125 | P27: =IFERROR(VLOOKUP($I27,RESUMO!$A$3:$M$200,2,FALSE),"") | Q27: =IFERROR((P27*-1)/N27-1,"") | R27: =T$10*$F27 -> -214725.61 | S27: -0.1049125 | T27: =IFERROR(VLOOKUP($I27,RESUMO!$A$3:$M$200,3,FALSE),"") | U27: =IFERROR((T27*-1)/R27-1,"") | V27: =X$10*$F27 -> -275525.76 | W27: -0.1049125 | X27: =IFERROR(VLOOKUP($I27,RESUMO!$A$3:$M$200,4,FALSE),"") | Y27: =IFERROR((X27*-1)/V27-1,"") | Z27: =AB$10*$F27 -> -244143.12 | AA27: -0.1049125 | AB27: =IFERROR(VLOOKUP($I27,RESUMO!$A$3:$M$200,5,FALSE),"") | AC27: =IFERROR((AB27*-1)/Z27-1,"") | AD27: -268876.59 | AE27: -0.1049125 | AF27: =IFERROR(VLOOKUP($I27,RESUMO!$A$3:$M$200,6,FALSE),"") | AG27: =IFERROR((AF27*-1)/AD27-1,"") | AH27: -232663.56 | AI27: -0.1049125 | AJ27: -235651.25 | AK27: -0.1049125 | AL27: -282328.52 | AM27: -0.1049125 | AN27: -312577.13 | AO27: -0.1049125 | AP27: -315950.76 | AQ27: -0.1049125 | AR27: -287310.39 | AS27: -0.1049125 | AT27: -257714.5 | AU27: -0.1049125 | AW27: -3147375 | AX27: -0.1049125 | AY27: -262281.25
B28: % | C28: 2 | D28: 9 | E28: % 2-9 de 2025 | F28: -0.074375 | H28: Mylena | I28: Compras - Tecido | J28: -185937.5 | K28: -0.074375 | L28: -148750 | M28: -0.074375 | N28: =P$10*$F28 -> -111996.4 | O28: -0.074375 | P28: =IFERROR(VLOOKUP($I28,RESUMO!$A$3:$M$200,2,FALSE),"") | Q28: =IFERROR((P28*-1)/N28-1,"") | R28: =T$10*$F28 -> -152224.16 | S28: -0.074375 | T28: =IFERROR(VLOOKUP($I28,RESUMO!$A$3:$M$200,3,FALSE),"") | U28: =IFERROR((T28*-1)/R28-1,"") | V28: =X$10*$F28 -> -195326.85 | W28: -0.074375 | X28: =IFERROR(VLOOKUP($I28,RESUMO!$A$3:$M$200,4,FALSE),"") | Y28: =IFERROR((X28*-1)/V28-1,"") | Z28: =AB$10*$F28 -> -173078.94 | AA28: -0.074375 | AB28: =IFERROR(VLOOKUP($I28,RESUMO!$A$3:$M$200,5,FALSE),"") | AC28: =IFERROR((AB28*-1)/Z28-1,"") | AD28: -190613.1 | AE28: -0.074375 | AF28: =IFERROR(VLOOKUP($I28,RESUMO!$A$3:$M$200,6,FALSE),"") | AG28: =IFERROR((AF28*-1)/AD28-1,"") | AH28: -164940.8 | AI28: -0.074375 | AJ28: -167058.85 | AK28: -0.074375 | AL28: -200149.49 | AM28: -0.074375 | AN28: -221593.46 | AO28: -0.074375 | AP28: -223985.11 | AQ28: -0.074375 | AR28: -203681.26 | AS28: -0.074375 | AT28: -182700.02 | AU28: -0.074375 | AW28: -2231250 | AX28: -0.074375 | AY28: -185937.5
B29: % | C29: 2 | D29: 9 | E29: % 2-9 de 2025 | F29: -0.0567375 | H29: Mylena | I29: Compras - Madeira | J29: -141843.75 | K29: -0.0567375 | L29: -113475 | M29: -0.0567375 | N29: =P$10*$F29 -> -85437.255 | O29: -0.0567375 | P29: =IFERROR(VLOOKUP($I29,RESUMO!$A$3:$M$200,2,FALSE),"") | Q29: =IFERROR((P29*-1)/N29-1,"") | R29: =T$10*$F29 -> -116125.29 | S29: -0.0567375 | T29: =IFERROR(VLOOKUP($I29,RESUMO!$A$3:$M$200,3,FALSE),"") | U29: =IFERROR((T29*-1)/R29-1,"") | V29: =X$10*$F29 -> -149006.48 | W29: -0.0567375 | X29: =IFERROR(VLOOKUP($I29,RESUMO!$A$3:$M$200,4,FALSE),"") | Y29: =IFERROR((X29*-1)/V29-1,"") | Z29: =AB$10*$F29 -> -132034.51 | AA29: -0.0567375 | AB29: =IFERROR(VLOOKUP($I29,RESUMO!$A$3:$M$200,5,FALSE),"") | AC29: =IFERROR((AB29*-1)/Z29-1,"") | AD29: -145410.56 | AE29: -0.0567375 | AF29: =IFERROR(VLOOKUP($I29,RESUMO!$A$3:$M$200,6,FALSE),"") | AG29: =IFERROR((AF29*-1)/AD29-1,"") | AH29: -125826.27 | AI29: -0.0567375 | AJ29: -127442.04 | AK29: -0.0567375 | AL29: -152685.47 | AM29: -0.0567375 | AN29: -169044.15 | AO29: -0.0567375 | AP29: -170868.64 | AQ29: -0.0567375 | AR29: -155379.71 | AS29: -0.0567375 | AT29: -139374.02 | AU29: -0.0567375 | AW29: -1702125 | AX29: -0.0567375 | AY29: -141843.75
B30: % | C30: 2 | D30: 9 | E30: % 2-9 de 2025 | F30: -0.06165 | H30: Mylena | I30: Compras - Pés/Mecanismos/Bases | J30: -154125 | K30: -0.06165 | L30: -123300 | M30: -0.06165 | N30: =P$10*$F30 -> -92834.665 | O30: -0.06165 | P30: =IFERROR(VLOOKUP($I30,RESUMO!$A$3:$M$200,2,FALSE),"") -> 1 | Q30: =IFERROR((P30*-1)/N30-1,"") -> -0.99998923 | R30: =T$10*$F30 -> -126179.76 | S30: -0.06165 | T30: =IFERROR(VLOOKUP($I30,RESUMO!$A$3:$M$200,3,FALSE),"") -> 2516.68 | U30: =IFERROR((T30*-1)/R30-1,"") -> -0.9800548 | V30: =X$10*$F30 -> -161907.91 | W30: -0.06165 | X30: =IFERROR(VLOOKUP($I30,RESUMO!$A$3:$M$200,4,FALSE),"") -> 12217.75 | Y30: =IFERROR((X30*-1)/V30-1,"") -> -0.92453889 | Z30: =AB$10*$F30 -> -143466.44 | AA30: -0.06165 | AB30: =IFERROR(VLOOKUP($I30,RESUMO!$A$3:$M$200,5,FALSE),"") -> 962.38 | AC30: =IFERROR((AB30*-1)/Z30-1,"") -> -0.99329195 | AD30: -158000.64 | AE30: -0.06165 | AF30: =IFERROR(VLOOKUP($I30,RESUMO!$A$3:$M$200,6,FALSE),"") -> 67.11 | AG30: =IFERROR((AF30*-1)/AD30-1,"") -> -0.99957525 | AH30: -136720.68 | AI30: -0.06165 | AJ30: -138476.35 | AK30: -0.06165 | AL30: -165905.43 | AM30: -0.06165 | AN30: -183680.49 | AO30: -0.06165 | AP30: -185662.95 | AQ30: -0.06165 | AR30: -168832.94 | AS30: -0.06165 | AT30: -151441.43 | AU30: -0.06165 | AW30: -1849500 | AX30: -0.06165 | AY30: -154125
B31: % | C31: 2 | D31: 9 | E31: % 2-9 de 2025 | F31: -0.005125 | H31: Mylena | I31: Frete sobre compras | J31: -12812.5 | K31: -0.005125 | L31: -10250 | M31: -0.005125 | N31: =P$10*$F31 -> -7717.3991 | O31: -0.005125 | P31: =IFERROR(VLOOKUP($I31,RESUMO!$A$3:$M$200,2,FALSE),"") -> 10391.84 | Q31: =IFERROR((P31*-1)/N31-1,"") -> 0.34654691 | R31: =T$10*$F31 -> -10489.396 | S31: -0.005125 | T31: =IFERROR(VLOOKUP($I31,RESUMO!$A$3:$M$200,3,FALSE),"") -> 19083.35 | U31: =IFERROR((T31*-1)/R31-1,"") -> 0.81929921 | V31: =X$10*$F31 -> -13459.497 | W31: -0.005125 | X31: =IFERROR(VLOOKUP($I31,RESUMO!$A$3:$M$200,4,FALSE),"") -> 15728.86 | Y31: =IFERROR((X31*-1)/V31-1,"") -> 0.16860678 | Z31: =AB$10*$F31 -> -11926.448 | AA31: -0.005125 | AB31: =IFERROR(VLOOKUP($I31,RESUMO!$A$3:$M$200,5,FALSE),"") -> 16200.64 | AC31: =IFERROR((AB31*-1)/Z31-1,"") -> 0.35837928 | AD31: -13134.684 | AE31: -0.005125 | AF31: =IFERROR(VLOOKUP($I31,RESUMO!$A$3:$M$200,6,FALSE),"") -> 2910.02 | AG31: =IFERROR((AF31*-1)/AD31-1,"") -> -0.77844766 | AH31: -11365.669 | AI31: -0.005125 | AJ31: -11511.618 | AK31: -0.005125 | AL31: -13791.814 | AM31: -0.005125 | AN31: -15269.465 | AO31: -0.005125 | AP31: -15434.268 | AQ31: -0.005125 | AR31: -14035.179 | AS31: -0.005125 | AT31: -12589.413 | AU31: -0.005125 | AW31: -153750 | AX31: -0.005125 | AY31: -12812.5
I32: Custos Diretos | J32: -349495.63 | K32: -0.13979825 | L32: -349495.63 | M32: -0.17474782 | N32: -349495.63 | O32: -0.21527998 | P32: =SUM(P33:P45) -> 298438.85 | Q32: =(P32*-1)/N32-1 -> -0.14608704 | R32: -349495.63 | S32: -0.15700697 | T32: =SUM(T33:T45) -> 359850.92 | U32: =(T32*-1)/R32-1 -> 0.029629237 | V32: -349495.63 | W32: -0.12480076 | X32: =SUM(X33:X45) -> 333045.58 | Y32: =(X32*-1)/V32-1 -> -0.047067973 | Z32: -349495.63 | AA32: -0.14286646 | AB32: =SUM(AB33:AB45) -> 255313.36 | AC32: =(AB32*-1)/Z32-1 -> -0.26948054 | AD32: -369175.1 | AE32: -0.14404781 | AF32: =SUM(AF33:AF45) -> 21727.68 | AG32: =(AF32*-1)/AD32-1 -> -0.94114533 | AH32: -369175.1 | AI32: -0.1664682 | AJ32: -369175.1 | AK32: -0.16435764 | AL32: -369175.1 | AM32: -0.13718445 | AN32: -369175.1 | AO32: -0.12390888 | AP32: -369175.1 | AQ32: -0.12258582 | AR32: -369175.1 | AS32: -0.13480571 | AT32: -369175.1 | AU32: -0.15028678 | AW32: -4351383.3 | AX32: -0.14504611 | AY32: -362615.28
E33: Diretoria - 25.11.25 | F33: -4320 | H33: Rafael | I33: Energia Eletrica (Prod) | J33: -4320 | K33: -0.001728 | L33: -4320 | M33: -0.00216 | N33: -4320 | O33: -0.0026610047 | P33: =IFERROR(VLOOKUP($I33,RESUMO!$A$3:$M$200,2,FALSE),"") -> 4543.34 | Q33: =IFERROR((P33*-1)/N33-1,"") -> 0.051699074 | R33: -4320 | S33: -0.0019407113 | T33: =IFERROR(VLOOKUP($I33,RESUMO!$A$3:$M$200,3,FALSE),"") -> 6905.72 | U33: =IFERROR((T33*-1)/R33-1,"") -> 0.5985463 | V33: -4320 | W33: -0.0015426209 | X33: =IFERROR(VLOOKUP($I33,RESUMO!$A$3:$M$200,4,FALSE),"") -> 8155.15 | Y33: =IFERROR((X33*-1)/V33-1,"") -> 0.8877662 | Z33: -4320 | AA33: -0.0017659251 | AB33: =IFERROR(VLOOKUP($I33,RESUMO!$A$3:$M$200,5,FALSE),"") -> 8554.02 | AC33: =IFERROR((AB33*-1)/Z33-1,"") -> 0.98009722 | AD33: -4320 | AE33: -0.0016856135 | AF33: =IFERROR(VLOOKUP($I33,RESUMO!$A$3:$M$200,6,FALSE),"") -> 0 | AG33: =IFERROR((AF33*-1)/AD33-1,"") -> -1 | AH33: -4320 | AI33: -0.0019479716 | AJ33: -4320 | AK33: -0.0019232743 | AL33: -4320 | AM33: -0.0016053001 | AN33: -4320 | AO33: -0.0014499525 | AP33: -4320 | AQ33: -0.0014344704 | AR33: -4320 | AS33: -0.0015774647 | AT33: -4320 | AU33: -0.0017586205 | AW33: -51840 | AX33: -0.001728 | AY33: -4320
B34: $ | C34: 1 | D34: 9 | E34: $ 1-9 de 2025 | F34: -19046.924 | H34: Mylena | I34: Material de Expediente (Prod) | J34: -19046.924 | K34: -0.0076187698 | L34: -19046.924 | M34: -0.0095234622 | N34: -19046.924 | O34: -0.011732397 | P34: =IFERROR(VLOOKUP($I34,RESUMO!$A$3:$M$200,2,FALSE),"") -> 14950.47 | Q34: =IFERROR((P34*-1)/N34-1,"") -> -0.2150717 | R34: -19046.924 | S34: -0.0085566159 | T34: =IFERROR(VLOOKUP($I34,RESUMO!$A$3:$M$200,3,FALSE),"") -> 21105.59 | U34: =IFERROR((T34*-1)/R34-1,"") -> 0.10808388 | V34: -19046.924 | W34: -0.0068014316 | X34: =IFERROR(VLOOKUP($I34,RESUMO!$A$3:$M$200,4,FALSE),"") -> 9382.13 | Y34: =IFERROR((X34*-1)/V34-1,"") -> -0.50742021 | Z34: -19046.924 | AA34: -0.007785982 | AB34: =IFERROR(VLOOKUP($I34,RESUMO!$A$3:$M$200,5,FALSE),"") -> 16740.67 | AC34: =IFERROR((AB34*-1)/Z34-1,"") -> -0.12108277 | AD34: -19046.924 | AE34: -0.0074318871 | AF34: =IFERROR(VLOOKUP($I34,RESUMO!$A$3:$M$200,6,FALSE),"") -> 5750.17 | AG34: =IFERROR((AF34*-1)/AD34-1,"") -> -0.69810507 | AH34: -19046.924 | AI34: -0.0085886268 | AJ34: -19046.924 | AK34: -0.0084797362 | AL34: -19046.924 | AM34: -0.0070777847 | AN34: -19046.924 | AO34: -0.0063928557 | AP34: -19046.924 | AQ34: -0.0063245946 | AR34: -19046.924 | AS34: -0.0069550581 | AT34: -19046.924 | AU34: -0.0077537758 | AW34: -228563.09 | AX34: -0.0076187698 | AY34: -19046.924
E35: Diretoria - 25.11.25 | F35: -2194.03 | H35: Rafael | I35: EPIs/Uniformes (Prod) | J35: -2194.03 | K35: -0.000877612 | L35: -2194.03 | M35: -0.001097015 | N35: -2194.03 | O35: -0.0013514639 | P35: =IFERROR(VLOOKUP($I35,RESUMO!$A$3:$M$200,2,FALSE),"") -> 1899.2 | Q35: =IFERROR((P35*-1)/N35-1,"") -> -0.13437829 | R35: -2194.03 | S35: -0.00098564322 | T35: =IFERROR(VLOOKUP($I35,RESUMO!$A$3:$M$200,3,FALSE),"") -> 1694.16 | U35: =IFERROR((T35*-1)/R35-1,"") -> -0.22783189 | V35: -2194.03 | W35: -0.00078346218 | X35: =IFERROR(VLOOKUP($I35,RESUMO!$A$3:$M$200,4,FALSE),"") -> 0 | Y35: =IFERROR((X35*-1)/V35-1,"") -> -1 | Z35: -2194.03 | AA35: -0.00089687331 | AB35: =IFERROR(VLOOKUP($I35,RESUMO!$A$3:$M$200,5,FALSE),"") -> 1307.92 | AC35: =IFERROR((AB35*-1)/Z35-1,"") -> -0.40387324 | AD35: -2194.03 | AE35: -0.00085608484 | AF35: =IFERROR(VLOOKUP($I35,RESUMO!$A$3:$M$200,6,FALSE),"") -> 9103.6 | AG35: =IFERROR((AF35*-1)/AD35-1,"") -> 3.1492596 | AH35: -2194.03 | AI35: -0.00098933059 | AJ35: -2194.03 | AK35: -0.00097678739 | AL35: -2194.03 | AM35: -0.00081529551 | AN35: -2194.03 | AO35: -0.00073639801 | AP35: -2194.03 | AQ35: -0.00072853495 | AR35: -2194.03 | AS35: -0.00080115853 | AT35: -2194.03 | AU35: -0.00089316345 | AW35: -26328.36 | AX35: -0.000877612 | AY35: -2194.03
E36: Salarios e Ordenados MOD | F36: AUX | H36: Rafael | I36: Salarios e Ordenados MOD | J36: -208162.69 | K36: -0.083265075 | L36: -208162.69 | M36: -0.10408134 | N36: -208162.69 | O36: -0.12822266 | P36: =IFERROR(VLOOKUP($I36,RESUMO!$A$3:$M$200,2,FALSE),"") -> 185861.81 | Q36: =IFERROR((P36*-1)/N36-1,"") -> -0.10713196 | R36: -208162.69 | S36: -0.093514738 | T36: =IFERROR(VLOOKUP($I36,RESUMO!$A$3:$M$200,3,FALSE),"") -> 205896.33 | U36: =IFERROR((T36*-1)/R36-1,"") -> -0.01088743 | V36: -208162.69 | W36: -0.074332435 | X36: =IFERROR(VLOOKUP($I36,RESUMO!$A$3:$M$200,4,FALSE),"") -> 218151.71 | Y36: =IFERROR((X36*-1)/V36-1,"") -> 0.047986618 | Z36: -208162.69 | AA36: -0.085092527 | AB36: =IFERROR(VLOOKUP($I36,RESUMO!$A$3:$M$200,5,FALSE),"") -> 202715.75 | AC36: =IFERROR((AB36*-1)/Z36-1,"") -> -0.026166729 | AD36: -221693.26 | AE36: -0.086502117 | AF36: =IFERROR(VLOOKUP($I36,RESUMO!$A$3:$M$200,6,FALSE),"") -> 3820.7 | AG36: =IFERROR((AF36*-1)/AD36-1,"") -> -0.98276583 | AH36: -221693.26 | AI36: -0.099965782 | AJ36: -221693.26 | AK36: -0.098698369 | AL36: -221693.26 | AM36: -0.082380606 | AN36: -221693.26 | AO36: -0.074408498 | AP36: -221693.26 | AQ36: -0.073613984 | AR36: -221693.26 | AS36: -0.080952151 | AT36: -221693.26 | AU36: -0.090248683 | AW36: -2606196.8 | AX36: -0.086873228 | AY36: -217183.07
B37: $ | C37: 1 | D37: 9 | E37: $ 1-9 de 2025 | F37: -122.7 | H37: Rafael | I37: Horas Extras MOD | J37: -122.7 | K37: -4.908e-05 | L37: -122.7 | M37: -6.135e-05 | N37: -122.7 | O37: -7.5579925e-05 | P37: =IFERROR(VLOOKUP($I37,RESUMO!$A$3:$M$200,2,FALSE),"") | Q37: =IFERROR((P37*-1)/N37-1,"") | R37: -122.7 | S37: -5.5121591e-05 | T37: =IFERROR(VLOOKUP($I37,RESUMO!$A$3:$M$200,3,FALSE),"") | U37: =IFERROR((T37*-1)/R37-1,"") | V37: -122.7 | W37: -4.381472e-05 | X37: =IFERROR(VLOOKUP($I37,RESUMO!$A$3:$M$200,4,FALSE),"") | Y37: =IFERROR((X37*-1)/V37-1,"") | Z37: -122.7 | AA37: -5.0157179e-05 | AB37: =IFERROR(VLOOKUP($I37,RESUMO!$A$3:$M$200,5,FALSE),"") | AC37: =IFERROR((AB37*-1)/Z37-1,"") | AD37: -122.7 | AE37: -4.7876105e-05 | AF37: =IFERROR(VLOOKUP($I37,RESUMO!$A$3:$M$200,6,FALSE),"") | AG37: =IFERROR((AF37*-1)/AD37-1,"") | AH37: -122.7 | AI37: -5.5327804e-05 | AJ37: -122.7 | AK37: -5.4626333e-05 | AL37: -122.7 | AM37: -4.5594983e-05 | AN37: -122.7 | AO37: -4.118268e-05 | AP37: -122.7 | AQ37: -4.0742943e-05 | AR37: -122.7 | AS37: -4.4804379e-05 | AT37: -122.7 | AU37: -4.9949707e-05 | AW37: -1472.4 | AX37: -4.908e-05 | AY37: -122.7
E38: Provisão | F38: 0.083333333 | H38: Rafael | I38: 13° Salario MOD | J38: -17346.891 | K38: -0.0069387562 | L38: -17346.891 | M38: -0.0086734453 | N38: -17346.891 | O38: -0.010685222 | P38: =IFERROR(VLOOKUP($I38,RESUMO!$A$3:$M$200,2,FALSE),"") | Q38: =IFERROR((P38*-1)/N38-1,"") | R38: -17346.891 | S38: -0.0077928949 | T38: =IFERROR(VLOOKUP($I38,RESUMO!$A$3:$M$200,3,FALSE),"") | U38: =IFERROR((T38*-1)/R38-1,"") | V38: -17346.891 | W38: -0.0061943696 | X38: =IFERROR(VLOOKUP($I38,RESUMO!$A$3:$M$200,4,FALSE),"") | Y38: =IFERROR((X38*-1)/V38-1,"") | Z38: -17346.891 | AA38: -0.007091044 | AB38: =IFERROR(VLOOKUP($I38,RESUMO!$A$3:$M$200,5,FALSE),"") | AC38: =IFERROR((AB38*-1)/Z38-1,"") | AD38: -18474.438 | AE38: -0.0072085098 | AF38: =IFERROR(VLOOKUP($I38,RESUMO!$A$3:$M$200,6,FALSE),"") | AG38: =IFERROR((AF38*-1)/AD38-1,"") | AH38: -18474.438 | AI38: -0.0083304818 | AJ38: -18474.438 | AK38: -0.0082248641 | AL38: -18474.438 | AM38: -0.0068650505 | AN38: -18474.438 | AO38: -0.0062007081 | AP38: -18474.438 | AQ38: -0.0061344987 | AR38: -18474.438 | AS38: -0.0067460126 | AT38: -18474.438 | AU38: -0.0075207236 | AW38: -217183.07 | AX38: -0.0072394357 | AY38: -18098.589
B39: $ | C39: 1 | D39: 9 | E39: $ 1-9 de 2025 | F39: -7819.1 | H39: Rafael | I39: Gratificacoes MOD | J39: -7819.1 | K39: -0.00312764 | L39: -7819.1 | M39: -0.00390955 | N39: -7819.1 | O39: -0.0048163569 | P39: =IFERROR(VLOOKUP($I39,RESUMO!$A$3:$M$200,2,FALSE),"") -> 6816.55 | Q39: =IFERROR((P39*-1)/N39-1,"") -> -0.12821808 | R39: -7819.1 | S39: -0.0035126425 | T39: =IFERROR(VLOOKUP($I39,RESUMO!$A$3:$M$200,3,FALSE),"") -> 9992.25 | U39: =IFERROR((T39*-1)/R39-1,"") -> 0.27792841 | V39: -7819.1 | W39: -0.0027921082 | X39: =IFERROR(VLOOKUP($I39,RESUMO!$A$3:$M$200,4,FALSE),"") -> 8223.1 | Y39: =IFERROR((X39*-1)/V39-1,"") -> 0.051668351 | Z39: -7819.1 | AA39: -0.0031962836 | AB39: =IFERROR(VLOOKUP($I39,RESUMO!$A$3:$M$200,5,FALSE),"") -> 1988.1 | AC39: =IFERROR((AB39*-1)/Z39-1,"") -> -0.745738 | AD39: -7819.1 | AE39: -0.0030509214 | AF39: =IFERROR(VLOOKUP($I39,RESUMO!$A$3:$M$200,6,FALSE),"") -> 0 | AG39: =IFERROR((AF39*-1)/AD39-1,"") -> -1 | AH39: -7819.1 | AI39: -0.0035257835 | AJ39: -7819.1 | AK39: -0.003481082 | AL39: -7819.1 | AM39: -0.0029055561 | AN39: -7819.1 | AO39: -0.0026243806 | AP39: -7819.1 | AQ39: -0.0025963581 | AR39: -7819.1 | AS39: -0.0028551746 | AT39: -7819.1 | AU39: -0.0031830624 | AW39: -93829.2 | AX39: -0.00312764 | AY39: -7819.1
E40: Diretoria - 25.11.25 | F40: -10000 | H40: Rafael | I40: Rescisões MOD | J40: -10000 | K40: -0.004 | L40: -10000 | M40: -0.005 | N40: -10000 | O40: -0.0061597331 | P40: =IFERROR(VLOOKUP($I40,RESUMO!$A$3:$M$200,2,FALSE),"") -> 0 | Q40: =IFERROR((P40*-1)/N40-1,"") -> -1 | R40: -10000 | S40: -0.0044923872 | T40: =IFERROR(VLOOKUP($I40,RESUMO!$A$3:$M$200,3,FALSE),"") -> 30936.21 | U40: =IFERROR((T40*-1)/R40-1,"") -> 2.093621 | V40: -10000 | W40: -0.0035708818 | X40: =IFERROR(VLOOKUP($I40,RESUMO!$A$3:$M$200,4,FALSE),"") -> 394.44 | Y40: =IFERROR((X40*-1)/V40-1,"") -> -0.960556 | Z40: -10000 | AA40: -0.0040877896 | AB40: =IFERROR(VLOOKUP($I40,RESUMO!$A$3:$M$200,5,FALSE),"") -> 0 | AC40: =IFERROR((AB40*-1)/Z40-1,"") -> -1 | AD40: -10000 | AE40: -0.003901883 | AF40: =IFERROR(VLOOKUP($I40,RESUMO!$A$3:$M$200,6,FALSE),"") -> 1694.75 | AG40: =IFERROR((AF40*-1)/AD40-1,"") -> -0.830525 | AH40: -10000 | AI40: -0.0045091935 | AJ40: -10000 | AK40: -0.0044520239 | AL40: -10000 | AM40: -0.0037159725 | AN40: -10000 | AO40: -0.0033563716 | AP40: -10000 | AQ40: -0.0033205332 | AR40: -10000 | AS40: -0.0036515386 | AT40: -10000 | AU40: -0.0040708807 | AW40: -120000 | AX40: -0.004 | AY40: -10000
B41: $ | C41: 1 | D41: 9 | E41: $ 1-9 de 2025 | F41: -1291.6117 | H41: Rafael | I41: Assistência Médica MOD | J41: -1291.6117 | K41: -0.00051664467 | L41: -1291.6117 | M41: -0.00064580583 | N41: -1291.6117 | O41: -0.00079559832 | P41: =IFERROR(VLOOKUP($I41,RESUMO!$A$3:$M$200,2,FALSE),"") -> 808 | Q41: =IFERROR((P41*-1)/N41-1,"") -> -0.37442498 | R41: -1291.6117 | S41: -0.00058024197 | T41: =IFERROR(VLOOKUP($I41,RESUMO!$A$3:$M$200,3,FALSE),"") -> 570 | U41: =IFERROR((T41*-1)/R41-1,"") -> -0.55869089 | V41: -1291.6117 | W41: -0.00046121926 | X41: =IFERROR(VLOOKUP($I41,RESUMO!$A$3:$M$200,4,FALSE),"") -> 349.9 | Y41: =IFERROR((X41*-1)/V41-1,"") -> -0.72909814 | Z41: -1291.6117 | AA41: -0.00052798368 | AB41: =IFERROR(VLOOKUP($I41,RESUMO!$A$3:$M$200,5,FALSE),"") -> 420 | AC41: =IFERROR((AB41*-1)/Z41-1,"") -> -0.67482486 | AD41: -1291.6117 | AE41: -0.00050397176 | AF41: =IFERROR(VLOOKUP($I41,RESUMO!$A$3:$M$200,6,FALSE),"") -> 0 | AG41: =IFERROR((AF41*-1)/AD41-1,"") -> -1 | AH41: -1291.6117 | AI41: -0.0005824127 | AJ41: -1291.6117 | AK41: -0.0005750286 | AL41: -1291.6117 | AM41: -0.00047995934 | AN41: -1291.6117 | AO41: -0.00043351288 | AP41: -1291.6117 | AQ41: -0.00042888395 | AR41: -1291.6117 | AS41: -0.00047163699 | AT41: -1291.6117 | AU41: -0.0005257997 | AW41: -15499.34 | AX41: -0.00051664467 | AY41: -1291.6117
E42: Média + IPCA | F42: -1940.2017 | H42: Rafael | I42: Seguro de Vida MOD | J42: -1940.2017 | K42: -0.00077608067 | L42: -1940.2017 | M42: -0.00097010083 | N42: -1940.2017 | O42: -0.0011951124 | P42: =IFERROR(VLOOKUP($I42,RESUMO!$A$3:$M$200,2,FALSE),"") -> 1983.19 | Q42: =IFERROR((P42*-1)/N42-1,"") -> 0.022156631 | R42: -1940.2017 | S42: -0.00087161371 | T42: =IFERROR(VLOOKUP($I42,RESUMO!$A$3:$M$200,3,FALSE),"") -> 1883.98 | U42: =IFERROR((T42*-1)/R42-1,"") -> -0.028977228 | V42: -1940.2017 | W42: -0.00069282309 | X42: =IFERROR(VLOOKUP($I42,RESUMO!$A$3:$M$200,4,FALSE),"") -> 1980.53 | Y42: =IFERROR((X42*-1)/V42-1,"") -> 0.02078564 | Z42: -1940.2017 | AA42: -0.00079311363 | AB42: =IFERROR(VLOOKUP($I42,RESUMO!$A$3:$M$200,5,FALSE),"") -> 2040.6 | AC42: =IFERROR((AB42*-1)/Z42-1,"") -> 0.051746339 | AD42: -1940.2017 | AE42: -0.00075704399 | AF42: =IFERROR(VLOOKUP($I42,RESUMO!$A$3:$M$200,6,FALSE),"") -> 0 | AG42: =IFERROR((AF42*-1)/AD42-1,"") -> -1 | AH42: -1940.2017 | AI42: -0.00087487448 | AJ42: -1940.2017 | AK42: -0.00086378241 | AL42: -1940.2017 | AM42: -0.0007209736 | AN42: -1940.2017 | AO42: -0.00065120379 | AP42: -1940.2017 | AQ42: -0.00064425041 | AR42: -1940.2017 | AS42: -0.00070847214 | AT42: -1940.2017 | AU42: -0.00078983296 | AW42: -23282.42 | AX42: -0.00077608067 | AY42: -1940.2017
E43: Provisão | F43: 0.08 | H43: Rafael | I43: FGTS MOD | J43: -16653.015 | K43: -0.006661206 | L43: -16653.015 | M43: -0.0083265075 | N43: -16653.015 | O43: -0.010257813 | P43: =IFERROR(VLOOKUP($I43,RESUMO!$A$3:$M$200,2,FALSE),"") -> 34431.98 | Q43: =IFERROR((P43*-1)/N43-1,"") -> 1.0676124 | R43: -16653.015 | S43: -0.0074811791 | T43: =IFERROR(VLOOKUP($I43,RESUMO!$A$3:$M$200,3,FALSE),"") -> 32736.5 | U43: =IFERROR((T43*-1)/R43-1,"") -> 0.96580019 | V43: -16653.015 | W43: -0.0059465948 | X43: =IFERROR(VLOOKUP($I43,RESUMO!$A$3:$M$200,4,FALSE),"") -> 35869.64 | Y43: =IFERROR((X43*-1)/V43-1,"") -> 1.1539427 | Z43: -16653.015 | AA43: -0.0068074022 | AB43: =IFERROR(VLOOKUP($I43,RESUMO!$A$3:$M$200,5,FALSE),"") -> 0 | AC43: =IFERROR((AB43*-1)/Z43-1,"") -> -1 | AD43: -17735.461 | AE43: -0.0069201694 | AF43: =IFERROR(VLOOKUP($I43,RESUMO!$A$3:$M$200,6,FALSE),"") -> 0 | AG43: =IFERROR((AF43*-1)/AD43-1,"") -> -1 | AH43: -17735.461 | AI43: -0.0079972625 | AJ43: -17735.461 | AK43: -0.0078958695 | AL43: -17735.461 | AM43: -0.0065904485 | AN43: -17735.461 | AO43: -0.0059526798 | AP43: -17735.461 | AQ43: -0.0058891187 | AR43: -17735.461 | AS43: -0.0064761721 | AT43: -17735.461 | AU43: -0.0072198946 | AW43: -208495.75 | AX43: -0.0069498582 | AY43: -17374.646
E44: Provisão | F44: 0.18 | H44: Rafael | I44: INSS MOD | J44: -37469.284 | K44: -0.014987713 | L44: -37469.284 | M44: -0.018734642 | N44: -37469.284 | O44: -0.023080079 | P44: =IFERROR(VLOOKUP($I44,RESUMO!$A$3:$M$200,2,FALSE),"") -> 44369.08 | Q44: =IFERROR((P44*-1)/N44-1,"") -> 0.1841454 | R44: -37469.284 | S44: -0.016832653 | T44: =IFERROR(VLOOKUP($I44,RESUMO!$A$3:$M$200,3,FALSE),"") -> 42800.44 | U44: =IFERROR((T44*-1)/R44-1,"") -> 0.14228071 | V44: -37469.284 | W44: -0.013379838 | X44: =IFERROR(VLOOKUP($I44,RESUMO!$A$3:$M$200,4,FALSE),"") -> 44918.66 | Y44: =IFERROR((X44*-1)/V44-1,"") -> 0.19881289 | Z44: -37469.284 | AA44: -0.015316655 | AB44: =IFERROR(VLOOKUP($I44,RESUMO!$A$3:$M$200,5,FALSE),"") -> 0 | AC44: =IFERROR((AB44*-1)/Z44-1,"") -> -1 | AD44: -39904.787 | AE44: -0.015570381 | AF44: =IFERROR(VLOOKUP($I44,RESUMO!$A$3:$M$200,6,FALSE),"") -> 0 | AG44: =IFERROR((AF44*-1)/AD44-1,"") -> -1 | AH44: -39904.787 | AI44: -0.017993841 | AJ44: -39904.787 | AK44: -0.017765706 | AL44: -39904.787 | AM44: -0.014828509 | AN44: -39904.787 | AO44: -0.01339353 | AP44: -39904.787 | AQ44: -0.013250517 | AR44: -39904.787 | AS44: -0.014571387 | AT44: -39904.787 | AU44: -0.016244763 | AW44: -469115.43 | AX44: -0.015637181 | AY44: -39092.953
E45: Provisão | F45: 0.11111111 | H45: Rafael | I45: Férias MOD | J45: -23129.187 | K45: -0.009251675 | L45: -23129.187 | M45: -0.011564594 | N45: -23129.187 | O45: -0.014246962 | P45: =IFERROR(VLOOKUP($I45,RESUMO!$A$3:$M$200,2,FALSE),"") -> 2775.23 | Q45: =IFERROR((P45*-1)/N45-1,"") -> -0.88001178 | R45: -23129.187 | S45: -0.010390526 | T45: =IFERROR(VLOOKUP($I45,RESUMO!$A$3:$M$200,3,FALSE),"") -> 5329.74 | U45: =IFERROR((T45*-1)/R45-1,"") -> -0.76956648 | V45: -23129.187 | W45: -0.0082591595 | X45: =IFERROR(VLOOKUP($I45,RESUMO!$A$3:$M$200,4,FALSE),"") -> 5620.32 | Y45: =IFERROR((X45*-1)/V45-1,"") -> -0.75700314 | Z45: -23129.187 | AA45: -0.0094547253 | AB45: =IFERROR(VLOOKUP($I45,RESUMO!$A$3:$M$200,5,FALSE),"") -> 21546.3 | AC45: =IFERROR((AB45*-1)/Z45-1,"") -> -0.068436793 | AD45: -24632.585 | AE45: -0.0096113464 | AF45: =IFERROR(VLOOKUP($I45,RESUMO!$A$3:$M$200,6,FALSE),"") -> 1358.46 | AG45: =IFERROR((AF45*-1)/AD45-1,"") -> -0.9448511 | AH45: -24632.585 | AI45: -0.011107309 | AJ45: -24632.585 | AK45: -0.010966485 | AL45: -24632.585 | AM45: -0.0091534007 | AN45: -24632.585 | AO45: -0.0082676108 | AP45: -24632.585 | AQ45: -0.0081793316 | AR45: -24632.585 | AS45: -0.0089946834 | AT45: -24632.585 | AU45: -0.010027631 | AW45: -289577.43 | AX45: -0.0096525809 | AY45: -24131.452
I46: Custos Indiretos de Fabricação | J46: -94186.35 | K46: -0.03767454 | L46: -94186.35 | M46: -0.047093175 | N46: -94186.35 | O46: -0.058016278 | P46: =SUM(P47:P62) -> 87389.24 | Q46: =(P46*-1)/N46-1 -> -0.072166617 | R46: -94186.35 | S46: -0.042312155 | T46: =SUM(T47:T62) -> 65780.3 | U46: =(T46*-1)/R46-1 -> -0.30159413 | V46: -94186.35 | W46: -0.033632833 | X46: =SUM(X47:X62) -> 107487.2 | Y46: =(X46*-1)/V46-1 -> 0.14121844 | Z46: -94186.35 | AA46: -0.038501399 | AB46: =SUM(AB47:AB62) -> 67636.97 | AC46: =(AB46*-1)/Z46-1 -> -0.2818814 | AD46: -98152.946 | AE46: -0.038298131 | AF46: =SUM(AF47:AF62) -> 16917.44 | AG46: =(AF46*-1)/AD46-1 -> -0.82764206 | AH46: -98152.946 | AI46: -0.044259063 | AJ46: -98152.946 | AK46: -0.043697926 | AL46: -98152.946 | AM46: -0.036473365 | AN46: -98152.946 | AO46: -0.032943776 | AP46: -98152.946 | AQ46: -0.032592012 | AR46: -98152.946 | AS46: -0.035840927 | AT46: -98152.946 | AU46: -0.039956894 | AW46: -1161969 | AX46: -0.038732299 | AY46: -96830.747
E47: Diretoria - 25.11.25 | F47: -11666.667 | H47: Rafael | I47: Manutenção de Equipamentos (Prod) | J47: -11666.667 | K47: -0.0046666667 | L47: -11666.667 | M47: -0.0058333333 | N47: -11666.667 | O47: -0.0071863553 | P47: =IFERROR(VLOOKUP($I47,RESUMO!$A$3:$M$200,2,FALSE),"") -> 2679.92 | Q47: =IFERROR((P47*-1)/N47-1,"") -> -0.77029257 | R47: -11666.667 | S47: -0.0052411184 | T47: =IFERROR(VLOOKUP($I47,RESUMO!$A$3:$M$200,3,FALSE),"") -> 9080.05 | U47: =IFERROR((T47*-1)/R47-1,"") -> -0.22171 | V47: -11666.667 | W47: -0.0041660288 | X47: =IFERROR(VLOOKUP($I47,RESUMO!$A$3:$M$200,4,FALSE),"") -> 50727.39 | Y47: =IFERROR((X47*-1)/V47-1,"") -> 3.348062 | Z47: -11666.667 | AA47: -0.0047690879 | AB47: =IFERROR(VLOOKUP($I47,RESUMO!$A$3:$M$200,5,FALSE),"") -> 6964.81 | AC47: =IFERROR((AB47*-1)/Z47-1,"") -> -0.40301629 | AD47: -11666.667 | AE47: -0.0045521969 | AF47: =IFERROR(VLOOKUP($I47,RESUMO!$A$3:$M$200,6,FALSE),"") -> 1139.6 | AG47: =IFERROR((AF47*-1)/AD47-1,"") -> -0.90232 | AH47: -11666.667 | AI47: -0.0052607258 | AJ47: -11666.667 | AK47: -0.0051940278 | AL47: -11666.667 | AM47: -0.0043353012 | AN47: -11666.667 | AO47: -0.0039157669 | AP47: -11666.667 | AQ47: -0.0038739554 | AR47: -11666.667 | AS47: -0.0042601284 | AT47: -11666.667 | AU47: -0.0047493609 | AW47: -140000 | AX47: -0.0046666667 | AY47: -11666.667
E48: Salarios e Ordenados CIF | F48: AUX | H48: Rafael | I48: Salarios e Ordenados CIF | J48: -41957.289 | K48: -0.016782915 | L48: -41957.289 | M48: -0.020978644 | N48: -41957.289 | O48: -0.02584457 | P48: =IFERROR(VLOOKUP($I48,RESUMO!$A$3:$M$200,2,FALSE),"") -> 36962.58 | Q48: =IFERROR((P48*-1)/N48-1,"") -> -0.11904269 | R48: -41957.289 | S48: -0.018848839 | T48: =IFERROR(VLOOKUP($I48,RESUMO!$A$3:$M$200,3,FALSE),"") -> 30986.82 | U48: =IFERROR((T48*-1)/R48-1,"") -> -0.26146753 | V48: -41957.289 | W48: -0.014982452 | X48: =IFERROR(VLOOKUP($I48,RESUMO!$A$3:$M$200,4,FALSE),"") -> 28474.9 | Y48: =IFERROR((X48*-1)/V48-1,"") -> -0.32133603 | Z48: -41957.289 | AA48: -0.017151257 | AB48: =IFERROR(VLOOKUP($I48,RESUMO!$A$3:$M$200,5,FALSE),"") -> 28865.57 | AC48: =IFERROR((AB48*-1)/Z48-1,"") -> -0.3120249 | AD48: -44684.512 | AE48: -0.017435374 | AF48: =IFERROR(VLOOKUP($I48,RESUMO!$A$3:$M$200,6,FALSE),"") -> 0 | AG48: =IFERROR((AF48*-1)/AD48-1,"") -> -1 | AH48: -44684.512 | AI48: -0.020149111 | AJ48: -44684.512 | AK48: -0.019893652 | AL48: -44684.512 | AM48: -0.016604642 | AN48: -44684.512 | AO48: -0.014997783 | AP48: -44684.512 | AQ48: -0.014837641 | AR48: -44684.512 | AS48: -0.016316722 | AT48: -44684.512 | AU48: -0.018190532 | AW48: -525305.25 | AX48: -0.017510175 | AY48: -43775.438
B49: $ | C49: 1 | D49: 9 | E49: $ 1-9 de 2025 | F49: -28.333333 | H49: Rafael | I49: Horas Extras CIF | J49: -28.333333 | K49: -1.1333333e-05 | L49: -28.333333 | M49: -1.4166667e-05 | N49: -28.333333 | O49: -1.7452577e-05 | P49: =IFERROR(VLOOKUP($I49,RESUMO!$A$3:$M$200,2,FALSE),"") -> 230 | Q49: =IFERROR((P49*-1)/N49-1,"") -> 7.1176471 | R49: -28.333333 | S49: -1.272843e-05 | T49: =IFERROR(VLOOKUP($I49,RESUMO!$A$3:$M$200,3,FALSE),"") -> 0 | U49: =IFERROR((T49*-1)/R49-1,"") -> -1 | V49: -28.333333 | W49: -1.0117498e-05 | X49: =IFERROR(VLOOKUP($I49,RESUMO!$A$3:$M$200,4,FALSE),"") -> 0 | Y49: =IFERROR((X49*-1)/V49-1,"") -> -1 | Z49: -28.333333 | AA49: -1.1582071e-05 | AB49: =IFERROR(VLOOKUP($I49,RESUMO!$A$3:$M$200,5,FALSE),"") -> 0 | AC49: =IFERROR((AB49*-1)/Z49-1,"") -> -1 | AD49: -28.333333 | AE49: -1.1055335e-05 | AF49: =IFERROR(VLOOKUP($I49,RESUMO!$A$3:$M$200,6,FALSE),"") -> 0 | AG49: =IFERROR((AF49*-1)/AD49-1,"") -> -1 | AH49: -28.333333 | AI49: -1.2776048e-05 | AJ49: -28.333333 | AK49: -1.2614068e-05 | AL49: -28.333333 | AM49: -1.0528589e-05 | AN49: -28.333333 | AO49: -9.5097197e-06 | AP49: -28.333333 | AQ49: -9.4081775e-06 | AR49: -28.333333 | AS49: -1.0346026e-05 | AT49: -28.333333 | AU49: -1.1534162e-05 | AW49: -340 | AX49: -1.1333333e-05 | AY49: -28.333333
E50: Provisão | F50: 0.083333333 | H50: Rafael | I50: 13° Salario CIF | J50: -3496.4407 | K50: -0.0013985763 | L50: -3496.4407 | M50: -0.0017482204 | N50: -3496.4407 | O50: -0.0021537142 | P50: =IFERROR(VLOOKUP($I50,RESUMO!$A$3:$M$200,2,FALSE),"") | Q50: =IFERROR((P50*-1)/N50-1,"") | R50: -3496.4407 | S50: -0.0015707365 | T50: =IFERROR(VLOOKUP($I50,RESUMO!$A$3:$M$200,3,FALSE),"") | U50: =IFERROR((T50*-1)/R50-1,"") | V50: -3496.4407 | W50: -0.0012485377 | X50: =IFERROR(VLOOKUP($I50,RESUMO!$A$3:$M$200,4,FALSE),"") | Y50: =IFERROR((X50*-1)/V50-1,"") | Z50: -3496.4407 | AA50: -0.0014292714 | AB50: =IFERROR(VLOOKUP($I50,RESUMO!$A$3:$M$200,5,FALSE),"") | AC50: =IFERROR((AB50*-1)/Z50-1,"") | AD50: -3723.7094 | AE50: -0.0014529478 | AF50: =IFERROR(VLOOKUP($I50,RESUMO!$A$3:$M$200,6,FALSE),"") | AG50: =IFERROR((AF50*-1)/AD50-1,"") | AH50: -3723.7094 | AI50: -0.0016790926 | AJ50: -3723.7094 | AK50: -0.0016578043 | AL50: -3723.7094 | AM50: -0.0013837202 | AN50: -3723.7094 | AO50: -0.0012498153 | AP50: -3723.7094 | AQ50: -0.0012364701 | AR50: -3723.7094 | AS50: -0.0013597269 | AT50: -3723.7094 | AU50: -0.0015158777 | AW50: -43775.438 | AX50: -0.0014591813 | AY50: -3647.9532
B51: $ | C51: 1 | D51: 9 | E51: $ 1-9 de 2025 | F51: -3484.806 | H51: Rafael | I51: Gratificações CIF | J51: -3484.806 | K51: -0.0013939224 | L51: -3484.806 | M51: -0.001742403 | N51: -3484.806 | O51: -0.0021465475 | P51: =IFERROR(VLOOKUP($I51,RESUMO!$A$3:$M$200,2,FALSE),"") -> 3000.69 | Q51: =IFERROR((P51*-1)/N51-1,"") -> -0.13892194 | R51: -3484.806 | S51: -0.0015655098 | T51: =IFERROR(VLOOKUP($I51,RESUMO!$A$3:$M$200,3,FALSE),"") -> 2925.69 | U51: =IFERROR((T51*-1)/R51-1,"") -> -0.16044394 | V51: -3484.806 | W51: -0.001244383 | X51: =IFERROR(VLOOKUP($I51,RESUMO!$A$3:$M$200,4,FALSE),"") -> 1589.46 | Y51: =IFERROR((X51*-1)/V51-1,"") -> -0.54388853 | Z51: -3484.806 | AA51: -0.0014245154 | AB51: =IFERROR(VLOOKUP($I51,RESUMO!$A$3:$M$200,5,FALSE),"") -> 1479.46 | AC51: =IFERROR((AB51*-1)/Z51-1,"") -> -0.57545413 | AD51: -3484.806 | AE51: -0.0013597305 | AF51: =IFERROR(VLOOKUP($I51,RESUMO!$A$3:$M$200,6,FALSE),"") -> 0 | AG51: =IFERROR((AF51*-1)/AD51-1,"") -> -1 | AH51: -3484.806 | AI51: -0.0015713665 | AJ51: -3484.806 | AK51: -0.0015514439 | AL51: -3484.806 | AM51: -0.0012949443 | AN51: -3484.806 | AO51: -0.0011696304 | AP51: -3484.806 | AQ51: -0.0011571414 | AR51: -3484.806 | AS51: -0.0012724904 | AT51: -3484.806 | AU51: -0.001418623 | AW51: -41817.672 | AX51: -0.0013939224 | AY51: -3484.806
E52: Diretoria - 25.11.25 | F52: -2841.8078 | H52: Rafael | I52: Rescisões CIF | J52: -2841.8078 | K52: -0.0011367231 | L52: -2841.8078 | M52: -0.0014209039 | N52: -2841.8078 | O52: -0.0017504777 | P52: =IFERROR(VLOOKUP($I52,RESUMO!$A$3:$M$200,2,FALSE),"") -> 0 | Q52: =IFERROR((P52*-1)/N52-1,"") -> -1 | R52: -2841.8078 | S52: -0.0012766501 | T52: =IFERROR(VLOOKUP($I52,RESUMO!$A$3:$M$200,3,FALSE),"") -> 0 | U52: =IFERROR((T52*-1)/R52-1,"") -> -1 | V52: -2841.8078 | W52: -0.001014776 | X52: =IFERROR(VLOOKUP($I52,RESUMO!$A$3:$M$200,4,FALSE),"") -> 0 | Y52: =IFERROR((X52*-1)/V52-1,"") -> -1 | Z52: -2841.8078 | AA52: -0.0011616712 | AB52: =IFERROR(VLOOKUP($I52,RESUMO!$A$3:$M$200,5,FALSE),"") -> 13159.51 | AC52: =IFERROR((AB52*-1)/Z52-1,"") -> 3.6306827 | AD52: -2841.8078 | AE52: -0.0011088402 | AF52: =IFERROR(VLOOKUP($I52,RESUMO!$A$3:$M$200,6,FALSE),"") -> 12776.45 | AG52: =IFERROR((AF52*-1)/AD52-1,"") -> 3.4958882 | AH52: -2841.8078 | AI52: -0.0012814261 | AJ52: -2841.8078 | AK52: -0.0012651796 | AL52: -2841.8078 | AM52: -0.001056008 | AN52: -2841.8078 | AO52: -0.0009538163 | AP52: -2841.8078 | AQ52: -0.00094363172 | AR52: -2841.8078 | AS52: -0.0010376971 | AT52: -2841.8078 | AU52: -0.0011568661 | AW52: -34101.693 | AX52: -0.0011367231 | AY52: -2841.8078
E53: Diretoria - 25.11.25 | F53: -97.555556 | H53: Rafael | I53: Assistência Médica CIF | J53: -97.555556 | K53: -3.9022222e-05 | L53: -97.555556 | M53: -4.8777778e-05 | N53: -97.555556 | O53: -6.0091619e-05 | P53: =IFERROR(VLOOKUP($I53,RESUMO!$A$3:$M$200,2,FALSE),"") -> 0 | Q53: =IFERROR((P53*-1)/N53-1,"") -> -1 | R53: -97.555556 | S53: -4.3825733e-05 | T53: =IFERROR(VLOOKUP($I53,RESUMO!$A$3:$M$200,3,FALSE),"") -> 0 | U53: =IFERROR((T53*-1)/R53-1,"") -> -1 | V53: -97.555556 | W53: -3.4835936e-05 | X53: =IFERROR(VLOOKUP($I53,RESUMO!$A$3:$M$200,4,FALSE),"") -> 0 | Y53: =IFERROR((X53*-1)/V53-1,"") -> -1 | Z53: -97.555556 | AA53: -3.9878659e-05 | AB53: =IFERROR(VLOOKUP($I53,RESUMO!$A$3:$M$200,5,FALSE),"") -> 225 | AC53: =IFERROR((AB53*-1)/Z53-1,"") -> 1.3063781 | AD53: -97.555556 | AE53: -3.8065037e-05 | AF53: =IFERROR(VLOOKUP($I53,RESUMO!$A$3:$M$200,6,FALSE),"") -> 0 | AG53: =IFERROR((AF53*-1)/AD53-1,"") -> -1 | AH53: -97.555556 | AI53: -4.3989688e-05 | AJ53: -97.555556 | AK53: -4.3431966e-05 | AL53: -97.555556 | AM53: -3.6251376e-05 | AN53: -97.555556 | AO53: -3.274327e-05 | AP53: -97.555556 | AQ53: -3.2393646e-05 | AR53: -97.555556 | AS53: -3.5622788e-05 | AT53: -97.555556 | AU53: -3.9713703e-05 | AW53: -1170.6667 | AX53: -3.9022222e-05 | AY53: -97.555556
E54: Média + IPCA | F54: -494.9945 | H54: Rafael | I54: Seguro de Vida CIF | J54: -494.9945 | K54: -0.0001979978 | L54: -494.9945 | M54: -0.00024749725 | N54: -494.9945 | O54: -0.0003049034 | P54: =IFERROR(VLOOKUP($I54,RESUMO!$A$3:$M$200,2,FALSE),"") -> 361.18 | Q54: =IFERROR((P54*-1)/N54-1,"") -> -0.27033533 | R54: -494.9945 | S54: -0.00022237069 | T54: =IFERROR(VLOOKUP($I54,RESUMO!$A$3:$M$200,3,FALSE),"") -> 243.78 | U54: =IFERROR((T54*-1)/R54-1,"") -> -0.50750968 | V54: -494.9945 | W54: -0.00017675669 | X54: =IFERROR(VLOOKUP($I54,RESUMO!$A$3:$M$200,4,FALSE),"") -> 272.04 | Y54: =IFERROR((X54*-1)/V54-1,"") -> -0.45041814 | Z54: -494.9945 | AA54: -0.00020234334 | AB54: =IFERROR(VLOOKUP($I54,RESUMO!$A$3:$M$200,5,FALSE),"") -> 276.28 | AC54: =IFERROR((AB54*-1)/Z54-1,"") -> -0.44185238 | AD54: -494.9945 | AE54: -0.00019314106 | AF54: =IFERROR(VLOOKUP($I54,RESUMO!$A$3:$M$200,6,FALSE),"") -> 0 | AG54: =IFERROR((AF54*-1)/AD54-1,"") -> -1 | AH54: -494.9945 | AI54: -0.0002232026 | AJ54: -494.9945 | AK54: -0.00022037273 | AL54: -494.9945 | AM54: -0.00018393859 | AN54: -494.9945 | AO54: -0.00016613855 | AP54: -494.9945 | AQ54: -0.00016436457 | AR54: -494.9945 | AS54: -0.00018074915 | AT54: -494.9945 | AU54: -0.00020150636 | AW54: -5939.934 | AX54: -0.0001979978 | AY54: -494.9945
E55: Provisão | F55: 0.08 | H55: Rafael | I55: FGTS CIF | J55: -3356.5831 | K55: -0.0013426332 | L55: -3356.5831 | M55: -0.0016782915 | N55: -3356.5831 | O55: -0.0020675656 | P55: =IFERROR(VLOOKUP($I55,RESUMO!$A$3:$M$200,2,FALSE),"") -> 6497.95 | Q55: =IFERROR((P55*-1)/N55-1,"") -> 0.93588236 | R55: -3356.5831 | S55: -0.0015079071 | T55: =IFERROR(VLOOKUP($I55,RESUMO!$A$3:$M$200,3,FALSE),"") -> 5251.66 | U55: =IFERROR((T55*-1)/R55-1,"") -> 0.56458513 | V55: -3356.5831 | W55: -0.0011985962 | X55: =IFERROR(VLOOKUP($I55,RESUMO!$A$3:$M$200,4,FALSE),"") -> 5035.68 | Y55: =IFERROR((X55*-1)/V55-1,"") -> 0.50023993 | Z55: -3356.5831 | AA55: -0.0013721006 | AB55: =IFERROR(VLOOKUP($I55,RESUMO!$A$3:$M$200,5,FALSE),"") -> 0 | AC55: =IFERROR((AB55*-1)/Z55-1,"") -> -1 | AD55: -3574.761 | AE55: -0.0013948299 | AF55: =IFERROR(VLOOKUP($I55,RESUMO!$A$3:$M$200,6,FALSE),"") -> 0 | AG55: =IFERROR((AF55*-1)/AD55-1,"") -> -1 | AH55: -3574.761 | AI55: -0.0016119289 | AJ55: -3574.761 | AK55: -0.0015914921 | AL55: -3574.761 | AM55: -0.0013283714 | AN55: -3574.761 | AO55: -0.0011998226 | AP55: -3574.761 | AQ55: -0.0011870113 | AR55: -3574.761 | AS55: -0.0013053378 | AT55: -3574.761 | AU55: -0.0014552426 | AW55: -42024.42 | AX55: -0.001400814 | AY55: -3502.035
E56: Provisão | F56: 0.18 | H56: Rafael | I56: INSS CIF | J56: -7552.312 | K56: -0.0030209248 | L56: -7552.312 | M56: -0.003776156 | N56: -7552.312 | O56: -0.0046520226 | P56: =IFERROR(VLOOKUP($I56,RESUMO!$A$3:$M$200,2,FALSE),"") -> 8026.61 | Q56: =IFERROR((P56*-1)/N56-1,"") -> 0.0628017 | R56: -7552.312 | S56: -0.0033927909 | T56: =IFERROR(VLOOKUP($I56,RESUMO!$A$3:$M$200,3,FALSE),"") -> 8297.76 | U56: =IFERROR((T56*-1)/R56-1,"") -> 0.098704614 | V56: -7552.312 | W56: -0.0026968413 | X56: =IFERROR(VLOOKUP($I56,RESUMO!$A$3:$M$200,4,FALSE),"") -> 8006.02 | Y56: =IFERROR((X56*-1)/V56-1,"") -> 0.060075383 | Z56: -7552.312 | AA56: -0.0030872263 | AB56: =IFERROR(VLOOKUP($I56,RESUMO!$A$3:$M$200,5,FALSE),"") -> 0 | AC56: =IFERROR((AB56*-1)/Z56-1,"") -> -1 | AD56: -8043.2122 | AE56: -0.0031383673 | AF56: =IFERROR(VLOOKUP($I56,RESUMO!$A$3:$M$200,6,FALSE),"") -> 0 | AG56: =IFERROR((AF56*-1)/AD56-1,"") -> -1 | AH56: -8043.2122 | AI56: -0.0036268401 | AJ56: -8043.2122 | AK56: -0.0035808573 | AL56: -8043.2122 | AM56: -0.0029888356 | AN56: -8043.2122 | AO56: -0.0026996009 | AP56: -8043.2122 | AQ56: -0.0026707754 | AR56: -8043.2122 | AS56: -0.00293701 | AT56: -8043.2122 | AU56: -0.0032742958 | AW56: -94554.946 | AX56: -0.0031518315 | AY56: -7879.5788
E57: Provisão | F57: 0.11111111 | H57: Rafael | I57: Férias CIF | J57: -4661.921 | K57: -0.0018647684 | L57: -4661.921 | M57: -0.0023309605 | N57: -4661.921 | O57: -0.0028716189 | P57: =IFERROR(VLOOKUP($I57,RESUMO!$A$3:$M$200,2,FALSE),"") -> 0 | Q57: =IFERROR((P57*-1)/N57-1,"") -> -1 | R57: -4661.921 | S57: -0.0020943154 | T57: =IFERROR(VLOOKUP($I57,RESUMO!$A$3:$M$200,3,FALSE),"") -> 0 | U57: =IFERROR((T57*-1)/R57-1,"") -> -1 | V57: -4661.921 | W57: -0.0016647169 | X57: =IFERROR(VLOOKUP($I57,RESUMO!$A$3:$M$200,4,FALSE),"") -> 1458.08 | Y57: =IFERROR((X57*-1)/V57-1,"") -> -0.68723623 | Z57: -4661.921 | AA57: -0.0019056952 | AB57: =IFERROR(VLOOKUP($I57,RESUMO!$A$3:$M$200,5,FALSE),"") -> 1316.22 | AC57: =IFERROR((AB57*-1)/Z57-1,"") -> -0.71766574 | AD57: -4964.9458 | AE57: -0.0019372638 | AF57: =IFERROR(VLOOKUP($I57,RESUMO!$A$3:$M$200,6,FALSE),"") -> 0 | AG57: =IFERROR((AF57*-1)/AD57-1,"") -> -1 | AH57: -4964.9458 | AI57: -0.0022387902 | AJ57: -4964.9458 | AK57: -0.0022104057 | AL57: -4964.9458 | AM57: -0.0018449602 | AN57: -4964.9458 | AO57: -0.0016664203 | AP57: -4964.9458 | AQ57: -0.0016486268 | AR57: -4964.9458 | AS57: -0.0018129692 | AT57: -4964.9458 | AU57: -0.0020211702 | AW57: -58367.251 | AX57: -0.001945575 | AY57: -4863.9375
B58: $ | C58: 5 | D58: 9 | E58: $ 5-9 de 2025 | F58: -2399.746 | H58: Rafael | I58: Medicina e Seguranca do Trabalho CIF | J58: -2399.746 | K58: -0.0009598984 | L58: -2399.746 | M58: -0.001199873 | N58: -2399.746 | O58: -0.0014781795 | P58: =IFERROR(VLOOKUP($I58,RESUMO!$A$3:$M$200,2,FALSE),"") -> 2316.15 | Q58: =IFERROR((P58*-1)/N58-1,"") -> -0.034835353 | R58: -2399.746 | S58: -0.0010780588 | T58: =IFERROR(VLOOKUP($I58,RESUMO!$A$3:$M$200,3,FALSE),"") -> 2405.31 | U58: =IFERROR((T58*-1)/R58-1,"") -> 0.0023185787 | V58: -2399.746 | W58: -0.00085692094 | X58: =IFERROR(VLOOKUP($I58,RESUMO!$A$3:$M$200,4,FALSE),"") -> 2405.31 | Y58: =IFERROR((X58*-1)/V58-1,"") -> 0.0023185787 | Z58: -2399.746 | AA58: -0.00098096568 | AB58: =IFERROR(VLOOKUP($I58,RESUMO!$A$3:$M$200,5,FALSE),"") -> 2405.31 | AC58: =IFERROR((AB58*-1)/Z58-1,"") -> 0.0023185787 | AD58: -2399.746 | AE58: -0.00093635282 | AF58: =IFERROR(VLOOKUP($I58,RESUMO!$A$3:$M$200,6,FALSE),"") -> 0 | AG58: =IFERROR((AF58*-1)/AD58-1,"") -> -1 | AH58: -2399.746 | AI58: -0.0010820919 | AJ58: -2399.746 | AK58: -0.0010683726 | AL58: -2399.746 | AM58: -0.00089173901 | AN58: -2399.746 | AO58: -0.00080544394 | AP58: -2399.746 | AQ58: -0.00079684363 | AR58: -2399.746 | AS58: -0.00087627652 | AT58: -2399.746 | AU58: -0.00097690798 | AW58: -28796.952 | AX58: -0.0009598984 | AY58: -2399.746
E59: Diretoria - 25.11.25 | F59: -2500 | H59: Rafael | I59: Cursos e Treinamentos CIF | J59: -2500 | K59: -0.001 | L59: -2500 | M59: -0.00125 | N59: -2500 | O59: -0.0015399333 | P59: =IFERROR(VLOOKUP($I59,RESUMO!$A$3:$M$200,2,FALSE),"") -> 2934.94 | Q59: =IFERROR((P59*-1)/N59-1,"") -> 0.173976 | R59: -2500 | S59: -0.0011230968 | T59: =IFERROR(VLOOKUP($I59,RESUMO!$A$3:$M$200,3,FALSE),"") -> 1387.7 | U59: =IFERROR((T59*-1)/R59-1,"") -> -0.44492 | V59: -2500 | W59: -0.00089272045 | X59: =IFERROR(VLOOKUP($I59,RESUMO!$A$3:$M$200,4,FALSE),"") -> 705.03 | Y59: =IFERROR((X59*-1)/V59-1,"") -> -0.717988 | Z59: -2500 | AA59: -0.0010219474 | AB59: =IFERROR(VLOOKUP($I59,RESUMO!$A$3:$M$200,5,FALSE),"") -> 0 | AC59: =IFERROR((AB59*-1)/Z59-1,"") -> -1 | AD59: -2500 | AE59: -0.00097547076 | AF59: =IFERROR(VLOOKUP($I59,RESUMO!$A$3:$M$200,6,FALSE),"") -> 0 | AG59: =IFERROR((AF59*-1)/AD59-1,"") -> -1 | AH59: -2500 | AI59: -0.0011272984 | AJ59: -2500 | AK59: -0.001113006 | AL59: -2500 | AM59: -0.00092899312 | AN59: -2500 | AO59: -0.00083909291 | AP59: -2500 | AQ59: -0.00083013331 | AR59: -2500 | AS59: -0.00091288466 | AT59: -2500 | AU59: -0.0010177202 | AW59: -30000 | AX59: -0.001 | AY59: -2500
E60: Diretoria - 25.11.25 | F60: -1950 | H60: Mylena | I60: Material de Limpeza CIF | J60: -1950 | K60: -0.00078 | L60: -1950 | M60: -0.000975 | N60: -1950 | O60: -0.001201148 | P60: =IFERROR(VLOOKUP($I60,RESUMO!$A$3:$M$200,2,FALSE),"") -> 1649.3 | Q60: =IFERROR((P60*-1)/N60-1,"") -> -0.15420513 | R60: -1950 | S60: -0.0008760155 | T60: =IFERROR(VLOOKUP($I60,RESUMO!$A$3:$M$200,3,FALSE),"") -> 1675.48 | U60: =IFERROR((T60*-1)/R60-1,"") -> -0.14077949 | V60: -1950 | W60: -0.00069632195 | X60: =IFERROR(VLOOKUP($I60,RESUMO!$A$3:$M$200,4,FALSE),"") -> 2109.7 | Y60: =IFERROR((X60*-1)/V60-1,"") -> 0.081897436 | Z60: -1950 | AA60: -0.00079711898 | AB60: =IFERROR(VLOOKUP($I60,RESUMO!$A$3:$M$200,5,FALSE),"") -> 2093.6 | AC60: =IFERROR((AB60*-1)/Z60-1,"") -> 0.073641026 | AD60: -1950 | AE60: -0.00076086719 | AF60: =IFERROR(VLOOKUP($I60,RESUMO!$A$3:$M$200,6,FALSE),"") -> 2112.39 | AG60: =IFERROR((AF60*-1)/AD60-1,"") -> 0.083276923 | AH60: -1950 | AI60: -0.00087929274 | AJ60: -1950 | AK60: -0.00086814465 | AL60: -1950 | AM60: -0.00072461464 | AN60: -1950 | AO60: -0.00065449247 | AP60: -1950 | AQ60: -0.00064750398 | AR60: -1950 | AS60: -0.00071205003 | AT60: -1950 | AU60: -0.00079382174 | AW60: -23400 | AX60: -0.00078 | AY60: -1950
E61: Diretoria - 25.11.25 | F61: -7000 | H61: Rafael | I61: Manutenção Predial CIF | J61: -7000 | K61: -0.0028 | L61: -7000 | M61: -0.0035 | N61: -7000 | O61: -0.0043118132 | P61: =IFERROR(VLOOKUP($I61,RESUMO!$A$3:$M$200,2,FALSE),"") -> 22729.92 | Q61: =IFERROR((P61*-1)/N61-1,"") -> 2.2471314 | R61: -7000 | S61: -0.003144671 | T61: =IFERROR(VLOOKUP($I61,RESUMO!$A$3:$M$200,3,FALSE),"") -> 3526.05 | U61: =IFERROR((T61*-1)/R61-1,"") -> -0.49627857 | V61: -7000 | W61: -0.0024996173 | X61: =IFERROR(VLOOKUP($I61,RESUMO!$A$3:$M$200,4,FALSE),"") -> 6703.59 | Y61: =IFERROR((X61*-1)/V61-1,"") -> -0.042344286 | Z61: -7000 | AA61: -0.0028614528 | AB61: =IFERROR(VLOOKUP($I61,RESUMO!$A$3:$M$200,5,FALSE),"") -> 8001.47 | AC61: =IFERROR((AB61*-1)/Z61-1,"") -> 0.14306714 | AD61: -7000 | AE61: -0.0027313181 | AF61: =IFERROR(VLOOKUP($I61,RESUMO!$A$3:$M$200,6,FALSE),"") -> 889 | AG61: =IFERROR((AF61*-1)/AD61-1,"") -> -0.873 | AH61: -7000 | AI61: -0.0031564355 | AJ61: -7000 | AK61: -0.0031164167 | AL61: -7000 | AM61: -0.0026011807 | AN61: -7000 | AO61: -0.0023494601 | AP61: -7000 | AQ61: -0.0023243733 | AR61: -7000 | AS61: -0.002556077 | AT61: -7000 | AU61: -0.0028496165 | AW61: -84000 | AX61: -0.0028 | AY61: -7000
B62: $ | C62: 1 | D62: 9 | E62: $ 1-9 de 2025 | F62: -697.895 | H62: Letícia | I62: IPTU e Taxas Municipais CIF | J62: -697.895 | K62: -0.000279158 | L62: -697.895 | M62: -0.0003489475 | N62: -697.895 | O62: -0.00042988469 | P62: =IFERROR(VLOOKUP($I62,RESUMO!$A$3:$M$200,2,FALSE),"") -> 0 | Q62: =IFERROR((P62*-1)/N62-1,"") -> -1 | R62: -697.895 | S62: -0.00031352145 | T62: =IFERROR(VLOOKUP($I62,RESUMO!$A$3:$M$200,3,FALSE),"") -> 0 | U62: =IFERROR((T62*-1)/R62-1,"") -> -1 | V62: -697.895 | W62: -0.00024921006 | X62: =IFERROR(VLOOKUP($I62,RESUMO!$A$3:$M$200,4,FALSE),"") -> 0 | Y62: =IFERROR((X62*-1)/V62-1,"") -> -1 | Z62: -697.895 | AA62: -0.0002852848 | AB62: =IFERROR(VLOOKUP($I62,RESUMO!$A$3:$M$200,5,FALSE),"") -> 2849.74 | AC62: =IFERROR((AB62*-1)/Z62-1,"") -> 3.0833363 | AD62: -697.895 | AE62: -0.00027231047 | AF62: =IFERROR(VLOOKUP($I62,RESUMO!$A$3:$M$200,6,FALSE),"") -> 0 | AG62: =IFERROR((AF62*-1)/AD62-1,"") -> -1 | AH62: -697.895 | AI62: -0.00031469436 | AJ62: -697.895 | AK62: -0.00031070452 | AL62: -697.895 | AM62: -0.00025933586 | AN62: -697.895 | AO62: -0.0002342395 | AP62: -697.895 | AQ62: -0.00023173835 | AR62: -697.895 | AS62: -0.00025483906 | AT62: -697.895 | AU62: -0.00028410473 | AW62: -8374.74 | AX62: -0.000279158 | AY62: -697.895
AF63: =IFERROR(VLOOKUP($I63,RESUMO!$A$3:$M$200,6,FALSE),"")
I64: Lucro Bruto | J64: 897943.02 | K64: 0.35917721 | L64: 629618.02 | M64: 0.31480901 | N64: 427540.83 | O64: 0.26335374 | P64: =P21-P23 -> 411097.7 | Q64: =P64/N64-1 -> -0.038459787 | R64: 750894.49 | S64: 0.33733088 | T64: =T21-T23 -> 652776.45 | U64: =T64/R64-1 -> -0.13066821 | V64: 1059168.1 | W64: 0.37821641 | X64: =X21-X23 -> 977071.84 | Y64: =X64/V64-1 -> -0.077510125 | Z64: 869130.19 | AA64: 0.35528214 | AB64: =AB21-AB23 -> 1013077.1 | AC64: =AB64/Z64-1 -> 0.16562177 | AD64: 908033.53 | AE64: 0.35430406 | AF64: =AF21-AF23 -> 388949.96 | AG64: =AF64/AD64-1 -> -0.57165683 | AH64: 722796.08 | AI64: 0.32592274 | AJ64: 738078.79 | AK64: 0.32859444 | AL64: 976843.03 | AM64: 0.36299218 | AN64: 1131571.2 | AO64: 0.37979734 | AP64: 1148828 | AQ64: 0.38147217 | AR64: 1002326.4 | AS64: 0.36600336 | AT64: 850937.06 | AU64: 0.34640633 | AW64: 10586148 | AX64: 0.35287159 | AY64: 882178.98
I66: Despesas Gerais e Administrativas | J66: -707408.81 | K66: -0.28296352 | L66: -659214.06 | M66: -0.32960703 | N66: -622918.31 | O66: -0.38370105 | P66: =SUM(P67+P85+P101+P123) -> 655078.41 | Q66: =IFERROR((P66*-1)/N66-1,"") -> 0.051628124 | R66: -680996.93 | S66: -0.30593019 | T66: =SUM(T67+T85+T101+T123) -> 569914.08 | U66: =IFERROR((T66*-1)/R66-1,"") -> -0.16311799 | V66: -736366.98 | W66: -0.26294795 | X66: =SUM(X67+X85+X101+X123) -> 658115.23 | Y66: =IFERROR((X66*-1)/V66-1,"") -> -0.10626733 | Z66: -702233.64 | AA66: -0.28705834 | AB66: =SUM(AB67+AB85+AB101+AB123) -> 624388.79 | AC66: =IFERROR((AB66*-1)/Z66-1,"") -> -0.11085321 | AD66: -719188.9 | AE66: -0.2806191 | AF66: =SUM(AF67+AF85+AF101+AF123) -> 207371 | AG66: =IFERROR((AF66*-1)/AD66-1,"") -> -0.7116599 | AH66: -685917.79 | AI66: -0.30929361 | AJ66: -688662.77 | AK66: -0.30659431 | AL66: -731548.01 | AM66: -0.27184123 | AN66: -759339.24 | AO66: -0.25486247 | AP66: -762438.81 | AQ66: -0.25317034 | AR66: -736125.16 | AS66: -0.26879895 | AT66: -708933.62 | AU66: -0.28859842 | AW66: -8534670.2 | AX66: -0.28448901 | AY66: -711222.51
I67: Despesa com Pessoal | J67: -174857.96 | K67: -0.069943185 | L67: -174857.96 | M67: -0.087428982 | N67: -174857.96 | O67: -0.10770784 | P67: =SUM(P68:P84) -> 162457.66 | Q67: =(P67*-1)/N67-1 -> -0.070916433 | R67: -174857.96 | S67: -0.078552967 | T67: =SUM(T68:T84) -> 172282.52 | U67: =(T67*-1)/R67-1 -> -0.014728772 | V67: -174857.96 | W67: -0.062439712 | X67: =SUM(X68:X84) -> 186511.62 | Y67: =(X67*-1)/V67-1 -> 0.066646418 | Z67: -174857.96 | AA67: -0.071478257 | AB67: =SUM(AB68:AB84) -> 158165.32 | AC67: =(AB67*-1)/Z67-1 -> -0.095464014 | AD67: -180578.52 | AE67: -0.070459626 | AF67: =SUM(AF68:AF84) -> 63986.17 | AG67: =(AF67*-1)/AD67-1 -> -0.64566012 | AH67: -180578.52 | AI67: -0.081426349 | AJ67: -180578.52 | AK67: -0.080393988 | AL67: -180578.52 | AM67: -0.067102481 | AN67: -180578.52 | AO67: -0.060608862 | AP67: -180578.52 | AQ67: -0.059961697 | AR67: -180578.52 | AS67: -0.065938944 | AT67: -180578.52 | AU67: -0.073511361 | AW67: -2144060 | AX67: -0.071468667 | AY67: -178671.67
E68: Diretoria - 25.11.25 | F68: -63900 | H68: Mylena | I68: Pró-Labore | J68: -63900 | K68: -0.02556 | L68: -63900 | M68: -0.03195 | N68: -63900 | O68: -0.039360695 | P68: =IFERROR(VLOOKUP($I68,RESUMO!$A$3:$M$200,2,FALSE),"") -> 64498.68 | Q68: =IFERROR((P68*-1)/N68-1,"") -> 0.0093690141 | R68: -63900 | S68: -0.028706354 | T68: =IFERROR(VLOOKUP($I68,RESUMO!$A$3:$M$200,3,FALSE),"") -> 60318.18 | U68: =IFERROR((T68*-1)/R68-1,"") -> -0.056053521 | V68: -63900 | W68: -0.022817935 | X68: =IFERROR(VLOOKUP($I68,RESUMO!$A$3:$M$200,4,FALSE),"") -> 59830.19 | Y68: =IFERROR((X68*-1)/V68-1,"") -> -0.063690297 | Z68: -63900 | AA68: -0.026120976 | AB68: =IFERROR(VLOOKUP($I68,RESUMO!$A$3:$M$200,5,FALSE),"") -> 61974.34 | AC68: =IFERROR((AB68*-1)/Z68-1,"") -> -0.030135524 | AD68: -63900 | AE68: -0.024933033 | AF68: =IFERROR(VLOOKUP($I68,RESUMO!$A$3:$M$200,6,FALSE),"") -> 62746.85 | AG68: =IFERROR((AF68*-1)/AD68-1,"") -> -0.018046166 | AH68: -63900 | AI68: -0.028813747 | AJ68: -63900 | AK68: -0.028448433 | AL68: -63900 | AM68: -0.023745064 | AN68: -63900 | AO68: -0.021447215 | AP68: -63900 | AQ68: -0.021218207 | AR68: -63900 | AS68: -0.023333332 | AT68: -63900 | AU68: -0.026012928 | AW68: -766800 | AX68: -0.02556 | AY68: -63900
E69: Salarios e Ordenados (Adm) | F69: AUX | H69: Rafael | I69: Salarios e Ordenados (Adm) | J69: -60510.08 | K69: -0.024204032 | L69: -60510.08 | M69: -0.03025504 | N69: -60510.08 | O69: -0.037272594 | P69: =IFERROR(VLOOKUP($I69,RESUMO!$A$3:$M$200,2,FALSE),"") -> 53990.01 | Q69: =IFERROR((P69*-1)/N69-1,"") -> -0.10775179 | R69: -60510.08 | S69: -0.027183471 | T69: =IFERROR(VLOOKUP($I69,RESUMO!$A$3:$M$200,3,FALSE),"") -> 71662.62 | U69: =IFERROR((T69*-1)/R69-1,"") -> 0.1843088 | V69: -60510.08 | W69: -0.021607434 | X69: =IFERROR(VLOOKUP($I69,RESUMO!$A$3:$M$200,4,FALSE),"") -> 74200.57 | Y69: =IFERROR((X69*-1)/V69-1,"") -> 0.2262514 | Z69: -60510.08 | AA69: -0.024735248 | AB69: =IFERROR(VLOOKUP($I69,RESUMO!$A$3:$M$200,5,FALSE),"") -> 67351.37 | AC69: =IFERROR((AB69*-1)/Z69-1,"") -> 0.11306034 | AD69: -64443.235 | AE69: -0.025144996 | AF69: =IFERROR(VLOOKUP($I69,RESUMO!$A$3:$M$200,6,FALSE),"") -> 0 | AG69: =IFERROR((AF69*-1)/AD69-1,"") -> -1 | AH69: -64443.235 | AI69: -0.029058702 | AJ69: -64443.235 | AK69: -0.028690282 | AL69: -64443.235 | AM69: -0.023946929 | AN69: -64443.235 | AO69: -0.021629545 | AP69: -64443.235 | AQ69: -0.02139859 | AR69: -64443.235 | AS69: -0.023531696 | AT69: -64443.235 | AU69: -0.026234072 | AW69: -757586.2 | AX69: -0.025252873 | AY69: -63132.183
E70: Sem Histórico | H70: Rafael | I70: Horas Extras (adm) | J70: 0 | K70: 0 | L70: 0 | M70: 0 | N70: 0 | O70: 0 | P70: =IFERROR(VLOOKUP($I70,RESUMO!$A$3:$M$200,2,FALSE),"") | Q70: =IFERROR((P70*-1)/N70-1,"") | R70: 0 | S70: 0 | T70: =IFERROR(VLOOKUP($I70,RESUMO!$A$3:$M$200,3,FALSE),"") | U70: =IFERROR((T70*-1)/R70-1,"") | V70: 0 | W70: 0 | X70: =IFERROR(VLOOKUP($I70,RESUMO!$A$3:$M$200,4,FALSE),"") | Y70: =IFERROR((X70*-1)/V70-1,"") | Z70: 0 | AA70: 0 | AB70: =IFERROR(VLOOKUP($I70,RESUMO!$A$3:$M$200,5,FALSE),"") | AC70: =IFERROR((AB70*-1)/Z70-1,"") | AD70: 0 | AE70: 0 | AF70: =IFERROR(VLOOKUP($I70,RESUMO!$A$3:$M$200,6,FALSE),"") | AG70: =IFERROR((AF70*-1)/AD70-1,"") | AH70: 0 | AI70: 0 | AJ70: 0 | AK70: 0 | AL70: 0 | AM70: 0 | AN70: 0 | AO70: 0 | AP70: 0 | AQ70: 0 | AR70: 0 | AS70: 0 | AT70: 0 | AU70: 0 | AW70: 0 | AX70: 0 | AY70: 0
E71: Provisão | F71: 0.083333333 | H71: Rafael | I71: 13° Salario (Adm) | J71: -5042.5066 | K71: -0.0020170027 | L71: -5042.5066 | M71: -0.0025212533 | N71: -5042.5066 | O71: -0.0031060495 | P71: =IFERROR(VLOOKUP($I71,RESUMO!$A$3:$M$200,2,FALSE),"") | Q71: =IFERROR((P71*-1)/N71-1,"") | R71: -5042.5066 | S71: -0.0022652892 | T71: =IFERROR(VLOOKUP($I71,RESUMO!$A$3:$M$200,3,FALSE),"") | U71: =IFERROR((T71*-1)/R71-1,"") | V71: -5042.5066 | W71: -0.0018006195 | X71: =IFERROR(VLOOKUP($I71,RESUMO!$A$3:$M$200,4,FALSE),"") | Y71: =IFERROR((X71*-1)/V71-1,"") | Z71: -5042.5066 | AA71: -0.0020612706 | AB71: =IFERROR(VLOOKUP($I71,RESUMO!$A$3:$M$200,5,FALSE),"") | AC71: =IFERROR((AB71*-1)/Z71-1,"") | AD71: -5370.2696 | AE71: -0.0020954164 | AF71: =IFERROR(VLOOKUP($I71,RESUMO!$A$3:$M$200,6,FALSE),"") | AG71: =IFERROR((AF71*-1)/AD71-1,"") | AH71: -5370.2696 | AI71: -0.0024215585 | AJ71: -5370.2696 | AK71: -0.0023908568 | AL71: -5370.2696 | AM71: -0.0019955774 | AN71: -5370.2696 | AO71: -0.0018024621 | AP71: -5370.2696 | AQ71: -0.0017832159 | AR71: -5370.2696 | AS71: -0.0019609747 | AT71: -5370.2696 | AU71: -0.0021861727 | AW71: -63132.183 | AX71: -0.0021044061 | AY71: -5261.0153
E72: Provisão | F72: 0.11111111 | H72: Rafael | I72: Ferias (Adm) | J72: -6723.3422 | K72: -0.0026893369 | L72: -6723.3422 | M72: -0.0033616711 | N72: -6723.3422 | O72: -0.0041413994 | P72: =IFERROR(VLOOKUP($I72,RESUMO!$A$3:$M$200,2,FALSE),"") -> 0 | Q72: =IFERROR((P72*-1)/N72-1,"") -> -1 | R72: -6723.3422 | S72: -0.0030203856 | T72: =IFERROR(VLOOKUP($I72,RESUMO!$A$3:$M$200,3,FALSE),"") -> 297.9 | U72: =IFERROR((T72*-1)/R72-1,"") -> -0.95569168 | V72: -6723.3422 | W72: -0.002400826 | X72: =IFERROR(VLOOKUP($I72,RESUMO!$A$3:$M$200,4,FALSE),"") -> 1372.31 | Y72: =IFERROR((X72*-1)/V72-1,"") -> -0.79588872 | Z72: -6723.3422 | AA72: -0.0027483609 | AB72: =IFERROR(VLOOKUP($I72,RESUMO!$A$3:$M$200,5,FALSE),"") -> 2681.09 | AC72: =IFERROR((AB72*-1)/Z72-1,"") -> -0.6012266 | AD72: -7160.3594 | AE72: -0.0027938885 | AF72: =IFERROR(VLOOKUP($I72,RESUMO!$A$3:$M$200,6,FALSE),"") -> 0 | AG72: =IFERROR((AF72*-1)/AD72-1,"") -> -1 | AH72: -7160.3594 | AI72: -0.0032287446 | AJ72: -7160.3594 | AK72: -0.0031878091 | AL72: -7160.3594 | AM72: -0.0026607699 | AN72: -7160.3594 | AO72: -0.0024032827 | AP72: -7160.3594 | AQ72: -0.0023776211 | AR72: -7160.3594 | AS72: -0.0026146329 | AT72: -7160.3594 | AU72: -0.0029148969 | AW72: -84176.244 | AX72: -0.0028058748 | AY72: -7014.687
B73: $ | C73: 1 | D73: 9 | E73: $ 1-9 de 2025 | F73: -4585.0111 | H73: Rafael | I73: Gratificações (Adm) | J73: -4585.0111 | K73: -0.0018340044 | L73: -4585.0111 | M73: -0.0022925056 | N73: -4585.0111 | O73: -0.0028242445 | P73: =IFERROR(VLOOKUP($I73,RESUMO!$A$3:$M$200,2,FALSE),"") -> 2919.01 | Q73: =IFERROR((P73*-1)/N73-1,"") -> -0.36335814 | R73: -4585.0111 | S73: -0.0020597645 | T73: =IFERROR(VLOOKUP($I73,RESUMO!$A$3:$M$200,3,FALSE),"") -> 4519.01 | U73: =IFERROR((T73*-1)/R73-1,"") -> -0.014394973 | V73: -4585.0111 | W73: -0.0016372533 | X73: =IFERROR(VLOOKUP($I73,RESUMO!$A$3:$M$200,4,FALSE),"") -> 4955.24 | Y73: =IFERROR((X73*-1)/V73-1,"") -> 0.080747654 | Z73: -4585.0111 | AA73: -0.0018742561 | AB73: =IFERROR(VLOOKUP($I73,RESUMO!$A$3:$M$200,5,FALSE),"") -> 1980.24 | AC73: =IFERROR((AB73*-1)/Z73-1,"") -> -0.56810574 | AD73: -4585.0111 | AE73: -0.0017890177 | AF73: =IFERROR(VLOOKUP($I73,RESUMO!$A$3:$M$200,6,FALSE),"") -> 0 | AG73: =IFERROR((AF73*-1)/AD73-1,"") -> -1 | AH73: -4585.0111 | AI73: -0.0020674702 | AJ73: -4585.0111 | AK73: -0.0020412579 | AL73: -4585.0111 | AM73: -0.0017037775 | AN73: -4585.0111 | AO73: -0.0015389001 | AP73: -4585.0111 | AQ73: -0.0015224682 | AR73: -4585.0111 | AS73: -0.0016742345 | AT73: -4585.0111 | AU73: -0.0018665033 | AW73: -55020.133 | AX73: -0.0018340044 | AY73: -4585.0111
E74: Diretoria - 25.11.25 | F74: -333 | H74: Rafael | I74: EPIs/Uniformes (Adm) | J74: -333 | K74: -0.0001332 | L74: -333 | M74: -0.0001665 | N74: -333 | O74: -0.00020511911 | P74: =IFERROR(VLOOKUP($I74,RESUMO!$A$3:$M$200,2,FALSE),"") | Q74: =IFERROR((P74*-1)/N74-1,"") | R74: -333 | S74: -0.00014959649 | T74: =IFERROR(VLOOKUP($I74,RESUMO!$A$3:$M$200,3,FALSE),"") | U74: =IFERROR((T74*-1)/R74-1,"") | V74: -333 | W74: -0.00011891036 | X74: =IFERROR(VLOOKUP($I74,RESUMO!$A$3:$M$200,4,FALSE),"") | Y74: =IFERROR((X74*-1)/V74-1,"") | Z74: -333 | AA74: -0.0001361234 | AB74: =IFERROR(VLOOKUP($I74,RESUMO!$A$3:$M$200,5,FALSE),"") | AC74: =IFERROR((AB74*-1)/Z74-1,"") | AD74: -333 | AE74: -0.0001299327 | AF74: =IFERROR(VLOOKUP($I74,RESUMO!$A$3:$M$200,6,FALSE),"") | AG74: =IFERROR((AF74*-1)/AD74-1,"") | AH74: -333 | AI74: -0.00015015614 | AJ74: -333 | AK74: -0.00014825239 | AL74: -333 | AM74: -0.00012374188 | AN74: -333 | AO74: -0.00011176718 | AP74: -333 | AQ74: -0.00011057376 | AR74: -333 | AS74: -0.00012159624 | AT74: -333 | AU74: -0.00013556033 | AW74: -3996 | AX74: -0.0001332 | AY74: -333
E75: Diretoria - 25.11.25 | F75: -6666.6667 | H75: Rafael | I75: Rescisões (Adm) | J75: -6666.6667 | K75: -0.0026666667 | L75: -6666.6667 | M75: -0.0033333333 | N75: -6666.6667 | O75: -0.0041064887 | P75: =IFERROR(VLOOKUP($I75,RESUMO!$A$3:$M$200,2,FALSE),"") -> 879.73 | Q75: =IFERROR((P75*-1)/N75-1,"") -> -0.8680405 | R75: -6666.6667 | S75: -0.0029949248 | T75: =IFERROR(VLOOKUP($I75,RESUMO!$A$3:$M$200,3,FALSE),"") -> 0 | U75: =IFERROR((T75*-1)/R75-1,"") -> -1 | V75: -6666.6667 | W75: -0.0023805879 | X75: =IFERROR(VLOOKUP($I75,RESUMO!$A$3:$M$200,4,FALSE),"") -> 11928.27 | Y75: =IFERROR((X75*-1)/V75-1,"") -> 0.7892405 | Z75: -6666.6667 | AA75: -0.0027251931 | AB75: =IFERROR(VLOOKUP($I75,RESUMO!$A$3:$M$200,5,FALSE),"") -> 12417.35 | AC75: =IFERROR((AB75*-1)/Z75-1,"") -> 0.8626025 | AD75: -6666.6667 | AE75: -0.0026012554 | AF75: =IFERROR(VLOOKUP($I75,RESUMO!$A$3:$M$200,6,FALSE),"") -> 0 | AG75: =IFERROR((AF75*-1)/AD75-1,"") -> -1 | AH75: -6666.6667 | AI75: -0.003006129 | AJ75: -6666.6667 | AK75: -0.0029680159 | AL75: -6666.6667 | AM75: -0.002477315 | AN75: -6666.6667 | AO75: -0.0022375811 | AP75: -6666.6667 | AQ75: -0.0022136888 | AR75: -6666.6667 | AS75: -0.0024343591 | AT75: -6666.6667 | AU75: -0.0027139205 | AW75: -80000 | AX75: -0.0026666667 | AY75: -6666.6667
E76: Sem Histórico | H76: Rafael | I76: Indenização Trabalhista | J76: 0 | K76: 0 | L76: 0 | M76: 0 | N76: 0 | O76: 0 | P76: =IFERROR(VLOOKUP($I76,RESUMO!$A$3:$M$200,2,FALSE),"") | Q76: =IFERROR((P76*-1)/N76-1,"") | R76: 0 | S76: 0 | T76: =IFERROR(VLOOKUP($I76,RESUMO!$A$3:$M$200,3,FALSE),"") | U76: =IFERROR((T76*-1)/R76-1,"") | V76: 0 | W76: 0 | X76: =IFERROR(VLOOKUP($I76,RESUMO!$A$3:$M$200,4,FALSE),"") | Y76: =IFERROR((X76*-1)/V76-1,"") | Z76: 0 | AA76: 0 | AB76: =IFERROR(VLOOKUP($I76,RESUMO!$A$3:$M$200,5,FALSE),"") | AC76: =IFERROR((AB76*-1)/Z76-1,"") | AD76: 0 | AE76: 0 | AF76: =IFERROR(VLOOKUP($I76,RESUMO!$A$3:$M$200,6,FALSE),"") | AG76: =IFERROR((AF76*-1)/AD76-1,"") | AH76: 0 | AI76: 0 | AJ76: 0 | AK76: 0 | AL76: 0 | AM76: 0 | AN76: 0 | AO76: 0 | AP76: 0 | AQ76: 0 | AR76: 0 | AS76: 0 | AT76: 0 | AU76: 0 | AW76: 0 | AX76: 0 | AY76: 0
B77: $ | C77: 1 | D77: 9 | E77: $ 1-9 de 2025 | F77: -305.81 | H77: Rafael | I77: Assistência Médica (Adm) | J77: -305.81 | K77: -0.000122324 | L77: -305.81 | M77: -0.000152905 | N77: -305.81 | O77: -0.0001883708 | P77: =IFERROR(VLOOKUP($I77,RESUMO!$A$3:$M$200,2,FALSE),"") -> 0 | Q77: =IFERROR((P77*-1)/N77-1,"") -> -1 | R77: -305.81 | S77: -0.00013738169 | T77: =IFERROR(VLOOKUP($I77,RESUMO!$A$3:$M$200,3,FALSE),"") -> 75 | U77: =IFERROR((T77*-1)/R77-1,"") -> -0.75474968 | V77: -305.81 | W77: -0.00010920114 | X77: =IFERROR(VLOOKUP($I77,RESUMO!$A$3:$M$200,4,FALSE),"") -> 0 | Y77: =IFERROR((X77*-1)/V77-1,"") -> -1 | Z77: -305.81 | AA77: -0.0001250087 | AB77: =IFERROR(VLOOKUP($I77,RESUMO!$A$3:$M$200,5,FALSE),"") -> 0 | AC77: =IFERROR((AB77*-1)/Z77-1,"") -> -1 | AD77: -305.81 | AE77: -0.00011932348 | AF77: =IFERROR(VLOOKUP($I77,RESUMO!$A$3:$M$200,6,FALSE),"") -> 0 | AG77: =IFERROR((AF77*-1)/AD77-1,"") -> -1 | AH77: -305.81 | AI77: -0.00013789565 | AJ77: -305.81 | AK77: -0.00013614734 | AL77: -305.81 | AM77: -0.00011363815 | AN77: -305.81 | AO77: -0.0001026412 | AP77: -305.81 | AQ77: -0.00010154523 | AR77: -305.81 | AS77: -0.0001116677 | AT77: -305.81 | AU77: -0.0001244916 | AW77: -3669.72 | AX77: -0.000122324 | AY77: -305.81
E78: Média + IPCA | F78: -608.86933 | H78: Rafael | I78: Seguro de Vida (Adm) | J78: -608.86933 | K78: -0.00024354773 | L78: -608.86933 | M78: -0.00030443467 | N78: -608.86933 | O78: -0.00037504726 | P78: =IFERROR(VLOOKUP($I78,RESUMO!$A$3:$M$200,2,FALSE),"") -> 650.3 | Q78: =IFERROR((P78*-1)/N78-1,"") -> 0.068045251 | R78: -608.86933 | S78: -0.00027352768 | T78: =IFERROR(VLOOKUP($I78,RESUMO!$A$3:$M$200,3,FALSE),"") -> 721.42 | U78: =IFERROR((T78*-1)/R78-1,"") -> 0.18485192 | V78: -608.86933 | W78: -0.00021742004 | X78: =IFERROR(VLOOKUP($I78,RESUMO!$A$3:$M$200,4,FALSE),"") -> 596.62 | Y78: =IFERROR((X78*-1)/V78-1,"") -> -0.020118164 | Z78: -608.86933 | AA78: -0.00024889298 | AB78: =IFERROR(VLOOKUP($I78,RESUMO!$A$3:$M$200,5,FALSE),"") -> 600.63 | AC78: =IFERROR((AB78*-1)/Z78-1,"") -> -0.013532186 | AD78: -608.86933 | AE78: -0.00023757369 | AF78: =IFERROR(VLOOKUP($I78,RESUMO!$A$3:$M$200,6,FALSE),"") -> 0 | AG78: =IFERROR((AF78*-1)/AD78-1,"") -> -1 | AH78: -608.86933 | AI78: -0.00027455097 | AJ78: -608.86933 | AK78: -0.00027107008 | AL78: -608.86933 | AM78: -0.00022625417 | AN78: -608.86933 | AO78: -0.00020435918 | AP78: -608.86933 | AQ78: -0.00020217709 | AR78: -608.86933 | AS78: -0.00022233099 | AT78: -608.86933 | AU78: -0.00024786344 | AW78: -7306.432 | AX78: -0.00024354773 | AY78: -608.86933
E79: Provisão | F79: 0.18 | H79: Rafael | I79: INSS (Adm) | J79: -10891.814 | K79: -0.0043567257 | L79: -10891.814 | M79: -0.0054459072 | N79: -10891.814 | O79: -0.006709067 | P79: =IFERROR(VLOOKUP($I79,RESUMO!$A$3:$M$200,2,FALSE),"") -> 22949.23 | Q79: =IFERROR((P79*-1)/N79-1,"") -> 1.1070163 | R79: -10891.814 | S79: -0.0048930247 | T79: =IFERROR(VLOOKUP($I79,RESUMO!$A$3:$M$200,3,FALSE),"") -> 17763.09 | U79: =IFERROR((T79*-1)/R79-1,"") -> 0.63086603 | V79: -10891.814 | W79: -0.0038893382 | X79: =IFERROR(VLOOKUP($I79,RESUMO!$A$3:$M$200,4,FALSE),"") -> 20718.49 | Y79: =IFERROR((X79*-1)/V79-1,"") -> 0.90220741 | Z79: -10891.814 | AA79: -0.0044523446 | AB79: =IFERROR(VLOOKUP($I79,RESUMO!$A$3:$M$200,5,FALSE),"") -> 178.31 | AC79: =IFERROR((AB79*-1)/Z79-1,"") -> -0.98362899 | AD79: -11599.782 | AE79: -0.0045260994 | AF79: =IFERROR(VLOOKUP($I79,RESUMO!$A$3:$M$200,6,FALSE),"") -> 0 | AG79: =IFERROR((AF79*-1)/AD79-1,"") -> -1 | AH79: -11599.782 | AI79: -0.0052305663 | AJ79: -11599.782 | AK79: -0.0051642508 | AL79: -11599.782 | AM79: -0.0043104472 | AN79: -11599.782 | AO79: -0.003893318 | AP79: -11599.782 | AQ79: -0.0038517462 | AR79: -11599.782 | AS79: -0.0042357053 | AT79: -11599.782 | AU79: -0.004722133 | AW79: -136365.52 | AX79: -0.0045455172 | AY79: -11363.793
E80: Provisão | F80: 0.08 | H80: Rafael | I80: FGTS (Adm) | J80: -4840.8064 | K80: -0.0019363226 | L80: -4840.8064 | M80: -0.0024204032 | N80: -4840.8064 | O80: -0.0029818075 | P80: =IFERROR(VLOOKUP($I80,RESUMO!$A$3:$M$200,2,FALSE),"") -> 8774.55 | Q80: =IFERROR((P80*-1)/N80-1,"") -> 0.81262156 | R80: -4840.8064 | S80: -0.0021746776 | T80: =IFERROR(VLOOKUP($I80,RESUMO!$A$3:$M$200,3,FALSE),"") -> 9673.71 | U80: =IFERROR((T80*-1)/R80-1,"") -> 0.99836747 | V80: -4840.8064 | W80: -0.0017285947 | X80: =IFERROR(VLOOKUP($I80,RESUMO!$A$3:$M$200,4,FALSE),"") -> 8826.9 | Y80: =IFERROR((X80*-1)/V80-1,"") -> 0.82343587 | Z80: -4840.8064 | AA80: -0.0019788198 | AB80: =IFERROR(VLOOKUP($I80,RESUMO!$A$3:$M$200,5,FALSE),"") -> 0 | AC80: =IFERROR((AB80*-1)/Z80-1,"") -> -1 | AD80: -5155.4588 | AE80: -0.0020115997 | AF80: =IFERROR(VLOOKUP($I80,RESUMO!$A$3:$M$200,6,FALSE),"") -> 0 | AG80: =IFERROR((AF80*-1)/AD80-1,"") -> -1 | AH80: -5155.4588 | AI80: -0.0023246961 | AJ80: -5155.4588 | AK80: -0.0022952226 | AL80: -5155.4588 | AM80: -0.0019157543 | AN80: -5155.4588 | AO80: -0.0017303636 | AP80: -5155.4588 | AQ80: -0.0017118872 | AR80: -5155.4588 | AS80: -0.0018825357 | AT80: -5155.4588 | AU80: -0.0020987258 | AW80: -60606.896 | AX80: -0.0020202299 | AY80: -5050.5747
B81: $ | C81: 1 | D81: 9 | E81: $ 1-9 de 2025 | F81: -30 | H81: Rafael | I81: Medicina e Seguranca do Trabalho (Adm) | J81: -30 | K81: -1.2e-05 | L81: -30 | M81: -1.5e-05 | N81: -30 | O81: -1.8479199e-05 | P81: =IFERROR(VLOOKUP($I81,RESUMO!$A$3:$M$200,2,FALSE),"") | Q81: =IFERROR((P81*-1)/N81-1,"") | R81: -30 | S81: -1.3477162e-05 | T81: =IFERROR(VLOOKUP($I81,RESUMO!$A$3:$M$200,3,FALSE),"") | U81: =IFERROR((T81*-1)/R81-1,"") | V81: -30 | W81: -1.0712645e-05 | X81: =IFERROR(VLOOKUP($I81,RESUMO!$A$3:$M$200,4,FALSE),"") | Y81: =IFERROR((X81*-1)/V81-1,"") | Z81: -30 | AA81: -1.2263369e-05 | AB81: =IFERROR(VLOOKUP($I81,RESUMO!$A$3:$M$200,5,FALSE),"") | AC81: =IFERROR((AB81*-1)/Z81-1,"") | AD81: -30 | AE81: -1.1705649e-05 | AF81: =IFERROR(VLOOKUP($I81,RESUMO!$A$3:$M$200,6,FALSE),"") | AG81: =IFERROR((AF81*-1)/AD81-1,"") | AH81: -30 | AI81: -1.3527581e-05 | AJ81: -30 | AK81: -1.3356072e-05 | AL81: -30 | AM81: -1.1147917e-05 | AN81: -30 | AO81: -1.0069115e-05 | AP81: -30 | AQ81: -9.9615997e-06 | AR81: -30 | AS81: -1.0954616e-05 | AT81: -30 | AU81: -1.2212642e-05 | AW81: -360 | AX81: -1.2e-05 | AY81: -30
B82: $ | C82: 1 | D82: 9 | E82: $ 1-9 de 2025 | F82: -2086.7233 | H82: Rafael | I82: Manutenção Predial (Adm) | J82: -2086.7233 | K82: -0.00083468933 | L82: -2086.7233 | M82: -0.0010433617 | N82: -2086.7233 | O82: -0.0012853659 | P82: =IFERROR(VLOOKUP($I82,RESUMO!$A$3:$M$200,2,FALSE),"") -> 2233.96 | Q82: =IFERROR((P82*-1)/N82-1,"") -> 0.070558787 | R82: -2086.7233 | S82: -0.00093743691 | T82: =IFERROR(VLOOKUP($I82,RESUMO!$A$3:$M$200,3,FALSE),"") -> 2457.64 | U82: =IFERROR((T82*-1)/R82-1,"") -> 0.17775076 | V82: -2086.7233 | W82: -0.00074514424 | X82: =IFERROR(VLOOKUP($I82,RESUMO!$A$3:$M$200,4,FALSE),"") -> 1143.76 | Y82: =IFERROR((X82*-1)/V82-1,"") -> -0.45188709 | Z82: -2086.7233 | AA82: -0.0008530086 | AB82: =IFERROR(VLOOKUP($I82,RESUMO!$A$3:$M$200,5,FALSE),"") -> 8026.26 | AC82: =IFERROR((AB82*-1)/Z82-1,"") -> 2.846346 | AD82: -2086.7233 | AE82: -0.00081421504 | AF82: =IFERROR(VLOOKUP($I82,RESUMO!$A$3:$M$200,6,FALSE),"") -> 0 | AG82: =IFERROR((AF82*-1)/AD82-1,"") -> -1 | AH82: -2086.7233 | AI82: -0.00094094393 | AJ82: -2086.7233 | AK82: -0.00092901421 | AL82: -2086.7233 | AM82: -0.00077542065 | AN82: -2086.7233 | AO82: -0.0007003819 | AP82: -2086.7233 | AQ82: -0.00069290342 | AR82: -2086.7233 | AS82: -0.00076197509 | AT82: -2086.7233 | AU82: -0.00084948018 | AW82: -25040.68 | AX82: -0.00083468933 | AY82: -2086.7233
E83: Diretoria - 25.11.25 | F83: -5833.3333 | H83: Mylena | I83: Cursos e Treinamentos (Adm) | J83: -5833.3333 | K83: -0.0023333333 | L83: -5833.3333 | M83: -0.0029166667 | N83: -5833.3333 | O83: -0.0035931777 | P83: =IFERROR(VLOOKUP($I83,RESUMO!$A$3:$M$200,2,FALSE),"") -> 2231.33 | Q83: =IFERROR((P83*-1)/N83-1,"") -> -0.61748629 | R83: -5833.3333 | S83: -0.0026205592 | T83: =IFERROR(VLOOKUP($I83,RESUMO!$A$3:$M$200,3,FALSE),"") -> 4424.49 | U83: =IFERROR((T83*-1)/R83-1,"") -> -0.241516 | V83: -5833.3333 | W83: -0.0020830144 | X83: =IFERROR(VLOOKUP($I83,RESUMO!$A$3:$M$200,4,FALSE),"") -> 1873.76 | Y83: =IFERROR((X83*-1)/V83-1,"") -> -0.678784 | Z83: -5833.3333 | AA83: -0.002384544 | AB83: =IFERROR(VLOOKUP($I83,RESUMO!$A$3:$M$200,5,FALSE),"") -> 2785.58 | AC83: =IFERROR((AB83*-1)/Z83-1,"") -> -0.522472 | AD83: -5833.3333 | AE83: -0.0022760984 | AF83: =IFERROR(VLOOKUP($I83,RESUMO!$A$3:$M$200,6,FALSE),"") -> 0 | AG83: =IFERROR((AF83*-1)/AD83-1,"") -> -1 | AH83: -5833.3333 | AI83: -0.0026303629 | AJ83: -5833.3333 | AK83: -0.0025970139 | AL83: -5833.3333 | AM83: -0.0021676506 | AN83: -5833.3333 | AO83: -0.0019578835 | AP83: -5833.3333 | AQ83: -0.0019369777 | AR83: -5833.3333 | AS83: -0.0021300642 | AT83: -5833.3333 | AU83: -0.0023746804 | AW83: -70000 | AX83: -0.0023333333 | AY83: -5833.3333
E84: Diretoria - 25.11.25 | F84: -2500 | H84: Mylena | I84: Confraternização | J84: -2500 | K84: -0.001 | L84: -2500 | M84: -0.00125 | N84: -2500 | O84: -0.0015399333 | P84: =IFERROR(VLOOKUP($I84,RESUMO!$A$3:$M$200,2,FALSE),"") -> 3330.86 | Q84: =IFERROR((P84*-1)/N84-1,"") -> 0.332344 | R84: -2500 | S84: -0.0011230968 | T84: =IFERROR(VLOOKUP($I84,RESUMO!$A$3:$M$200,3,FALSE),"") -> 369.46 | U84: =IFERROR((T84*-1)/R84-1,"") -> -0.852216 | V84: -2500 | W84: -0.00089272045 | X84: =IFERROR(VLOOKUP($I84,RESUMO!$A$3:$M$200,4,FALSE),"") -> 1065.51 | Y84: =IFERROR((X84*-1)/V84-1,"") -> -0.573796 | Z84: -2500 | AA84: -0.0010219474 | AB84: =IFERROR(VLOOKUP($I84,RESUMO!$A$3:$M$200,5,FALSE),"") -> 170.15 | AC84: =IFERROR((AB84*-1)/Z84-1,"") -> -0.93194 | AD84: -2500 | AE84: -0.00097547076 | AF84: =IFERROR(VLOOKUP($I84,RESUMO!$A$3:$M$200,6,FALSE),"") -> 1239.32 | AG84: =IFERROR((AF84*-1)/AD84-1,"") -> -0.504272 | AH84: -2500 | AI84: -0.0011272984 | AJ84: -2500 | AK84: -0.001113006 | AL84: -2500 | AM84: -0.00092899312 | AN84: -2500 | AO84: -0.00083909291 | AP84: -2500 | AQ84: -0.00083013331 | AR84: -2500 | AS84: -0.00091288466 | AT84: -2500 | AU84: -0.0010177202 | AW84: -30000 | AX84: -0.001 | AY84: -2500
I85: Despesas Administrativas | J85: -20355.613 | K85: -0.0081422453 | L85: -20355.613 | M85: -0.010177807 | N85: -20355.613 | O85: -0.012538515 | P85: =SUM(P86:P100) -> 16694.4 | Q85: =(P85*-1)/N85-1 -> -0.17986259 | R85: -20355.613 | S85: -0.0091445296 | T85: =SUM(T86:T100) -> 18621.32 | U85: =(T85*-1)/R85-1 -> -0.085199755 | V85: -20355.613 | W85: -0.0072687489 | X85: =SUM(X86:X100) -> 17985.82 | Y85: =(X85*-1)/V85-1 -> -0.11641964 | Z85: -20355.613 | AA85: -0.0083209465 | AB85: =SUM(AB86:AB100) -> 18594.11 | AC85: =(AB85*-1)/Z85-1 -> -0.086536487 | AD85: -20355.613 | AE85: -0.0079425222 | AF85: =SUM(AF86:AF100) -> 4525.85 | AG85: =(AF85*-1)/AD85-1 -> -0.77766084 | AH85: -20355.613 | AI85: -0.0091787399 | AJ85: -20355.613 | AK85: -0.0090623676 | AL85: -20355.613 | AM85: -0.0075640899 | AN85: -20355.613 | AO85: -0.0068321003 | AP85: -20355.613 | AQ85: -0.006759149 | AR85: -20355.613 | AS85: -0.0074329308 | AT85: -20355.613 | AU85: -0.0082865274 | AW85: -244267.36 | AX85: -0.0081422453 | AY85: -20355.613
E86: Diretoria - 25.11.25 | F86: -850 | H86: Letícia | I86: Aluguel de Imóvel | J86: -850 | K86: -0.00034 | L86: -850 | M86: -0.000425 | N86: -850 | O86: -0.00052357732 | P86: =IFERROR(VLOOKUP($I86,RESUMO!$A$3:$M$200,2,FALSE),"") -> 800 | Q86: =IFERROR((P86*-1)/N86-1,"") -> -0.058823529 | R86: -850 | S86: -0.00038185291 | T86: =IFERROR(VLOOKUP($I86,RESUMO!$A$3:$M$200,3,FALSE),"") -> 900 | U86: =IFERROR((T86*-1)/R86-1,"") -> 0.058823529 | V86: -850 | W86: -0.00030352495 | X86: =IFERROR(VLOOKUP($I86,RESUMO!$A$3:$M$200,4,FALSE),"") -> 900 | Y86: =IFERROR((X86*-1)/V86-1,"") -> 0.058823529 | Z86: -850 | AA86: -0.00034746212 | AB86: =IFERROR(VLOOKUP($I86,RESUMO!$A$3:$M$200,5,FALSE),"") -> 900 | AC86: =IFERROR((AB86*-1)/Z86-1,"") -> 0.058823529 | AD86: -850 | AE86: -0.00033166006 | AF86: =IFERROR(VLOOKUP($I86,RESUMO!$A$3:$M$200,6,FALSE),"") -> 900 | AG86: =IFERROR((AF86*-1)/AD86-1,"") -> 0.058823529 | AH86: -850 | AI86: -0.00038328145 | AJ86: -850 | AK86: -0.00037842203 | AL86: -850 | AM86: -0.00031585766 | AN86: -850 | AO86: -0.00028529159 | AP86: -850 | AQ86: -0.00028224532 | AR86: -850 | AS86: -0.00031038078 | AT86: -850 | AU86: -0.00034602486 | AW86: -10200 | AX86: -0.00034 | AY86: -850
B87: $ | C87: 1 | D87: 9 | E87: $ 1-9 de 2025 | F87: -30.98 | H87: Letícia | I87: Água | J87: -30.98 | K87: -1.2392e-05 | L87: -30.98 | M87: -1.549e-05 | N87: -30.98 | O87: -1.9082853e-05 | P87: =IFERROR(VLOOKUP($I87,RESUMO!$A$3:$M$200,2,FALSE),"") -> 32.23 | Q87: =IFERROR((P87*-1)/N87-1,"") -> 0.040348612 | R87: -30.98 | S87: -1.3917415e-05 | T87: =IFERROR(VLOOKUP($I87,RESUMO!$A$3:$M$200,3,FALSE),"") -> 32.23 | U87: =IFERROR((T87*-1)/R87-1,"") -> 0.040348612 | V87: -30.98 | W87: -1.1062592e-05 | X87: =IFERROR(VLOOKUP($I87,RESUMO!$A$3:$M$200,4,FALSE),"") -> 32.23 | Y87: =IFERROR((X87*-1)/V87-1,"") -> 0.040348612 | Z87: -30.98 | AA87: -1.2663972e-05 | AB87: =IFERROR(VLOOKUP($I87,RESUMO!$A$3:$M$200,5,FALSE),"") -> 32.23 | AC87: =IFERROR((AB87*-1)/Z87-1,"") -> 0.040348612 | AD87: -30.98 | AE87: -1.2088034e-05 | AF87: =IFERROR(VLOOKUP($I87,RESUMO!$A$3:$M$200,6,FALSE),"") -> 0 | AG87: =IFERROR((AF87*-1)/AD87-1,"") -> -1 | AH87: -30.98 | AI87: -1.3969482e-05 | AJ87: -30.98 | AK87: -1.379237e-05 | AL87: -30.98 | AM87: -1.1512083e-05 | AN87: -30.98 | AO87: -1.0398039e-05 | AP87: -30.98 | AQ87: -1.0287012e-05 | AR87: -30.98 | AS87: -1.1312467e-05 | AT87: -30.98 | AU87: -1.2611589e-05 | AW87: -371.76 | AX87: -1.2392e-05 | AY87: -30.98
B88: $ | C88: 1 | D88: 9 | E88: $ 1-9 de 2025 | F88: -59.852857 | H88: Letícia | I88: Energia Eletrica (Adm) | J88: -59.852857 | K88: -2.3941143e-05 | L88: -59.852857 | M88: -2.9926429e-05 | N88: -59.852857 | O88: -3.6867763e-05 | P88: =IFERROR(VLOOKUP($I88,RESUMO!$A$3:$M$200,2,FALSE),"") -> 98.41 | Q88: =IFERROR((P88*-1)/N88-1,"") -> 0.64419887 | R88: -59.852857 | S88: -2.6888221e-05 | T88: =IFERROR(VLOOKUP($I88,RESUMO!$A$3:$M$200,3,FALSE),"") -> 91.95 | U88: =IFERROR((T88*-1)/R88-1,"") -> 0.53626751 | V88: -59.852857 | W88: -2.1372748e-05 | X88: =IFERROR(VLOOKUP($I88,RESUMO!$A$3:$M$200,4,FALSE),"") -> 0 | Y88: =IFERROR((X88*-1)/V88-1,"") -> -1 | Z88: -59.852857 | AA88: -2.4466589e-05 | AB88: =IFERROR(VLOOKUP($I88,RESUMO!$A$3:$M$200,5,FALSE),"") -> 91.72 | AC88: =IFERROR((AB88*-1)/Z88-1,"") -> 0.53242476 | AD88: -59.852857 | AE88: -2.3353885e-05 | AF88: =IFERROR(VLOOKUP($I88,RESUMO!$A$3:$M$200,6,FALSE),"") -> 0 | AG88: =IFERROR((AF88*-1)/AD88-1,"") -> -1 | AH88: -59.852857 | AI88: -2.6988812e-05 | AJ88: -59.852857 | AK88: -2.6646635e-05 | AL88: -59.852857 | AM88: -2.2241157e-05 | AN88: -59.852857 | AO88: -2.0088843e-05 | AP88: -59.852857 | AQ88: -1.987434e-05 | AR88: -59.852857 | AS88: -2.1855502e-05 | AT88: -59.852857 | AU88: -2.4365384e-05 | AW88: -718.23429 | AX88: -2.3941143e-05 | AY88: -59.852857
B89: $ | C89: 1 | D89: 9 | E89: $ 1-9 de 2025 | F89: -2262.6267 | H89: Letícia | I89: Telefone e Internet | J89: -2262.6267 | K89: -0.00090505067 | L89: -2262.6267 | M89: -0.0011313133 | N89: -2262.6267 | O89: -0.0013937176 | P89: =IFERROR(VLOOKUP($I89,RESUMO!$A$3:$M$200,2,FALSE),"") -> 1996.05 | Q89: =IFERROR((P89*-1)/N89-1,"") -> -0.11781735 | R89: -2262.6267 | S89: -0.0010164595 | T89: =IFERROR(VLOOKUP($I89,RESUMO!$A$3:$M$200,3,FALSE),"") -> 2146.02 | U89: =IFERROR((T89*-1)/R89-1,"") -> -0.051535973 | V89: -2262.6267 | W89: -0.00080795724 | X89: =IFERROR(VLOOKUP($I89,RESUMO!$A$3:$M$200,4,FALSE),"") -> 2146.02 | Y89: =IFERROR((X89*-1)/V89-1,"") -> -0.051535973 | Z89: -2262.6267 | AA89: -0.00092491419 | AB89: =IFERROR(VLOOKUP($I89,RESUMO!$A$3:$M$200,5,FALSE),"") -> 2146.02 | AC89: =IFERROR((AB89*-1)/Z89-1,"") -> -0.051535973 | AD89: -2262.6267 | AE89: -0.00088285046 | AF89: =IFERROR(VLOOKUP($I89,RESUMO!$A$3:$M$200,6,FALSE),"") -> 464.9 | AG89: =IFERROR((AF89*-1)/AD89-1,"") -> -0.79453084 | AH89: -2262.6267 | AI89: -0.0010202622 | AJ89: -2262.6267 | AK89: -0.0010073268 | AL89: -2262.6267 | AM89: -0.00084078585 | AN89: -2262.6267 | AO89: -0.0007594216 | AP89: -2262.6267 | AQ89: -0.0007513127 | AR89: -2262.6267 | AS89: -0.00082620687 | AT89: -2262.6267 | AU89: -0.00092108833 | AW89: -27151.52 | AX89: -0.00090505067 | AY89: -2262.6267
B90: $ | C90: 1 | D90: 9 | E90: $ 1-9 de 2025 | F90: -410.715 | H90: Letícia | I90: Material de Expediente (Adm) | J90: -410.715 | K90: -0.000164286 | L90: -410.715 | M90: -0.0002053575 | N90: -410.715 | O90: -0.00025298948 | P90: =IFERROR(VLOOKUP($I90,RESUMO!$A$3:$M$200,2,FALSE),"") -> 111.89 | Q90: =IFERROR((P90*-1)/N90-1,"") -> -0.72757265 | R90: -410.715 | S90: -0.00018450908 | T90: =IFERROR(VLOOKUP($I90,RESUMO!$A$3:$M$200,3,FALSE),"") -> 373.27 | U90: =IFERROR((T90*-1)/R90-1,"") -> -0.091170276 | V90: -410.715 | W90: -0.00014666147 | X90: =IFERROR(VLOOKUP($I90,RESUMO!$A$3:$M$200,4,FALSE),"") -> 382.17 | Y90: =IFERROR((X90*-1)/V90-1,"") -> -0.069500749 | Z90: -410.715 | AA90: -0.00016789165 | AB90: =IFERROR(VLOOKUP($I90,RESUMO!$A$3:$M$200,5,FALSE),"") -> 671.82 | AC90: =IFERROR((AB90*-1)/Z90-1,"") -> 0.63573281 | AD90: -410.715 | AE90: -0.00016025619 | AF90: =IFERROR(VLOOKUP($I90,RESUMO!$A$3:$M$200,6,FALSE),"") -> 0 | AG90: =IFERROR((AF90*-1)/AD90-1,"") -> -1 | AH90: -410.715 | AI90: -0.00018519934 | AJ90: -410.715 | AK90: -0.0001828513 | AL90: -410.715 | AM90: -0.00015262056 | AN90: -410.715 | AO90: -0.00013785122 | AP90: -410.715 | AQ90: -0.00013637928 | AR90: -410.715 | AS90: -0.00014997417 | AT90: -410.715 | AU90: -0.00016719718 | AW90: -4928.58 | AX90: -0.000164286 | AY90: -410.715
B91: $ | C91: 1 | D91: 9 | E91: $ 1-9 de 2025 | F91: -680.29429 | H91: Mylena | I91: Material de Limpeza (Adm) | J91: -680.29429 | K91: -0.00027211771 | L91: -680.29429 | M91: -0.00034014714 | N91: -680.29429 | O91: -0.00041904312 | P91: =IFERROR(VLOOKUP($I91,RESUMO!$A$3:$M$200,2,FALSE),"") -> 367.37 | Q91: =IFERROR((P91*-1)/N91-1,"") -> -0.4599837 | R91: -680.29429 | S91: -0.00030561453 | T91: =IFERROR(VLOOKUP($I91,RESUMO!$A$3:$M$200,3,FALSE),"") -> 577.9 | U91: =IFERROR((T91*-1)/R91-1,"") -> -0.15051469 | V91: -680.29429 | W91: -0.00024292505 | X91: =IFERROR(VLOOKUP($I91,RESUMO!$A$3:$M$200,4,FALSE),"") -> 427.23 | Y91: =IFERROR((X91*-1)/V91-1,"") -> -0.37199237 | Z91: -680.29429 | AA91: -0.00027808999 | AB91: =IFERROR(VLOOKUP($I91,RESUMO!$A$3:$M$200,5,FALSE),"") -> 448.1 | AC91: =IFERROR((AB91*-1)/Z91-1,"") -> -0.34131447 | AD91: -680.29429 | AE91: -0.00026544287 | AF91: =IFERROR(VLOOKUP($I91,RESUMO!$A$3:$M$200,6,FALSE),"") -> 902.98 | AG91: =IFERROR((AF91*-1)/AD91-1,"") -> 0.32733733 | AH91: -680.29429 | AI91: -0.00030675786 | AJ91: -680.29429 | AK91: -0.00030286864 | AL91: -680.29429 | AM91: -0.00025279549 | AN91: -680.29429 | AO91: -0.00022833204 | AP91: -680.29429 | AQ91: -0.00022589398 | AR91: -680.29429 | AS91: -0.00024841209 | AT91: -680.29429 | AU91: -0.00027693969 | AW91: -8163.5314 | AX91: -0.00027211771 | AY91: -680.29429
B92: $ | C92: 1 | D92: 9 | E92: $ 1-9 de 2025 | F92: -224.60667 | H92: Letícia | I92: Copa | J92: -224.60667 | K92: -8.9842667e-05 | L92: -224.60667 | M92: -0.00011230333 | N92: -224.60667 | O92: -0.00013835171 | P92: =IFERROR(VLOOKUP($I92,RESUMO!$A$3:$M$200,2,FALSE),"") -> 15.99 | Q92: =IFERROR((P92*-1)/N92-1,"") -> -0.92880888 | R92: -224.60667 | S92: -0.00010090201 | T92: =IFERROR(VLOOKUP($I92,RESUMO!$A$3:$M$200,3,FALSE),"") -> 368.6 | U92: =IFERROR((T92*-1)/R92-1,"") -> 0.64109109 | V92: -224.60667 | W92: -8.0204386e-05 | X92: =IFERROR(VLOOKUP($I92,RESUMO!$A$3:$M$200,4,FALSE),"") -> 150.63 | Y92: =IFERROR((X92*-1)/V92-1,"") -> -0.32936096 | Z92: -224.60667 | AA92: -9.1814481e-05 | AB92: =IFERROR(VLOOKUP($I92,RESUMO!$A$3:$M$200,5,FALSE),"") -> 243.83 | AC92: =IFERROR((AB92*-1)/Z92-1,"") -> 0.085586655 | AD92: -224.60667 | AE92: -8.7638894e-05 | AF92: =IFERROR(VLOOKUP($I92,RESUMO!$A$3:$M$200,6,FALSE),"") -> 0 | AG92: =IFERROR((AF92*-1)/AD92-1,"") -> -1 | AH92: -224.60667 | AI92: -0.00010127949 | AJ92: -224.60667 | AK92: -9.9995424e-05 | AL92: -224.60667 | AM92: -8.346322e-05 | AN92: -224.60667 | AO92: -7.5386345e-05 | AP92: -224.60667 | AQ92: -7.458139e-05 | AR92: -224.60667 | AS92: -8.2015992e-05 | AT92: -224.60667 | AU92: -9.1434695e-05 | AW92: -2695.28 | AX92: -8.9842667e-05 | AY92: -224.60667
E93: Diretoria - 25.11.25 | F93: -550 | H93: Letícia | I93: SPC/Serasa/Associacao | J93: -550 | K93: -0.00022 | L93: -550 | M93: -0.000275 | N93: -550 | O93: -0.00033878532 | P93: =IFERROR(VLOOKUP($I93,RESUMO!$A$3:$M$200,2,FALSE),"") -> 351 | Q93: =IFERROR((P93*-1)/N93-1,"") -> -0.36181818 | R93: -550 | S93: -0.00024708129 | T93: =IFERROR(VLOOKUP($I93,RESUMO!$A$3:$M$200,3,FALSE),"") -> 617.44 | U93: =IFERROR((T93*-1)/R93-1,"") -> 0.12261818 | V93: -550 | W93: -0.0001963985 | X93: =IFERROR(VLOOKUP($I93,RESUMO!$A$3:$M$200,4,FALSE),"") -> 351 | Y93: =IFERROR((X93*-1)/V93-1,"") -> -0.36181818 | Z93: -550 | AA93: -0.00022482843 | AB93: =IFERROR(VLOOKUP($I93,RESUMO!$A$3:$M$200,5,FALSE),"") -> 351 | AC93: =IFERROR((AB93*-1)/Z93-1,"") -> -0.36181818 | AD93: -550 | AE93: -0.00021460357 | AF93: =IFERROR(VLOOKUP($I93,RESUMO!$A$3:$M$200,6,FALSE),"") -> 0 | AG93: =IFERROR((AF93*-1)/AD93-1,"") -> -1 | AH93: -550 | AI93: -0.00024800564 | AJ93: -550 | AK93: -0.00024486131 | AL93: -550 | AM93: -0.00020437849 | AN93: -550 | AO93: -0.00018460044 | AP93: -550 | AQ93: -0.00018262933 | AR93: -550 | AS93: -0.00020083463 | AT93: -550 | AU93: -0.00022389844 | AW93: -6600 | AX93: -0.00022 | AY93: -550
E94: Diretoria - 25.11.25 | F94: -416.66667 | H94: Letícia | I94: Despesas Cartorárias | J94: -416.66667 | K94: -0.00016666667 | L94: -416.66667 | M94: -0.00020833333 | N94: -416.66667 | O94: -0.00025665555 | P94: =IFERROR(VLOOKUP($I94,RESUMO!$A$3:$M$200,2,FALSE),"") -> 432.21 | Q94: =IFERROR((P94*-1)/N94-1,"") -> 0.037304 | R94: -416.66667 | S94: -0.0001871828 | T94: =IFERROR(VLOOKUP($I94,RESUMO!$A$3:$M$200,3,FALSE),"") -> 511.67 | U94: =IFERROR((T94*-1)/R94-1,"") -> 0.228008 | V94: -416.66667 | W94: -0.00014878674 | X94: =IFERROR(VLOOKUP($I94,RESUMO!$A$3:$M$200,4,FALSE),"") -> 350.68 | Y94: =IFERROR((X94*-1)/V94-1,"") -> -0.158368 | Z94: -416.66667 | AA94: -0.00017032457 | AB94: =IFERROR(VLOOKUP($I94,RESUMO!$A$3:$M$200,5,FALSE),"") -> 279.6 | AC94: =IFERROR((AB94*-1)/Z94-1,"") -> -0.32896 | AD94: -416.66667 | AE94: -0.00016257846 | AF94: =IFERROR(VLOOKUP($I94,RESUMO!$A$3:$M$200,6,FALSE),"") -> 0 | AG94: =IFERROR((AF94*-1)/AD94-1,"") -> -1 | AH94: -416.66667 | AI94: -0.00018788306 | AJ94: -416.66667 | AK94: -0.00018550099 | AL94: -416.66667 | AM94: -0.00015483219 | AN94: -416.66667 | AO94: -0.00013984882 | AP94: -416.66667 | AQ94: -0.00013835555 | AR94: -416.66667 | AS94: -0.00015214744 | AT94: -416.66667 | AU94: -0.00016962003 | AW94: -5000 | AX94: -0.00016666667 | AY94: -416.66667
B95: $ | C95: 4 | D95: 9 | E95: $ 4-9 de 2025 | F95: -11709.43 | H95: Mylena | I95: Seguros Veicular | J95: -11709.43 | K95: -0.004683772 | L95: -11709.43 | M95: -0.005854715 | N95: -11709.43 | O95: -0.0072126964 | P95: =IFERROR(VLOOKUP($I95,RESUMO!$A$3:$M$200,2,FALSE),"") -> 11212.42 | Q95: =IFERROR((P95*-1)/N95-1,"") -> -0.042445277 | R95: -11709.43 | S95: -0.0052603293 | T95: =IFERROR(VLOOKUP($I95,RESUMO!$A$3:$M$200,3,FALSE),"") -> 11212.42 | U95: =IFERROR((T95*-1)/R95-1,"") -> -0.042445277 | V95: -11709.43 | W95: -0.0041812991 | X95: =IFERROR(VLOOKUP($I95,RESUMO!$A$3:$M$200,4,FALSE),"") -> 11212.42 | Y95: =IFERROR((X95*-1)/V95-1,"") -> -0.042445277 | Z95: -11709.43 | AA95: -0.0047865687 | AB95: =IFERROR(VLOOKUP($I95,RESUMO!$A$3:$M$200,5,FALSE),"") -> 10898.11 | AC95: =IFERROR((AB95*-1)/Z95-1,"") -> -0.069287745 | AD95: -11709.43 | AE95: -0.0045688826 | AF95: =IFERROR(VLOOKUP($I95,RESUMO!$A$3:$M$200,6,FALSE),"") -> 1697.48 | AG95: =IFERROR((AF95*-1)/AD95-1,"") -> -0.85503308 | AH95: -11709.43 | AI95: -0.0052800086 | AJ95: -11709.43 | AK95: -0.0052130662 | AL95: -11709.43 | AM95: -0.004351192 | AN95: -11709.43 | AO95: -0.0039301199 | AP95: -11709.43 | AQ95: -0.0038881551 | AR95: -11709.43 | AS95: -0.0042757436 | AT95: -11709.43 | AU95: -0.0047667693 | AW95: -140513.16 | AX95: -0.004683772 | AY95: -11709.43
B96: $ | C96: 1 | D96: 9 | E96: $ 1-9 de 2025 | F96: -828.18 | H96: Letícia | I96: Combustíveis (Adm) | J96: -828.18 | K96: -0.000331272 | L96: -828.18 | M96: -0.00041409 | N96: -828.18 | O96: -0.00051013678 | P96: =IFERROR(VLOOKUP($I96,RESUMO!$A$3:$M$200,2,FALSE),"") -> 511.23 | Q96: =IFERROR((P96*-1)/N96-1,"") -> -0.38270666 | R96: -828.18 | S96: -0.00037205052 | T96: =IFERROR(VLOOKUP($I96,RESUMO!$A$3:$M$200,3,FALSE),"") -> 981.09 | U96: =IFERROR((T96*-1)/R96-1,"") -> 0.18463378 | V96: -828.18 | W96: -0.00029573329 | X96: =IFERROR(VLOOKUP($I96,RESUMO!$A$3:$M$200,4,FALSE),"") -> 780.64 | Y96: =IFERROR((X96*-1)/V96-1,"") -> -0.05740298 | Z96: -828.18 | AA96: -0.00033854256 | AB96: =IFERROR(VLOOKUP($I96,RESUMO!$A$3:$M$200,5,FALSE),"") -> 1078.18 | AC96: =IFERROR((AB96*-1)/Z96-1,"") -> 0.30186674 | AD96: -828.18 | AE96: -0.00032314615 | AF96: =IFERROR(VLOOKUP($I96,RESUMO!$A$3:$M$200,6,FALSE),"") -> 50.49 | AG96: =IFERROR((AF96*-1)/AD96-1,"") -> -0.93903499 | AH96: -828.18 | AI96: -0.00037344239 | AJ96: -828.18 | AK96: -0.00036870771 | AL96: -828.18 | AM96: -0.00030774941 | AN96: -828.18 | AO96: -0.00027796799 | AP96: -828.18 | AQ96: -0.00027499992 | AR96: -828.18 | AS96: -0.00030241313 | AT96: -828.18 | AU96: -0.0003371422 | AW96: -9938.16 | AX96: -0.000331272 | AY96: -828.18
E97: Diretoria - 25.11.25 | F97: -370 | H97: Mylena | I97: Rastreamento de frota | J97: -370 | K97: -0.000148 | L97: -370 | M97: -0.000185 | N97: -370 | O97: -0.00022791013 | P97: =IFERROR(VLOOKUP($I97,RESUMO!$A$3:$M$200,2,FALSE),"") -> 370 | Q97: =IFERROR((P97*-1)/N97-1,"") -> 0 | R97: -370 | S97: -0.00016621833 | T97: =IFERROR(VLOOKUP($I97,RESUMO!$A$3:$M$200,3,FALSE),"") -> 370 | U97: =IFERROR((T97*-1)/R97-1,"") -> 0 | V97: -370 | W97: -0.00013212263 | X97: =IFERROR(VLOOKUP($I97,RESUMO!$A$3:$M$200,4,FALSE),"") -> 370 | Y97: =IFERROR((X97*-1)/V97-1,"") -> 0 | Z97: -370 | AA97: -0.00015124822 | AB97: =IFERROR(VLOOKUP($I97,RESUMO!$A$3:$M$200,5,FALSE),"") -> 370 | AC97: =IFERROR((AB97*-1)/Z97-1,"") -> 0 | AD97: -370 | AE97: -0.00014436967 | AF97: =IFERROR(VLOOKUP($I97,RESUMO!$A$3:$M$200,6,FALSE),"") -> 370 | AG97: =IFERROR((AF97*-1)/AD97-1,"") -> 0 | AH97: -370 | AI97: -0.00016684016 | AJ97: -370 | AK97: -0.00016472488 | AL97: -370 | AM97: -0.00013749098 | AN97: -370 | AO97: -0.00012418575 | AP97: -370 | AQ97: -0.00012285973 | AR97: -370 | AS97: -0.00013510693 | AT97: -370 | AU97: -0.00015062259 | AW97: -4440 | AX97: -0.000148 | AY97: -370
B98: $ | C98: 1 | D98: 9 | E98: $ 1-9 de 2025 | F98: -79.55 | H98: Letícia | I98: Correios | J98: -79.55 | K98: -3.182e-05 | L98: -79.55 | M98: -3.9775e-05 | N98: -79.55 | O98: -4.9000677e-05 | P98: =IFERROR(VLOOKUP($I98,RESUMO!$A$3:$M$200,2,FALSE),"") | Q98: =IFERROR((P98*-1)/N98-1,"") | R98: -79.55 | S98: -3.573694e-05 | T98: =IFERROR(VLOOKUP($I98,RESUMO!$A$3:$M$200,3,FALSE),"") | U98: =IFERROR((T98*-1)/R98-1,"") | V98: -79.55 | W98: -2.8406365e-05 | X98: =IFERROR(VLOOKUP($I98,RESUMO!$A$3:$M$200,4,FALSE),"") | Y98: =IFERROR((X98*-1)/V98-1,"") | Z98: -79.55 | AA98: -3.2518367e-05 | AB98: =IFERROR(VLOOKUP($I98,RESUMO!$A$3:$M$200,5,FALSE),"") | AC98: =IFERROR((AB98*-1)/Z98-1,"") | AD98: -79.55 | AE98: -3.1039479e-05 | AF98: =IFERROR(VLOOKUP($I98,RESUMO!$A$3:$M$200,6,FALSE),"") | AG98: =IFERROR((AF98*-1)/AD98-1,"") | AH98: -79.55 | AI98: -3.5870634e-05 | AJ98: -79.55 | AK98: -3.541585e-05 | AL98: -79.55 | AM98: -2.9560561e-05 | AN98: -79.55 | AO98: -2.6699936e-05 | AP98: -79.55 | AQ98: -2.6414842e-05 | AR98: -79.55 | AS98: -2.904799e-05 | AT98: -79.55 | AU98: -3.2383856e-05 | AW98: -954.6 | AX98: -3.182e-05 | AY98: -79.55
B99: $ | C99: 1 | D99: 9 | E99: $ 1-9 de 2025 | F99: -1466.0444 | H99: Mylena | I99: Alimentação | J99: -1466.0444 | K99: -0.00058641778 | L99: -1466.0444 | M99: -0.00073302222 | N99: -1466.0444 | O99: -0.00090304425 | P99: =IFERROR(VLOOKUP($I99,RESUMO!$A$3:$M$200,2,FALSE),"") -> 295.6 | Q99: =IFERROR((P99*-1)/N99-1,"") -> -0.79836901 | R99: -1466.0444 | S99: -0.00065860393 | T99: =IFERROR(VLOOKUP($I99,RESUMO!$A$3:$M$200,3,FALSE),"") -> 338.73 | U99: =IFERROR((T99*-1)/R99-1,"") -> -0.76894971 | V99: -1466.0444 | W99: -0.00052350715 | X99: =IFERROR(VLOOKUP($I99,RESUMO!$A$3:$M$200,4,FALSE),"") -> 782.8 | Y99: =IFERROR((X99*-1)/V99-1,"") -> -0.4660462 | Z99: -1466.0444 | AA99: -0.00059928813 | AB99: =IFERROR(VLOOKUP($I99,RESUMO!$A$3:$M$200,5,FALSE),"") -> 983.5 | AC99: =IFERROR((AB99*-1)/Z99-1,"") -> -0.32914721 | AD99: -1466.0444 | AE99: -0.00057203339 | AF99: =IFERROR(VLOOKUP($I99,RESUMO!$A$3:$M$200,6,FALSE),"") -> 140 | AG99: =IFERROR((AF99*-1)/AD99-1,"") -> -0.90450494 | AH99: -1466.0444 | AI99: -0.00066106781 | AJ99: -1466.0444 | AK99: -0.00065268649 | AL99: -1466.0444 | AM99: -0.00054477808 | AN99: -1466.0444 | AO99: -0.000492059 | AP99: -1466.0444 | AQ99: -0.00048680493 | AR99: -1466.0444 | AS99: -0.00053533179 | AT99: -1466.0444 | AU99: -0.00059680921 | AW99: -17592.533 | AX99: -0.00058641778 | AY99: -1466.0444
E100: Diretoria - 25.11.25 | F100: -416.66667 | H100: Letícia | I100: Doações | J100: -416.66667 | K100: -0.00016666667 | L100: -416.66667 | M100: -0.00020833333 | N100: -416.66667 | O100: -0.00025665555 | P100: =IFERROR(VLOOKUP($I100,RESUMO!$A$3:$M$200,2,FALSE),"") -> 100 | Q100: =IFERROR((P100*-1)/N100-1,"") -> -0.76 | R100: -416.66667 | S100: -0.0001871828 | T100: =IFERROR(VLOOKUP($I100,RESUMO!$A$3:$M$200,3,FALSE),"") -> 100 | U100: =IFERROR((T100*-1)/R100-1,"") -> -0.76 | V100: -416.66667 | W100: -0.00014878674 | X100: =IFERROR(VLOOKUP($I100,RESUMO!$A$3:$M$200,4,FALSE),"") -> 100 | Y100: =IFERROR((X100*-1)/V100-1,"") -> -0.76 | Z100: -416.66667 | AA100: -0.00017032457 | AB100: =IFERROR(VLOOKUP($I100,RESUMO!$A$3:$M$200,5,FALSE),"") -> 100 | AC100: =IFERROR((AB100*-1)/Z100-1,"") -> -0.76 | AD100: -416.66667 | AE100: -0.00016257846 | AF100: =IFERROR(VLOOKUP($I100,RESUMO!$A$3:$M$200,6,FALSE),"") -> 0 | AG100: =IFERROR((AF100*-1)/AD100-1,"") -> -1 | AH100: -416.66667 | AI100: -0.00018788306 | AJ100: -416.66667 | AK100: -0.00018550099 | AL100: -416.66667 | AM100: -0.00015483219 | AN100: -416.66667 | AO100: -0.00013984882 | AP100: -416.66667 | AQ100: -0.00013835555 | AR100: -416.66667 | AS100: -0.00015214744 | AT100: -416.66667 | AU100: -0.00016962003 | AW100: -5000 | AX100: -0.00016666667 | AY100: -416.66667
I101: Despesas Comerciais | J101: -441392.12 | K101: -0.17655685 | L101: -393197.37 | M101: -0.19659869 | N101: -356901.62 | O101: -0.21984187 | P101: =SUM(P102:P122) -> 401746.29 | Q101: =(P101*-1)/N101-1 -> 0.12564996 | R101: -414980.24 | S101: -0.18642519 | T101: =SUM(T102:T122) -> 315472.21 | U101: =(T101*-1)/R101-1 -> -0.23978981 | V101: -470350.29 | W101: -0.16795653 | X101: =SUM(X102:X122) -> 387311.61 | Y101: =(X101*-1)/V101-1 -> -0.17654646 | Z101: -436216.95 | AA101: -0.17831631 | AB101: =SUM(AB102:AB122) -> 375329.97 | AC101: =(AB101*-1)/Z101-1 -> -0.13957958 | AD101: -447451.66 | AE101: -0.1745904 | AF101: =SUM(AF102:AF122) -> 110876.47 | AG101: =(AF101*-1)/AD101-1 -> -0.75220458 | AH101: -414180.54 | AI101: -0.18676202 | AJ101: -416925.52 | AK101: -0.18561624 | AL101: -459810.76 | AM101: -0.17086441 | AN101: -487602 | AO101: -0.16365735 | AP101: -490701.56 | AQ101: -0.16293908 | AR101: -464387.91 | AS101: -0.16957304 | AT101: -437196.37 | AU101: -0.17797743 | AW101: -5296705.4 | AX101: -0.17655685 | AY101: -441392.12
B102: $ | C102: 7 | D102: 9 | E102: $ 7-9 de 2025 | F102: -3751.0733 | H102: Mylena | I102: Carregamento | J102: -3751.0733 | K102: -0.0015004293 | L102: -3751.0733 | M102: -0.0018755367 | N102: -3751.0733 | O102: -0.0023105611 | P102: =IFERROR(VLOOKUP($I102,RESUMO!$A$3:$M$200,2,FALSE),"") -> 1955 | Q102: =IFERROR((P102*-1)/N102-1,"") -> -0.47881584 | R102: -3751.0733 | S102: -0.0016851274 | T102: =IFERROR(VLOOKUP($I102,RESUMO!$A$3:$M$200,3,FALSE),"") -> 2415 | U102: =IFERROR((T102*-1)/R102-1,"") -> -0.35618427 | V102: -3751.0733 | W102: -0.001339464 | X102: =IFERROR(VLOOKUP($I102,RESUMO!$A$3:$M$200,4,FALSE),"") -> 3042.48 | Y102: =IFERROR((X102*-1)/V102-1,"") -> -0.18890415 | Z102: -3751.0733 | AA102: -0.0015333599 | AB102: =IFERROR(VLOOKUP($I102,RESUMO!$A$3:$M$200,5,FALSE),"") -> 86 | AC102: =IFERROR((AB102*-1)/Z102-1,"") -> -0.97707323 | AD102: -3751.0733 | AE102: -0.0014636249 | AF102: =IFERROR(VLOOKUP($I102,RESUMO!$A$3:$M$200,6,FALSE),"") -> 0 | AG102: =IFERROR((AF102*-1)/AD102-1,"") -> -1 | AH102: -3751.0733 | AI102: -0.0016914316 | AJ102: -3751.0733 | AK102: -0.0016699868 | AL102: -3751.0733 | AM102: -0.0013938885 | AN102: -3751.0733 | AO102: -0.0012589996 | AP102: -3751.0733 | AQ102: -0.0012455564 | AR102: -3751.0733 | AS102: -0.0013697189 | AT102: -3751.0733 | AU102: -0.0015270172 | AW102: -45012.88 | AX102: -0.0015004293 | AY102: -3751.0733
E103: Diretoria - 25.11.25 | F103: -0.026 | H103: Mylena | I103: Combustiveis Frota | J103: -65000 | K103: -0.026 | L103: -52000 | M103: -0.026 | N103: -42209.621 | O103: -0.026 | P103: =IFERROR(VLOOKUP($I103,RESUMO!$A$3:$M$200,2,FALSE),"") -> 41074.3 | Q103: =IFERROR((P103*-1)/N103-1,"") -> -0.026897207 | R103: -57875.688 | S103: -0.026 | T103: =IFERROR(VLOOKUP($I103,RESUMO!$A$3:$M$200,3,FALSE),"") -> 47569.92 | U103: =IFERROR((T103*-1)/R103-1,"") -> -0.17806731 | V103: -72811.147 | W103: -0.026 | X103: =IFERROR(VLOOKUP($I103,RESUMO!$A$3:$M$200,4,FALSE),"") -> 69230.98 | Y103: =IFERROR((X103*-1)/V103-1,"") -> -0.049170586 | Z103: -63604.056 | AA103: -0.026 | AB103: =IFERROR(VLOOKUP($I103,RESUMO!$A$3:$M$200,5,FALSE),"") -> 55687.07 | AC103: =IFERROR((AB103*-1)/Z103-1,"") -> -0.12447297 | AD103: -66634.494 | AE103: -0.026 | AF103: =IFERROR(VLOOKUP($I103,RESUMO!$A$3:$M$200,6,FALSE),"") -> 22391.71 | AG103: =IFERROR((AF103*-1)/AD103-1,"") -> -0.66396218 | AH103: -57659.978 | AI103: -0.026 | AJ103: -58400.406 | AK103: -0.026 | AL103: -69968.225 | AM103: -0.026 | AN103: -77464.604 | AO103: -0.026 | AP103: -78300.677 | AQ103: -0.026 | AR103: -71202.862 | AS103: -0.026 | AT103: -63868.243 | AU103: -0.026 | AW103: -780000 | AX103: -0.026 | AY103: -65000
B104: $ | C104: 7 | D104: 9 | E104: $ 7-9 de 2025 | F104: -10745.78 | H104: Mylena | I104: Pedágio Frota | J104: -10745.78 | K104: -0.004298312 | L104: -10745.78 | M104: -0.00537289 | N104: -10745.78 | O104: -0.0066191137 | P104: =IFERROR(VLOOKUP($I104,RESUMO!$A$3:$M$200,2,FALSE),"") -> 4450.1 | Q104: =IFERROR((P104*-1)/N104-1,"") -> -0.58587464 | R104: -10745.78 | S104: -0.0048274204 | T104: =IFERROR(VLOOKUP($I104,RESUMO!$A$3:$M$200,3,FALSE),"") -> 10141.98 | U104: =IFERROR((T104*-1)/R104-1,"") -> -0.0561895 | V104: -10745.78 | W104: -0.003837191 | X104: =IFERROR(VLOOKUP($I104,RESUMO!$A$3:$M$200,4,FALSE),"") -> 9958.65 | Y104: =IFERROR((X104*-1)/V104-1,"") -> -0.07325015 | Z104: -10745.78 | AA104: -0.0043926488 | AB104: =IFERROR(VLOOKUP($I104,RESUMO!$A$3:$M$200,5,FALSE),"") -> 9830.1 | AC104: =IFERROR((AB104*-1)/Z104-1,"") -> -0.085212986 | AD104: -10745.78 | AE104: -0.0041928777 | AF104: =IFERROR(VLOOKUP($I104,RESUMO!$A$3:$M$200,6,FALSE),"") -> 0 | AG104: =IFERROR((AF104*-1)/AD104-1,"") -> -1 | AH104: -10745.78 | AI104: -0.0048454802 | AJ104: -10745.78 | AK104: -0.0047840469 | AL104: -10745.78 | AM104: -0.0039931023 | AN104: -10745.78 | AO104: -0.0036066831 | AP104: -10745.78 | AQ104: -0.003568172 | AR104: -10745.78 | AS104: -0.0039238631 | AT104: -10745.78 | AU104: -0.0043744789 | AW104: -128949.36 | AX104: -0.004298312 | AY104: -10745.78
E105: Diretoria - 25.11.25 | F105: -20000 | H105: Mylena | I105: IPVA e Licenciamento | J105: -20000 | K105: -0.008 | L105: -20000 | M105: -0.01 | N105: -20000 | O105: -0.012319466 | P105: =IFERROR(VLOOKUP($I105,RESUMO!$A$3:$M$200,2,FALSE),"") -> 4296.61 | Q105: =IFERROR((P105*-1)/N105-1,"") -> -0.7851695 | R105: -20000 | S105: -0.0089847743 | T105: =IFERROR(VLOOKUP($I105,RESUMO!$A$3:$M$200,3,FALSE),"") -> 4296.61 | U105: =IFERROR((T105*-1)/R105-1,"") -> -0.7851695 | V105: -20000 | W105: -0.0071417636 | X105: =IFERROR(VLOOKUP($I105,RESUMO!$A$3:$M$200,4,FALSE),"") -> 4296.61 | Y105: =IFERROR((X105*-1)/V105-1,"") -> -0.7851695 | Z105: -20000 | AA105: -0.0081755793 | AB105: =IFERROR(VLOOKUP($I105,RESUMO!$A$3:$M$200,5,FALSE),"") -> 4296.61 | AC105: =IFERROR((AB105*-1)/Z105-1,"") -> -0.7851695 | AD105: -20000 | AE105: -0.0078037661 | AF105: =IFERROR(VLOOKUP($I105,RESUMO!$A$3:$M$200,6,FALSE),"") -> 194.45 | AG105: =IFERROR((AF105*-1)/AD105-1,"") -> -0.9902775 | AH105: -20000 | AI105: -0.009018387 | AJ105: -20000 | AK105: -0.0089040477 | AL105: -20000 | AM105: -0.007431945 | AN105: -20000 | AO105: -0.0067127433 | AP105: -20000 | AQ105: -0.0066410665 | AR105: -20000 | AS105: -0.0073030773 | AT105: -20000 | AU105: -0.0081417615 | AW105: -240000 | AX105: -0.008 | AY105: -20000
...

Sheet RESUMO
A3: Soma de Vlr Despesa | B3: Rótulos de Coluna
A4: Rótulos de Linha | B4: jan | C4: fev | D4: mar | E4: abr | F4: mai | G4: Total Geral
A5: 0 - TRIBUTOS | B5: 136035.24 | C5: 115564.43 | D5: 169337.99 | E5: 140077.9 | G5: 561015.56
A6: COFINS | C6: 2460.61 | D6: 15906.25 | E6: 11442.92 | G6: 29809.78
A7: ICMS | B7: 60679.01 | C7: 18975.32 | D7: 39057.06 | E7: 24861.83 | G7: 143573.22
A8: Impostos a recolher | B8: 5659.96 | C8: 5659.96 | D8: 5659.96 | E8: 5659.96 | G8: 22639.84
A9: IPI | B9: 15874.39 | C9: 14761.73 | D9: 22197.7 | E9: 20723.31 | G9: 73557.13
A10: Outros Impostos | B10: 1443.62 | C10: 1490.09 | D10: 1921.23 | E10: 4716.69 | G10: 9571.63
A11: PIS | C11: 496.96 | D11: 3431.3 | E11: 2462.42 | G11: 6390.68
A12: Simples Nacional | B12: 52378.26 | C12: 71719.76 | D12: 81164.49 | E12: 70210.77 | G12: 275473.28
A13: 1 - CPV | B13: 10956.84 | C13: 22587.71 | D13: 29480.91 | E13: 17172.52 | F13: 2977.13 | G13: 83175.11
A14: Compras | B14: 564 | C14: 987.68 | D14: 1534.3 | E14: 9.5 | G14: 3095.48
A15: Compras - Pés/Mecanismos/Bases | B15: 1 | C15: 2516.68 | D15: 12217.75 | E15: 962.38 | F15: 67.11 | G15: 15764.92
A16: Frete sobre Compras | B16: 10391.84 | C16: 19083.35 | D16: 15728.86 | E16: 16200.64 | F16: 2910.02 | G16: 64314.71
A17: 2 - CUSTOS DIRETOS | B17: 298438.85 | C17: 359850.92 | D17: 333045.58 | E17: 255313.36 | F17: 21727.68 | G17: 1268376.4
A18: Assistência Médica MOD | B18: 808 | C18: 570 | D18: 349.9 | E18: 420 | G18: 2147.9
A19: Energia Eletrica (Prod) | B19: 4543.34 | C19: 6905.72 | D19: 8155.15 | E19: 8554.02 | G19: 28158.23
A20: EPIs/Uniformes (Prod) | B20: 1899.2 | C20: 1694.16 | E20: 1307.92 | F20: 9103.6 | G20: 14004.88
A21: Férias MOD | B21: 2775.23 | C21: 5329.74 | D21: 5620.32 | E21: 21546.3 | F21: 1358.46 | G21: 36630.05
A22: FGTS MOD | B22: 34431.98 | C22: 32736.5 | D22: 35869.64 | G22: 103038.12
A23: Gratificacoes MOD | B23: 6816.55 | C23: 9992.25 | D23: 8223.1 | E23: 1988.1 | G23: 27020
A24: INSS MOD | B24: 44369.08 | C24: 42800.44 | D24: 44918.66 | G24: 132088.18
A25: Material de Expediente (Prod) | B25: 14950.47 | C25: 21105.59 | D25: 9382.13 | E25: 16740.67 | F25: 5750.17 | G25: 67929.03
A26: Rescisões MOD | C26: 30936.21 | D26: 394.44 | F26: 1694.75 | G26: 33025.4
A27: Salarios e Ordenados MOD | B27: 185861.81 | C27: 205896.33 | D27: 218151.71 | E27: 202715.75 | F27: 3820.7 | G27: 816446.3
A28: Seguro de Vida MOD | B28: 1983.19 | C28: 1883.98 | D28: 1980.53 | E28: 2040.6 | G28: 7888.3
A29: 3 - CUSTOS INDIRETOS | B29: 87389.24 | C29: 65780.3 | D29: 107667.2 | E29: 67636.97 | F29: 16917.44 | G29: 345391.15
A30: Assistência Médica CIF | E30: 225 | G30: 225
A31: Cursos e Treinamentos CIF | B31: 2934.94 | C31: 1387.7 | D31: 705.03 | G31: 5027.67
A32: Férias CIF | D32: 1458.08 | E32: 1316.22 | G32: 2774.3
A33: FGTS CIF | B33: 6497.95 | C33: 5251.66 | D33: 5035.68 | G33: 16785.29
A34: Gratificações CIF | B34: 3000.69 | C34: 2925.69 | D34: 1589.46 | E34: 1479.46 | G34: 8995.3
A35: Horas Extras CIF | B35: 230 | G35: 230
A36: INSS CIF | B36: 8026.61 | C36: 8297.76 | D36: 8006.02 | G36: 24330.39
A37: IPTU e Taxas Municipais CIF | E37: 2849.74 | G37: 2849.74
A38: Manutenção de Equipamentos (Prod) | B38: 2679.92 | C38: 9080.05 | D38: 50727.39 | E38: 6964.81 | F38: 1139.6 | G38: 70591.77
A39: Manutenção Predial CIF | B39: 22729.92 | C39: 3526.05 | D39: 6703.59 | E39: 8001.47 | F39: 889 | G39: 41850.03
A40: Material de Limpeza CIF | B40: 1649.3 | C40: 1675.48 | D40: 2109.7 | E40: 2093.6 | F40: 2112.39 | G40: 9640.47
A41: Medicina e Seguranca do Trabalho CIF | B41: 2316.15 | C41: 2405.31 | D41: 2405.31 | E41: 2405.31 | G41: 9532.08
A42: Medicina e Segurança do Trabalho MOD | D42: 180 | G42: 180
A43: Rescisões CIF | E43: 13159.51 | F43: 12776.45 | G43: 25935.96
A44: Salarios e Ordenados CIF | B44: 36962.58 | C44: 30986.82 | D44: 28474.9 | E44: 28865.57 | G44: 125289.87
A45: Seguro de Vida CIF | B45: 361.18 | C45: 243.78 | D45: 272.04 | E45: 276.28 | G45: 1153.28
A46: 4 - GASTOS COM PESSOAL | B46: 162457.66 | C46: 172282.52 | D46: 186511.62 | E46: 158165.32 | F46: 63986.17 | G46: 743403.29
A47: Assistência Médica (Adm) | C47: 75 | G47: 75
A48: Confraternização | B48: 3330.86 | C48: 369.46 | D48: 1065.51 | E48: 170.15 | F48: 1239.32 | G48: 6175.3
A49: Cursos e Treinamentos (Adm) | B49: 2231.33 | C49: 4424.49 | D49: 1873.76 | E49: 2785.58 | G49: 11315.16
A50: Ferias (Adm) | C50: 297.9 | D50: 1372.31 | E50: 2681.09 | G50: 4351.3
A51: FGTS (Adm) | B51: 8774.55 | C51: 9673.71 | D51: 8826.9 | G51: 27275.16
A52: Gratificações (Adm) | B52: 2919.01 | C52: 4519.01 | D52: 4955.24 | E52: 1980.24 | G52: 14373.5
A53: INSS (Adm) | B53: 22949.23 | C53: 17763.09 | D53: 20718.49 | E53: 178.31 | G53: 61609.12
A54: Manutenção Predial (Adm) | B54: 2233.96 | C54: 2457.64 | D54: 1143.76 | E54: 8026.26 | G54: 13861.62
A55: Pró-Labore | B55: 64498.68 | C55: 60318.18 | D55: 59830.19 | E55: 61974.34 | F55: 62746.85 | G55: 309368.24
A56: Rescisões (Adm) | B56: 879.73 | D56: 11928.27 | E56: 12417.35 | G56: 25225.35
A57: Salarios e Ordenados (Adm) | B57: 53990.01 | C57: 71662.62 | D57: 74200.57 | E57: 67351.37 | G57: 267204.57
A58: Seguro de Vida (Adm) | B58: 650.3 | C58: 721.42 | D58: 596.62 | E58: 600.63 | G58: 2568.97
A59: 5 - DESPESAS ADMINISTRATIVAS | B59: 16694.4 | C59: 18621.32 | D59: 17985.82 | E59: 18594.11 | F59: 4525.85 | G59: 76421.5
A60: Água | B60: 32.23 | C60: 32.23 | D60: 32.23 | E60: 32.23 | G60: 128.92
A61: Alimentação | B61: 295.6 | C61: 338.73 | D61: 782.8 | E61: 983.5 | F61: 140 | G61: 2540.63
A62: Aluguel de Imóvel | B62: 800 | C62: 900 | D62: 900 | E62: 900 | F62: 900 | G62: 4400
A63: Combustíveis (Adm) | B63: 511.23 | C63: 981.09 | D63: 780.64 | E63: 1078.18 | F63: 50.49 | G63: 3401.63
A64: Copa | B64: 15.99 | C64: 368.6 | D64: 150.63 | E64: 243.83 | G64: 779.05
A65: Despesas Cartorárias | B65: 432.21 | C65: 511.67 | D65: 350.68 | E65: 279.6 | G65: 1574.16
A66: Doações | B66: 100 | C66: 100 | D66: 100 | E66: 100 | G66: 400
A67: Energia Eletrica (Adm) | B67: 98.41 | C67: 91.95 | E67: 91.72 | G67: 282.08
A68: Material de Expediente (Adm) | B68: 111.89 | C68: 373.27 | D68: 382.17 | E68: 671.82 | G68: 1539.15
A69: Material de Limpeza (Adm) | B69: 367.37 | C69: 577.9 | D69: 427.23 | E69: 448.1 | F69: 902.98 | G69: 2723.58
A70: Rastreamento de frota | B70: 370 | C70: 370 | D70: 370 | E70: 370 | F70: 370 | G70: 1850
A71: Seguros Veicular | B71: 11212.42 | C71: 11212.42 | D71: 11212.42 | E71: 10898.11 | F71: 1697.48 | G71: 46232.85
A72: SPC/Serasa/Associacao | B72: 351 | C72: 617.44 | D72: 351 | E72: 351 | G72: 1670.44
A73: Telefone e Internet | B73: 1996.05 | C73: 2146.02 | D73: 2146.02 | E73: 2146.02 | F73: 464.9 | G73: 8899.01
A74: 6 - DESPESA COM VENDAS | B74: 401746.29 | C74: 315472.21 | D74: 387311.61 | E74: 375329.97 | F74: 110876.47 | G74: 1590736.5
A75: Brindes | B75: 1368 | G75: 1368
A76: Carregamento | B76: 1955 | C76: 2415 | D76: 3042.48 | E76: 86 | G76: 7498.48
A77: Combustiveis Frota | B77: 41074.3 | C77: 47569.92 | D77: 69230.98 | E77: 55687.07 | F77: 22391.71 | G77: 235953.98
A78: Comissões sobre Vendas Externo | B78: 117100.22 | C78: 78726.2 | D78: 88339.05 | E78: 89083.76 | F78: 55869.19 | G78: 429118.42
A79: Comissões sobre Vendas Interno | B79: 7224.44 | C79: 5041.4 | D79: 10515.81 | E79: 8548.01 | G79: 31329.66
A80: Consultoria Comercial | B80: 13677.89 | C80: 10422.07 | D80: 14968.49 | E80: 26703.39 | F80: 11794.18 | G80: 77566.02
A81: Desenvolvimento de Novos Produtos | B81: 24000 | C81: 24000 | D81: 24000 | E81: 24510 | F81: 65 | G81: 96575
A82: Feiras e Eventos | B82: 119279.43 | C82: 38472.95 | D82: 41728.47 | E82: 53365.87 | F82: 3897.31 | G82: 256744.03
A83: Fretes | C83: 2334.16 | D83: 709 | G83: 3043.16
A84: Fretes Ass. Técnica | B84: 673.07 | C84: 1644.02 | D84: 420.81 | F84: 1769.79 | G84: 4507.69
A85: Fretes Karams | B85: 9673.85 | C85: 18654.35 | D85: 19808.55 | E85: 19421.25 | F85: 5264.75 | G85: 72822.75
A86: IPVA e Licenciamento | B86: 4296.61 | C86: 4296.61 | D86: 4296.61 | E86: 4296.61 | F86: 194.45 | G86: 17380.89
A87: Mostruário de Tecido | B87: 7122.33 | C87: 4005.16 | D87: 4874.22 | E87: 6293.77 | F87: 6341.55 | G87: 28637.03
A88: Multas de Trânsito | B88: 260.32 | C88: 260.32 | D88: 1564.33 | E88: 1766.82 | F88: 312.38 | G88: 4164.17
A89: Pedágio Frota | B89: 4450.1 | C89: 10141.98 | D89: 9958.65 | E89: 9830.1 | G89: 34380.83
A90: Publicidade e Propaganda | B90: 1965 | C90: 1965 | D90: 7759.59 | E90: 2594.91 | F90: 1800 | G90: 16084.5
A91: Royalties | B91: 35699.84 | C91: 45445.03 | D91: 61484.2 | E91: 61227.86 | G91: 203856.93
A92: Viagens e Estadias c/ Vendas | B92: 738.16 | C92: 1807.69 | D92: 2581.66 | E92: 2909.9 | F92: 585.36 | G92: 8622.77
A93: Manutenção com veiculos | B93: 11187.73 | C93: 18270.35 | D93: 22028.71 | E93: 9004.65 | F93: 590.8 | G93: 61082.24
A94: 7 - SERVIÇOS DE TERCEIROS | B94: 74180.06 | C94: 63538.03 | D94: 66306.18 | E94: 79299.39 | F94: 27982.51 | G94: 311306.17
A95: Consultoria Empresarial | B95: 16033.43 | C95: 14452.9 | D95: 20130.41 | E95: 24211.55 | F95: 5008.41 | G95: 79836.7
A96: Consultoria Juridica | B96: 6035.41 | C96: 6035.41 | D96: 6035.41 | G96: 18106.23
A97: Contabilidade | B97: 11823 | C97: 11880 | D97: 12244 | E97: 11880 | F97: 7448 | G97: 55275
A98: Curadoria | B98: 8966 | C98: 9436 | D98: 9436 | E98: 10504.37 | F98: 4718 | G98: 43060.37
A99: Outros Serviços de Terceiros | B99: 6685.85 | C99: 9350 | D99: 7769.93 | E99: 5650 | F99: 4400 | G99: 33855.78
A100: Sistemas de Informação | B100: 23441.37 | C100: 11301.72 | D100: 9711.93 | E100: 19383.47 | F100: 6176.1 | G100: 70014.59
A101: Vigilancia e Seguranca | B101: 1195 | C101: 1082 | D101: 978.5 | E101: 670 | F101: 232 | G101: 4157.5
A102: Consultoria Tributaria | E102: 7000 | G102: 7000
...

Sheet DESPESAS
A1: Cód. | B1: Emp | C1: Nro Doc. | D1: Dt. Entrada | E1: Fornecedor | F1: Vlr Despesa | G1: Plano de Contas | H1: Conta | I1: MÁQUINA2 | J1: CENTRO DE CUSTO | K1: SETOR | L1: TAG | M1: RESPONSÁVEL
A2: 53592 | B2: LAY | C2: 000005 | D2: 46052 | E2: CRIATIVE MOVEIS PLANEJADOS LTDA | F2: 564 | G2: 3.4.2.1 - Compras | H2: =VLOOKUP(DESPESAS[[#This Row],[Plano de Contas]],BASE!$B$3:$D$119,3,FALSE) -> Compras | I2: =IFERROR(VLOOKUP(DESPESAS[[#This Row],[Fornecedor]],Tabela2[],2,FALSE),"") | J2: =IFERROR(VLOOKUP(DESPESAS[[#This Row],[Plano de Contas]],BASE!$B$3:$F$119,4,FALSE),"") -> 1 - CPV | K2: =IFERROR(VLOOKUP(DESPESAS[[#This Row],[Plano de Contas]],BASE!$B$3:$H$119,5,FALSE),"") -> COMPRAS | L2: =IFERROR(VLOOKUP(DESPESAS[[#This Row],[Plano de Contas]],BASE!$B$3:$H$119,6,FALSE),"") -> 0 | M2: =VLOOKUP(DESPESAS[[#This Row],[Plano de Contas]],BASE!$B$3:$H$119,7,FALSE) -> MYLENA
A3: 53605 | B3: KAR | C3: 035688 | D3: 46053 | E3: METALURGICA CELINO LTDA | F3: 1 | G3: 3.4.2.6 - Compras - Pés/Mecanismos/Bases | H3: =VLOOKUP(DESPESAS[[#This Row],[Plano de Contas]],BASE!$B$3:$D$119,3,FALSE) -> Compras - Pés/Mecanismos/Bases | I3: =IFERROR(VLOOKUP(DESPESAS[[#This Row],[Fornecedor]],Tabela2[],2,FALSE),"") | J3: =IFERROR(VLOOKUP(DESPESAS[[#This Row],[Plano de Contas]],BASE!$B$3:$F$119,4,FALSE),"") -> 1 - CPV | K3: =IFERROR(VLOOKUP(DESPESAS[[#This Row],[Plano de Contas]],BASE!$B$3:$H$119,5,FALSE),"") -> COMPRAS | L3: =IFERROR(VLOOKUP(DESPESAS[[#This Row],[Plano de Contas]],BASE!$B$3:$H$119,6,FALSE),"") -> 0 | M3: =VLOOKUP(DESPESAS[[#This Row],[Plano de Contas]],BASE!$B$3:$H$119,7,FALSE) -> MYLENA
A4: 53632 | B4: KAR | C4: 019042 | D4: 46062 | E4: LINE DO BRASIL COMERCIO DE ATUADORES LINEARES LTDA | F4: 125.38 | G4: 3.4.2.6 - Compras - Pés/Mecanismos/Bases | H4: =VLOOKUP(DESPESAS[[#This Row],[Plano de Contas]],BASE!$B$3:$D$119,3,FALSE) -> Compras - Pés/Mecanismos/Bases | I4: =IFERROR(VLOOKUP(DESPESAS[[#This Row],[Fornecedor]],Tabela2[],2,FALSE),"") | J4: =IFERROR(VLOOKUP(DESPESAS[[#This Row],[Plano de Contas]],BASE!$B$3:$F$119,4,FALSE),"") -> 1 - CPV | K4: =IFERROR(VLOOKUP(DESPESAS[[#This Row],[Plano de Contas]],BASE!$B$3:$H$119,5,FALSE),"") -> COMPRAS | L4: =IFERROR(VLOOKUP(DESPESAS[[#This Row],[Plano de Contas]],BASE!$B$3:$H$119,6,FALSE),"") -> 0 | M4: =VLOOKUP(DESPESAS[[#This Row],[Plano de Contas]],BASE!$B$3:$H$119,7,FALSE) -> MYLENA
A5: 53685 | B5: LAY | C5: 002691 | D5: 46065 | E5: BONACK E SANCHES LTDA ME | F5: 1425.6 | G5: 3.4.2.6 - Compras - Pés/Mecanismos/Bases | H5: =VLOOKUP(DESPESAS[[#This Row],[Plano de Contas]],BASE!$B$3:$D$119,3,FALSE) -> Compras - Pés/Mecanismos/Bases | I5: =IFERROR(VLOOKUP(DESPESAS[[#This Row],[Fornecedor]],Tabela2[],2,FALSE),"") | J5: =IFERROR(VLOOKUP(DESPESAS[[#This Row],[Plano de Contas]],BASE!$B$3:$F$119,4,FALSE),"") -> 1 - CPV | K5: =IFERROR(VLOOKUP(DESPESAS[[#This Row],[Plano de Contas]],BASE!$B$3:$H$119,5,FALSE),"") -> COMPRAS | L5: =IFERROR(VLOOKUP(DESPESAS[[#This Row],[Plano de Contas]],BASE!$B$3:$H$119,6,FALSE),"") -> 0 | M5: =VLOOKUP(DESPESAS[[#This Row],[Plano de Contas]],BASE!$B$3:$H$119,7,FALSE) -> MYLENA
A6: 53687 | B6: KAR | C6: 130161 | D6: 46065 | E6: MANUFATURA DE BOTOES CARDENAS LTDA | F6: 967.68 | G6: 3.4.2.1 - Compras | H6: =VLOOKUP(DESPESAS[[#This Row],[Plano de Contas]],BASE!$B$3:$D$119,3,FALSE) -> Compras | I6: =IFERROR(VLOOKUP(DESPESAS[[#This Row],[Fornecedor]],Tabela2[],2,FALSE),"") | J6: =IFERROR(VLOOKUP(DESPESAS[[#This Row],[Plano de Contas]],BASE!$B$3:$F$119,4,FALSE),"") -> 1 - CPV | K6: =IFERROR(VLOOKUP(DESPESAS[[#This Row],[Plano de Contas]],BASE!$B$3:$H$119,5,FALSE),"") -> COMPRAS | L6: =IFERROR(VLOOKUP(DESPESAS[[#This Row],[Plano de Contas]],BASE!$B$3:$H$119,6,FALSE),"") -> 0 | M6: =VLOOKUP(DESPESAS[[#This Row],[Plano de Contas]],BASE!$B$3:$H$119,7,FALSE) -> MYLENA
A7: 53786 | B7: FK | C7: DIIH50 | D7: 46080 | E7: DIONIZIO PRIETO | F7: 100 | G7: 3.4.2.6 - Compras - Pés/Mecanismos/Bases | H7: =VLOOKUP(DESPESAS[[#This Row],[Plano de Contas]],BASE!$B$3:$D$119,3,FALSE) -> Compras - Pés/Mecanismos/Bases | I7: =IFERROR(VLOOKUP(DESPESAS[[#This Row],[Fornecedor]],Tabela2[],2,FALSE),"") | J7: =IFERROR(VLOOKUP(DESPESAS[[#This Row],[Plano de Contas]],BASE!$B$3:$F$119,4,FALSE),"") -> 1 - CPV | K7: =IFERROR(VLOOKUP(DESPESAS[[#This Row],[Plano de Contas]],BASE!$B$3:$H$119,5,FALSE),"") -> COMPRAS | L7: =IFERROR(VLOOKUP(DESPESAS[[#This Row],[Plano de Contas]],BASE!$B$3:$H$119,6,FALSE),"") -> 0 | M7: =VLOOKUP(DESPESAS[[#This Row],[Plano de Contas]],BASE!$B$3:$H$119,7,FALSE) -> MYLENA
A8: 53801 | B8: KOY | C8: 000008 | D8: 46080 | E8: CRIATIVE MOVEIS PLANEJADOS LTDA | F8: 20 | G8: 3.4.2.1 - Compras | H8: =VLOOKUP(DESPESAS[[#This Row],[Plano de Contas]],BASE!$B$3:$D$119,3,FALSE) -> Compras | I8: =IFERROR(VLOOKUP(DESPESAS[[#This Row],[Fornecedor]],Tabela2[],2,FALSE),"") | J8: =IFERROR(VLOOKUP(DESPESAS[[#This Row],[Plano de Contas]],BASE!$B$3:$F$119,4,FALSE),"") -> 1 - CPV | K8: =IFERROR(VLOOKUP(DESPESAS[[#This Row],[Plano de Contas]],BASE!$B$3:$H$119,5,FALSE),"") -> COMPRAS | L8: =IFERROR(VLOOKUP(DESPESAS[[#This Row],[Plano de Contas]],BASE!$B$3:$H$119,6,FALSE),"") -> 0 | M8: =VLOOKUP(DESPESAS[[#This Row],[Plano de Contas]],BASE!$B$3:$H$119,7,FALSE) -> MYLENA
A9: 53812 | B9: KAR | C9: 000010 | D9: 46080 | E9: CRIATIVE MOVEIS PLANEJADOS LTDA | F9: 865.7 | G9: 3.4.2.6 - Compras - Pés/Mecanismos/Bases | H9: =VLOOKUP(DESPESAS[[#This Row],[Plano de Contas]],BASE!$B$3:$D$119,3,FALSE) -> Compras - Pés/Mecanismos/Bases | I9: =IFERROR(VLOOKUP(DESPESAS[[#This Row],[Fornecedor]],Tabela2[],2,FALSE),"") | J9: =IFERROR(VLOOKUP(DESPESAS[[#This Row],[Plano de Contas]],BASE!$B$3:$F$119,4,FALSE),"") -> 1 - CPV | K9: =IFERROR(VLOOKUP(DESPESAS[[#This Row],[Plano de Contas]],BASE!$B$3:$H$119,5,FALSE),"") -> COMPRAS | L9: =IFERROR(VLOOKUP(DESPESAS[[#This Row],[Plano de Contas]],BASE!$B$3:$H$119,6,FALSE),"") -> 0 | M9: =VLOOKUP(DESPESAS[[#This Row],[Plano de Contas]],BASE!$B$3:$H$119,7,FALSE) -> MYLENA
A10: 53839 | B10: KAR | C10: 008036 | D10: 46087 | E10: MUNDIAL ACO COMERCIO DE FERRAGENS LTDA | F10: 25 | G10: 3.4.2.1 - Compras | H10: =VLOOKUP(DESPESAS[[#This Row],[Plano de Contas]],BASE!$B$3:$D$119,3,FALSE) -> Compras | I10: =IFERROR(VLOOKUP(DESPESAS[[#This Row],[Fornecedor]],Tabela2[],2,FALSE),"") | J10: =IFERROR(VLOOKUP(DESPESAS[[#This Row],[Plano de Contas]],BASE!$B$3:$F$119,4,FALSE),"") -> 1 - CPV | K10: =IFERROR(VLOOKUP(DESPESAS[[#This Row],[Plano de Contas]],BASE!$B$3:$H$119,5,FALSE),"") -> COMPRAS | L10: =IFERROR(VLOOKUP(DESPESAS[[#This Row],[Plano de Contas]],BASE!$B$3:$H$119,6,FALSE),"") -> 0 | M10: =VLOOKUP(DESPESAS[[#This Row],[Plano de Contas]],BASE!$B$3:$H$119,7,FALSE) -> MYLENA
A11: 53989 | B11: KAR | C11: 045593 | D11: 46111 | E11: GIROTEC MOVEIS E METALURGICA LTDA | F11: 1221.65 | G11: 3.4.2.6 - Compras - Pés/Mecanismos/Bases | H11: =VLOOKUP(DESPESAS[[#This Row],[Plano de Contas]],BASE!$B$3:$D$119,3,FALSE) -> Compras - Pés/Mecanismos/Bases | I11: =IFERROR(VLOOKUP(DESPESAS[[#This Row],[Fornecedor]],Tabela2[],2,FALSE),"") | J11: =IFERROR(VLOOKUP(DESPESAS[[#This Row],[Plano de Contas]],BASE!$B$3:$F$119,4,FALSE),"") -> 1 - CPV | K11: =IFERROR(VLOOKUP(DESPESAS[[#This Row],[Plano de Contas]],BASE!$B$3:$H$119,5,FALSE),"") -> COMPRAS | L11: =IFERROR(VLOOKUP(DESPESAS[[#This Row],[Plano de Contas]],BASE!$B$3:$H$119,6,FALSE),"") -> 0 | M11: =VLOOKUP(DESPESAS[[#This Row],[Plano de Contas]],BASE!$B$3:$H$119,7,FALSE) -> MYLENA
A12: 54001 | B12: LAY | C12: 000015 | D12: 46112 | E12: CRIATIVE MOVEIS PLANEJADOS LTDA | F12: 1320.1 | G12: 3.4.2.1 - Compras | H12: =VLOOKUP(DESPESAS[[#This Row],[Plano de Contas]],BASE!$B$3:$D$119,3,FALSE) -> Compras | I12: =IFERROR(VLOOKUP(DESPESAS[[#This Row],[Fornecedor]],Tabela2[],2,FALSE),"") | J12: =IFERROR(VLOOKUP(DESPESAS[[#This Row],[Plano de Contas]],BASE!$B$3:$F$119,4,FALSE),"") -> 1 - CPV | K12: =IFERROR(VLOOKUP(DESPESAS[[#This Row],[Plano de Contas]],BASE!$B$3:$H$119,5,FALSE),"") -> COMPRAS | L12: =IFERROR(VLOOKUP(DESPESAS[[#This Row],[Plano de Contas]],BASE!$B$3:$H$119,6,FALSE),"") -> 0 | M12: =VLOOKUP(DESPESAS[[#This Row],[Plano de Contas]],BASE!$B$3:$H$119,7,FALSE) -> MYLENA
A13: 54003 | B13: KOY | C13: 000014 | D13: 46112 | E13: CRIATIVE MOVEIS PLANEJADOS LTDA | F13: 189.2 | G13: 3.4.2.1 - Compras | H13: =VLOOKUP(DESPESAS[[#This Row],[Plano de Contas]],BASE!$B$3:$D$119,3,FALSE) -> Compras | I13: =IFERROR(VLOOKUP(DESPESAS[[#This Row],[Fornecedor]],Tabela2[],2,FALSE),"") | J13: =IFERROR(VLOOKUP(DESPESAS[[#This Row],[Plano de Contas]],BASE!$B$3:$F$119,4,FALSE),"") -> 1 - CPV | K13: =IFERROR(VLOOKUP(DESPESAS[[#This Row],[Plano de Contas]],BASE!$B$3:$H$119,5,FALSE),"") -> COMPRAS | L13: =IFERROR(VLOOKUP(DESPESAS[[#This Row],[Plano de Contas]],BASE!$B$3:$H$119,6,FALSE),"") -> 0 | M13: =VLOOKUP(DESPESAS[[#This Row],[Plano de Contas]],BASE!$B$3:$H$119,7,FALSE) -> MYLENA
... A4126: 201601 | B4126: KAR | C4126: 876 | D4126: 46153 | E4126: ALFZ COMERCIO DE BALANCAS ltda | F4126: 365.6 | G4126: 3.4.4.1 - Manutenção de Equipamentos (Prod) | H4126: =VLOOKUP(DESPESAS[[#This Row],[Plano de Contas]],BASE!$B$3:$D$119,3,FALSE) -> Manutenção de Equipamentos (Prod) | I4126: =IFERROR(VLOOKUP(DESPESAS[[#This Row],[Fornecedor]],Tabela2[],2,FALSE),"") | J4126: =IFERROR(VLOOKUP(DESPESAS[[#This Row],[Plano de Contas]],BASE!$B$3:$F$119,4,FALSE),"") -> 3 - CUSTOS INDIRETOS | K4126: =IFERROR(VLOOKUP(DESPESAS[[#This Row],[Plano de Contas]],BASE!$B$3:$H$119,5,FALSE),"") -> MANUTENÇÃO / TI | L4126: =IFERROR(VLOOKUP(DESPESAS[[#This Row],[Plano de Contas]],BASE!$B$3:$H$119,6,FALSE),"") -> 0 | M4126: =VLOOKUP(DESPESAS[[#This Row],[Plano de Contas]],BASE!$B$3:$H$119,7,FALSE) -> RAFAEL

Sheet FORNECEDORES MANUTENÇÃO
A2: FORNECEDOR | B2: MÁQUINA
A3: NEW CORTS LTDA - ME | B3: ACRILICO
A4: RIZON IND. DE MAQUINAS E EQUIPAMENTOS | B4: CNC MADEIRAS
A5: BLUTECH MANUTENÇÃO DE EQUIPAMENTOS LTDA | B5: CNC TECIDO
A6: R&J EQUIPAMENTOS LTDA | B6: CNC TECIDO
A7: ELAINE CRISTINA TAROCO SANTOS & CIA LTDA | B7: COMPONENTES T.I
A8: PANIR EQUIPAMENTOS LTDA | B8: COMPRESSORES
A9: PPO COMPRESSORES LTDA | B9: COMPRESSORES
A10: CASA DE FERRAGEM NISHIMOTO | B10: FERRAGENS GERAIS
A11: FERRAMENTAS GERAIS COMERCIO IMP DE FERRAM. E MAQUI | B11: FERRAGENS GERAIS
A12: RODRIGUES & LIMA FERRAGENS DE FERRAMENTAS LTDA - M | B12: FERRAGENS GERAIS
A13: A D TIZO JUNIOR - FERRAMENTAS ME | B13: GRAMPEADORES IMECO
... A51: EBANX LTDA | B51: SITE

Sheet BASE
B2: Plano de Contas | C2: Código | D2: Descrição | E2: CENTRO DE CUSTO | F2: SETOR | G2: TAG | H2: RESPONSÁVEL
B3: 1.3.1 - Maquinas e Equipamentos | C3: 1.3.1 | D3: Maquinas e Equipamentos | E3: 9 - INVESTIMENTOS | F3: MANUTENÇÃO / TI | H3: RAFAEL
B4: 1.3.2 - Moveis e Utensilios | C4: 1.3.2 | D4: Moveis e Utensilios | E4: 9 - INVESTIMENTOS | F4: ADMINISTRATIVO | H4: RAFAEL
B5: 1.3.3 - Computadores e Periféricos | C5: 1.3.3 | D5: Computadores e Periféricos | E5: 9 - INVESTIMENTOS | F5: MANUTENÇÃO / TI | H5: RAFAEL
B6: 1.3.4 - Construções e Reformas | C6: 1.3.4 | D6: Construções e Reformas | E6: 9 - INVESTIMENTOS | F6: MANUTENÇÃO / TI | H6: FÁBIO
B7: 1.3.5 - Consórcios | C7: 1.3.5 | D7: Consórcios | E7: 9 - INVESTIMENTOS | F7: FINANCEIRO | H7: FÁBIO
B8: 1.3.6 - Investimento em Ativos | C8: 1.3.6 | D8: Investimento em Ativos | E8: 9 - INVESTIMENTOS | F8: FINANCEIRO | H8: FÁBIO
B9: 2.1.4 - Aquisição de Financiamento | C9: 2.1.4 | D9: Aquisição de Financiamento | H9: NINGUÉM
B10: 2.9.6 - Impostos a recolher | C10: 2.9.6 | D10: Impostos a recolher | E10: 0 - TRIBUTOS | F10: FINANCEIRO | H10: LETÍCIA
B11: 3.3.1 - Simples Nacional | C11: 3.3.1 | D11: Simples Nacional | E11: 0 - TRIBUTOS | F11: FINANCEIRO | H11: LETÍCIA
B12: 3.3.2 - ICMS | C12: 3.3.2 | D12: ICMS | E12: 0 - TRIBUTOS | F12: FINANCEIRO | H12: LETÍCIA
B13: 3.3.3 - PIS | C13: 3.3.3 | D13: PIS | E13: 0 - TRIBUTOS | F13: FINANCEIRO | H13: LETÍCIA
B14: 3.3.4 - COFINS | C14: 3.3.4 | D14: COFINS | E14: 0 - TRIBUTOS | F14: FINANCEIRO | H14: LETÍCIA
B15: 3.3.7 - IPI | C15: 3.3.7 | D15: IPI | E15: 0 - TRIBUTOS | F15: FINANCEIRO | H15: LETÍCIA
B16: 3.3.8 - Outros Impostos | C16: 3.3.8 | D16: Outros Impostos | E16: 0 - TRIBUTOS | F16: FINANCEIRO | H16: LETÍCIA
B17: 3.4.2.1 - Compras | C17: 3.4.2.1 | D17: Compras | E17: 1 - CPV | F17: COMPRAS | H17: MYLENA
B18: 3.4.2.2 - Frete sobre Compras | C18: 3.4.2.2 | D18: Frete sobre Compras | E18: 1 - CPV | F18: COMPRAS | H18: MYLENA
B19: 3.4.2.4 - Compras - Tecido | C19: 3.4.2.4 | D19: Compras - Tecido | E19: 1 - CPV | F19: COMPRAS | H19: MYLENA
B20: 3.4.2.6 - Compras - Pés/Mecanismos/Bases | C20: 3.4.2.6 | D20: Compras - Pés/Mecanismos/Bases | E20: 1 - CPV | F20: COMPRAS | H20: MYLENA
B21: 3.4.3.1 - Energia Eletrica (Prod) | C21: 3.4.3.1 | D21: Energia Eletrica (Prod) | E21: 2 - CUSTOS DIRETOS | F21: PRODUÇÃO | H21: RAFAEL
B22: 3.4.3.10 - Seguro de Vida MOD | C22: 3.4.3.10 | D22: Seguro de Vida MOD | E22: 2 - CUSTOS DIRETOS | F22: DH | G22: CUSTO MÃO DE OBRA DIRETA | H22: RAFAEL
B23: 3.4.3.11 - FGTS MOD | C23: 3.4.3.11 | D23: FGTS MOD | E23: 2 - CUSTOS DIRETOS | F23: DH | G23: CUSTO MÃO DE OBRA DIRETA | H23: RAFAEL
B24: 3.4.3.12 - INSS MOD | C24: 3.4.3.12 | D24: INSS MOD | E24: 2 - CUSTOS DIRETOS | F24: DH | G24: CUSTO MÃO DE OBRA DIRETA | H24: RAFAEL
B25: 3.4.3.13 - Férias MOD | C25: 3.4.3.13 | D25: Férias MOD | E25: 2 - CUSTOS DIRETOS | F25: DH | G25: CUSTO MÃO DE OBRA DIRETA | H25: RAFAEL
B26: 3.4.3.14 - Medicina e Segurança do Trabalho MOD | C26: 3.4.3.14 | D26: Medicina e Segurança do Trabalho MOD | E26: 3 - CUSTOS INDIRETOS | F26: DH | G26: CUSTO MÃO DE OBRA DIRETA | H26: RAFAEL
B27: 3.4.3.2 - Material de Expediente (Prod) | C27: 3.4.3.2 | D27: Material de Expediente (Prod) | E27: 2 - CUSTOS DIRETOS | F27: PRODUÇÃO | H27: RAFAEL
B28: 3.4.3.3 - EPIs/Uniformes (Prod) | C28: 3.4.3.3 | D28: EPIs/Uniformes (Prod) | E28: 2 - CUSTOS DIRETOS | F28: COMPRAS | H28: RAFAEL
B29: 3.4.3.4 - Salarios e Ordenados MOD | C29: 3.4.3.4 | D29: Salarios e Ordenados MOD | E29: 2 - CUSTOS DIRETOS | F29: DH | G29: CUSTO MÃO DE OBRA DIRETA | H29: RAFAEL
B30: 3.4.3.5 - Horas Extras MOD | C30: 3.4.3.5 | D30: Horas Extras MOD | E30: 2 - CUSTOS DIRETOS | F30: DH | G30: CUSTO MÃO DE OBRA DIRETA | H30: RAFAEL
B31: 3.4.3.7 - Gratificacoes MOD | C31: 3.4.3.7 | D31: Gratificacoes MOD | E31: 2 - CUSTOS DIRETOS | F31: DH | G31: CUSTO MÃO DE OBRA DIRETA | H31: RAFAEL
B32: 3.4.3.8 - Rescisões MOD | C32: 3.4.3.8 | D32: Rescisões MOD | E32: 2 - CUSTOS DIRETOS | F32: DH | H32: RAFAEL
B33: 3.4.3.9 - Assistência Médica MOD | C33: 3.4.3.9 | D33: Assistência Médica MOD | E33: 2 - CUSTOS DIRETOS | F33: DH | G33: CUSTO MÃO DE OBRA DIRETA | H33: RAFAEL
B34: 3.4.4.1 - Manutenção de Equipamentos (Prod) | C34: 3.4.4.1 | D34: Manutenção de Equipamentos (Prod) | E34: 3 - CUSTOS INDIRETOS | F34: MANUTENÇÃO / TI | H34: RAFAEL
B35: 3.4.4.8 - Assistência Médica CIF | C35: 3.4.4.8 | D35: Assistência Médica CIF | E35: 3 - CUSTOS INDIRETOS | F35: DH | H35: RAFAEL
B36: 3.4.4.10 - FGTS CIF | C36: 3.4.4.10 | D36: FGTS CIF | E36: 3 - CUSTOS INDIRETOS | F36: DH | G36: CUSTO MÃO DE OBRA DIRETA | H36: RAFAEL
B37: 3.4.4.11 - INSS CIF | C37: 3.4.4.11 | D37: INSS CIF | E37: 3 - CUSTOS INDIRETOS | F37: DH | G37: CUSTO MÃO DE OBRA DIRETA | H37: RAFAEL
B38: 3.4.4.12 - Férias CIF | C38: 3.4.4.12 | D38: Férias CIF | E38: 3 - CUSTOS INDIRETOS | F38: DH | G38: CUSTO MÃO DE OBRA DIRETA | H38: RAFAEL
B39: 3.4.4.13 - Medicina e Seguranca do Trabalho CIF | C39: 3.4.4.13 | D39: Medicina e Seguranca do Trabalho CIF | E39: 3 - CUSTOS INDIRETOS | F39: DH | G39: CUSTO MÃO DE OBRA DIRETA | H39: RAFAEL
B40: 3.4.4.14 - Cursos e Treinamentos CIF | C40: 3.4.4.14 | D40: Cursos e Treinamentos CIF | E40: 3 - CUSTOS INDIRETOS | F40: DH | H40: FÁBIO
B41: 3.4.3.6 - 13° Salario MOD | C41: 3.4.3.6 | D41: 13° Salario MOD | E41: 2 - CUSTOS DIRETOS | F41: DH | G41: CUSTO MÃO DE OBRA DIRETA | H41: RAFAEL
B42: 3.5.2.4 - 13° Salario (Adm) | C42: 3.5.2.4 | D42: 13° Salario (Adm) | E42: 4 - GASTOS COM PESSOAL | F42: DH | H42: RAFAEL
B43: 3.4.4.5 - 13° Salario CIF | C43: 3.4.4.5 | D43: 13° Salario CIF | E43: 3 - CUSTOS INDIRETOS | F43: DH | G43: CUSTO MÃO DE OBRA DIRETA | H43: RAFAEL
B44: 3.4.4.15 - Material de Limpeza CIF | C44: 3.4.4.15 | D44: Material de Limpeza CIF | E44: 3 - CUSTOS INDIRETOS | F44: COMPRAS | H44: MYLENA
B45: 3.4.4.16 - Manutenção Predial CIF | C45: 3.4.4.16 | D45: Manutenção Predial CIF | E45: 3 - CUSTOS INDIRETOS | F45: MANUTENÇÃO / TI | H45: FÁBIO
B46: 3.4.4.17 - IPTU e Taxas Municipais CIF | C46: 3.4.4.17 | D46: IPTU e Taxas Municipais CIF | E46: 3 - CUSTOS INDIRETOS | F46: FINANCEIRO | H46: LETÍCIA
B47: 3.4.4.19 - Remessa de Industrialização | C47: 3.4.4.19 | D47: Remessa de Industrialização | H47: NINGUÉM
B48: 3.4.4.3 - Salarios e Ordenados CIF | C48: 3.4.4.3 | D48: Salarios e Ordenados CIF | E48: 3 - CUSTOS INDIRETOS | F48: DH | G48: CUSTO MÃO DE OBRA DIRETA | H48: RAFAEL
B49: 3.4.4.4 - Horas Extras CIF | C49: 3.4.4.4 | D49: Horas Extras CIF | E49: 3 - CUSTOS INDIRETOS | F49: DH | G49: CUSTO MÃO DE OBRA DIRETA | H49: RAFAEL
B50: 3.4.4.6 - Gratificações CIF | C50: 3.4.4.6 | D50: Gratificações CIF | E50: 3 - CUSTOS INDIRETOS | F50: DH | G50: CUSTO MÃO DE OBRA DIRETA | H50: RAFAEL
B51: 3.4.4.7 - Rescisões CIF | C51: 3.4.4.7 | D51: Rescisões CIF | E51: 3 - CUSTOS INDIRETOS | F51: DH | H51: RAFAEL
B52: 3.4.4.9 - Seguro de Vida CIF | C52: 3.4.4.9 | D52: Seguro de Vida CIF | E52: 3 - CUSTOS INDIRETOS | F52: DH | G52: CUSTO MÃO DE OBRA DIRETA | H52: RAFAEL
B53: 3.5.1.1 - Carregamento | C53: 3.5.1.1 | D53: Carregamento | E53: 6 - DESPESA COM VENDAS | F53: LOGÍSTICA | H53: MYLENA
B54: 3.5.1.10 - Fretes Ass. Técnica | C54: 3.5.1.10 | D54: Fretes Ass. Técnica | E54: 6 - DESPESA COM VENDAS | F54: LOGÍSTICA | H54: MYLENA
B55: 3.5.1.11 - Feiras e Eventos | C55: 3.5.1.11 | D55: Feiras e Eventos | E55: 6 - DESPESA COM VENDAS | F55: COMERCIAL | H55: THAIS
B56: 3.5.1.12 - Brindes | C56: 3.5.1.12 | D56: Brindes | E56: 6 - DESPESA COM VENDAS | F56: COMERCIAL | H56: THAIS
B57: 3.5.1.13 - Viagens e Estadias c/ Vendas | C57: 3.5.1.13 | D57: Viagens e Estadias c/ Vendas | E57: 6 - DESPESA COM VENDAS | F57: COMERCIAL | H57: LETÍCIA
B58: 3.5.1.14 - Comissões sobre Vendas Interno | C58: 3.5.1.14 | D58: Comissões sobre Vendas Interno | E58: 6 - DESPESA COM VENDAS | F58: COMERCIAL | H58: LETÍCIA
B59: 3.5.1.15 - Comissões sobre Vendas Externo | C59: 3.5.1.15 | D59: Comissões sobre Vendas Externo | E59: 6 - DESPESA COM VENDAS | F59: COMERCIAL | H59: LETÍCIA
B60: 3.5.1.16 - Consultoria Comercial | C60: 3.5.1.16 | D60: Consultoria Comercial | E60: 6 - DESPESA COM VENDAS | F60: COMERCIAL | H60: LETÍCIA
B61: 3.5.1.17 - Bonificações | C61: 3.5.1.17 | D61: Bonificações | E61: 6 - DESPESA COM VENDAS | F61: COMERCIAL | H61: LETÍCIA
B62: 3.5.1.18 - Royalties | C62: 3.5.1.18 | D62: Royalties | E62: 6 - DESPESA COM VENDAS | F62: COMERCIAL | H62: LETÍCIA
B63: 3.5.1.19 - Mostruário de Tecido | C63: 3.5.1.19 | D63: Mostruário de Tecido | E63: 6 - DESPESA COM VENDAS | F63: COMERCIAL | H63: LETÍCIA
B64: 3.5.1.2 - Combustiveis Frota | C64: 3.5.1.2 | D64: Combustiveis Frota | E64: 6 - DESPESA COM VENDAS | F64: LOGÍSTICA | H64: MYLENA
... B119: 3.5.4.8 - Consultoria Tributaria | C119: 3.5.4.8 | D119: Consultoria Tributaria | E119: 7 - SERVIÇOS DE TERCEIROS | F119: FINANCEIRO | H119: LETÍCIA
B120: =COUNTA(B3:B119) -> 117
